Workbook

Sheet Instrucciones
A1: Cedears | C1: Esta planilla es gratis, igualmente te dejo mi alias por si queres ayudarme a que pueda hacer más contenido como este: luis.dd.mp
C2: Para hacer uso de la planilla, debe seleccionar en el borde izquierdo superior: Archivo - Hacer una copia
C3: Tenga en cuenta que los valores son tomados con fórmulas de información provista por Google Finance - Se actualizan cada 20 minutos
C4: Siga las instrucciones detalladas abajo para un correcto funcionamiento de la planilla. Por favor chequee la información y mire el video antes de consultar dudas
C5: La sección "cartera" no se debe tocar, se completa automáticamente con las fórmulas de "operaciones abiertas"
C6: Redes sociales Finanzas Con Luis: YouTube (FinanzasConLuisDD), Instagram (@FinanzasConLuisDD), TikTok (@FinanzasConLuisDD)
C7: Unite a la comunidad de WhatsApp: https://chat.whatsapp.com/IgPxO6cBCom3ChTJphTGGe
C8: Link al video explicativo de YouTube: https://www.youtube.com/watch?v=vLqp9A7wnqk
B10: Completar: | C10: Ticker: El ticker debe ser el que cotiza en NY. Ejemplo: Disney es DIS, no DISN. Hay muchas acciones en las que es igual, pero en caso de ver un error, puede deberse a esto. Completar en mayúscula.
C11: Broker: Seleccionar aquel en el que se hizo la operación. Esto es útil en caso de operar en más de uno.
C12: Cantidad: Número de CEDEARs comprados
A13: OPERACIONES ABIERTAS | C13: Fecha de compra: El día en que compra
C14: Dólar compra: Dólar CCL en el momento de la compra - Escribir manualmente (NO como fórmula) para evitar su actualización posterior (esto es para fijar el precio de compra). Su referencia está en la celda G2)
C15: Precio de compra: Cantidad de pesos que se pagó por cada CEDEAR
C16: Dividendos: Se debe completar a mano en caso de cobrarlos. Sirve para reflejar el verdadero rendimiento de la inversión. Puede estar vacío o en 0.
C17: Comisión + Imp: Completar las comisiones, derechos de mercado, impuestos, etc. que se pagan, de modo tal que se reflejen correctamente en el precio de compra y en el precio actual
C18: Todos los otros valores se autocompletan. No se deben tocar las otras celdas.
C20: Una vez que se venda una operación abierta en su totalidad, se debe copiar y pegar (solo valores) desde operación abierta hacia operación cerrada.
A21: OPERACIONES CERRADAS | C21: Luego, se debe borrar la línea de operaciones abiertas ya que no se tiene más la posesión de esos activos. Se recomienda borrar contenido y no borrar la fila completa.
C22: En caso que la venta sea parcial (ejemplo: compra de 100 cedears y venta de 60), se debe cambiar en el cálculo de operaciones abiertas (de 100 a 60),
C23: copiar y pegar esos valores (solo valores) y luego cambiar la cantidad en operaciones abiertas (de 60 a 40, que son las cedears que quedan sin vender)
C24: Las operaciones cerradas sirven para llevar registro del pasado. En caso de no querer llevarlo, se puede optar por no completarlo
C26: En caso de un split de acciones, se debe ajustar el precio de compra (columna H). Ejemplo: Split en 10 acciones. Debo poner = Precio de compra / 10
A27: ACLARACIONES | C27: No se puede editar esta misma planilla, debés crearte una copia en tu drive (Archivo - Crear copia). De lo contrario, todos estarían viendo tus inversiones en esta planilla
C28: La parte de dividendos se completa únicamente al cobrarlos y se puede ver en el broker. Es opcional, en caso de no completarlo, se "subestima" el rendimiento
C29: En caso de usar brokers con distintas comisiones, se puede ajustar manualmente la formula de las columnas I, L y Z o directamente colocar la comisión del broker más usado o el de comisiones más altas

Sheet CEDEARs
A1: OPERACIONES ABIERTAS | G1: Dólar CCL | H1: Comisión + Imp | T1: CARTERA
G2: ='Info CEDEARs'!J3 -> 1472.2486 | H2: 0.006
A3: Ticker | B3: Broker | C3: Cantidad | D3: Ratio | E3: Cantidad (Real) | F3: Fecha compra | G3: Dólar compra | H3: Precio compra | I3: Precio (USD) | J3: Valor compra | K3: Fecha actual | L3: Precio actual (USD) | M3: Dividendos (USD) | N3: Valor actual | O3: Días | P3: Variación (%) | Q3: Variación ($) | R3: Proporción | T3: Ticker | U3: Cantidad | V3: Ratio | W3: Cantidad (Real) | X3: Precio prom | Y3: Valor compra | Z3: Precio actual | AA3: Dividendos | AB3: Valor actual | AC3: Variación (%) | AD3: Variación ($) | AE3: Proporción cartera
A4: SPY | B4: BALANZ | C4: 1 | D4: =IF(A4=0,"...",VLOOKUP(A4,'Info CEDEARs'!$A$1:$H$340,5,0)) -> 20 | E4: =IF(A4=0,"...",C4/D4) -> 0.05 | F4: 45490 | G4: 1306 | H4: 36575 | I4: =IF(H4=0,"...",H4*(1+$H$2)/G4*D4) -> 563.46784 | J4: =IF(H4=0,"...",I4*E4) -> 28.173392 | K4: =IF(A4=0,"...",TODAY()) -> 46096 | L4: =IFERROR(__xludf.DUMMYFUNCTION("IF(A4=0, ""..."", (GOOGLEFINANCE(A4)*(1-$H$2) ))"),658.3162599999999) -> 658.31626 | N4: =IF(A4=0,"...",(L4)*E4+M4) -> 32.915813 | O4: =IF(H4=0,"...",(K4-F4)) -> 606 | P4: =IF(H4=0,"...",N4/J4-1) -> 0.16832978 | Q4: =IF(H4=0,"...",N4-J4) -> 4.742421 | R4: =IF(H4=0,"...",N4/$N$28) -> #DIV/0! | T4: {=UNIQUE($A$4:$A$27)} -> SPY | U4: =IF(T4=0, "...", SUMIF($A$4:$A$27, T4, $C$4:$C$27)) -> 1 | V4: =IF(T4=0,"...",IFERROR(VLOOKUP(T4,'Info CEDEARs'!$A$1:$H$340,5,0),1)) -> 20 | W4: =IF(T4=0,"...",U4/V4) -> 0.05 | X4: =IF(T4=0,"...",Y4/W4) -> 563.46784 | Y4: =IF(T4=0,"...",(SUMIF($A$4:$A$27,T4,$J$4:$J$27))) -> 28.173392 | Z4: =IFERROR(__xludf.DUMMYFUNCTION("IF(T4=0, ""..."", IF(W4=""No Aplica"", GOOGLEFINANCE(T4)/#REF!, IF(T4=""BBAR"", GOOGLEFINANCE(""BCBA:""&T4)/#REF!*V4, GOOGLEFINANCE(T4)*(1-$H$2)) ))"),658.3162599999999) -> 658.31626 | AA4: =IF(T4=0,"...",(SUMIF($A$4:$A$27,T4,$M$4:$M$27))) -> 0 | AB4: =IF(T4=0,"...",(SUMIF($A$4:$A$27,T4,$N$4:$N$27))) -> 32.915813 | AC4: =IF(T4=0,"...",AB4/Y4-1) -> 0.16832978 | AD4: =IF(T4=0,"...",AB4-Y4) -> 4.742421 | AE4: =IFERROR(AB4/$AB$20,0) -> 0
A5: QQQ | B5: BALANZ | C5: 1 | D5: =IF(A5=0,"...",VLOOKUP(A5,'Info CEDEARs'!$A$1:$H$340,5,0)) -> 20 | E5: =IF(A5=0,"...",C5/D5) -> 0.05 | F5: 45490 | G5: 1306 | H5: 31700 | I5: =IF(H5=0,"...",H5*(1+$H$2)/G5*D5) -> 488.36447 | J5: =IF(H5=0,"...",I5*E5) -> 24.418224 | K5: =IF(A5=0,"...",TODAY()) -> 46096 | L5: =IFERROR(__xludf.DUMMYFUNCTION("IF(A5=0, ""..."", (GOOGLEFINANCE(A5)*(1-$H$2) ))"),590.15768) -> 590.15768 | N5: =IF(A5=0,"...",(L5)*E5+M5) -> 29.507884 | O5: =IF(H5=0,"...",(K5-F5)) -> 606 | P5: =IF(H5=0,"...",N5/J5-1) -> 0.20843697 | Q5: =IF(H5=0,"...",N5-J5) -> 5.0896604 | R5: =IF(H5=0,"...",N5/$N$28) -> #DIV/0! | T5: QQQ | U5: =IF(T5=0, "...", SUMIF($A$4:$A$27, T5, $C$4:$C$27)) -> 2 | V5: =IF(T5=0,"...",IFERROR(VLOOKUP(T5,'Info CEDEARs'!$A$1:$H$340,5,0),1)) -> 20 | W5: =IF(T5=0,"...",U5/V5) -> 0.1 | X5: =IF(T5=0,"...",Y5/W5) -> 486.2317 | Y5: =IF(T5=0,"...",(SUMIF($A$4:$A$27,T5,$J$4:$J$27))) -> 48.62317 | Z5: =IFERROR(__xludf.DUMMYFUNCTION("IF(T5=0, ""..."", IF(W5=""No Aplica"", GOOGLEFINANCE(T5)/#REF!, IF(T5=""BBAR"", GOOGLEFINANCE(""BCBA:""&T5)/#REF!*V5, GOOGLEFINANCE(T5)*(1-$H$2)) ))"),590.15768) -> 590.15768 | AA5: =IF(T5=0,"...",(SUMIF($A$4:$A$27,T5,$M$4:$M$27))) -> 0 | AB5: =IF(T5=0,"...",(SUMIF($A$4:$A$27,T5,$N$4:$N$27))) -> 59.015768 | AC5: =IF(T5=0,"...",AB5/Y5-1) -> 0.21373757 | AD5: =IF(T5=0,"...",AB5-Y5) -> 10.392598 | AE5: =IFERROR(AB5/$AB$20,0) -> 0
A6: PFE | B6: BALANZ | C6: 1 | D6: =IF(A6=0,"...",VLOOKUP(A6,'Info CEDEARs'!$A$1:$H$340,5,0)) -> 4 | E6: =IF(A6=0,"...",C6/D6) -> 0.25 | F6: 45520 | G6: 1277 | H6: 9050 | I6: =IF(H6=0,"...",H6*(1+$H$2)/G6*D6) -> 28.517776 | J6: =IF(H6=0,"...",I6*E6) -> 7.129444 | K6: =IF(A6=0,"...",TODAY()) -> 46096 | L6: =IFERROR(__xludf.DUMMYFUNCTION("IF(A6=0, ""..."", (GOOGLEFINANCE(A6)*(1-$H$2) ))"),26.42052) -> 26.42052 | N6: =IF(A6=0,"...",(L6)*E6+M6) -> 6.60513 | O6: =IF(H6=0,"...",(K6-F6)) -> 576 | P6: =IF(H6=0,"...",N6/J6-1) -> -0.073542061 | Q6: =IF(H6=0,"...",N6-J6) -> -0.52431401 | R6: =IF(H6=0,"...",N6/$N$28) -> #DIV/0! | T6: PFE | U6: =IF(T6=0, "...", SUMIF($A$4:$A$27, T6, $C$4:$C$27)) -> 8 | V6: =IF(T6=0,"...",IFERROR(VLOOKUP(T6,'Info CEDEARs'!$A$1:$H$340,5,0),1)) -> 4 | W6: =IF(T6=0,"...",U6/V6) -> 2 | X6: =IF(T6=0,"...",Y6/W6) -> 29.40519 | Y6: =IF(T6=0,"...",(SUMIF($A$4:$A$27,T6,$J$4:$J$27))) -> 58.81038 | Z6: =IFERROR(__xludf.DUMMYFUNCTION("IF(T6=0, ""..."", IF(W6=""No Aplica"", GOOGLEFINANCE(T6)/#REF!, IF(T6=""BBAR"", GOOGLEFINANCE(""BCBA:""&T6)/#REF!*V6, GOOGLEFINANCE(T6)*(1-$H$2)) ))"),26.42052) -> 26.42052 | AA6: =IF(T6=0,"...",(SUMIF($A$4:$A$27,T6,$M$4:$M$27))) -> 0 | AB6: =IF(T6=0,"...",(SUMIF($A$4:$A$27,T6,$N$4:$N$27))) -> 52.84104 | AC6: =IF(T6=0,"...",AB6/Y6-1) -> -0.10150146 | AD6: =IF(T6=0,"...",AB6-Y6) -> -5.9693396 | AE6: =IFERROR(AB6/$AB$20,0) -> 0
A7: PFE | B7: BALANZ | C7: 7 | D7: =IF(A7=0,"...",VLOOKUP(A7,'Info CEDEARs'!$A$1:$H$340,5,0)) -> 4 | E7: =IF(A7=0,"...",C7/D7) -> 1.75 | F7: 45537 | G7: 1304 | H7: 9570 | I7: =IF(H7=0,"...",H7*(1+$H$2)/G7*D7) -> 29.531963 | J7: =IF(H7=0,"...",I7*E7) -> 51.680936 | K7: =IF(A7=0,"...",TODAY()) -> 46096 | L7: =IFERROR(__xludf.DUMMYFUNCTION("IF(A7=0, ""..."", (GOOGLEFINANCE(A7)*(1-$H$2) ))"),26.42052) -> 26.42052 | N7: =IF(A7=0,"...",(L7)*E7+M7) -> 46.23591 | O7: =IF(H7=0,"...",(K7-F7)) -> 559 | P7: =IF(H7=0,"...",N7/J7-1) -> -0.10535849 | Q7: =IF(H7=0,"...",N7-J7) -> -5.4450256 | R7: =IF(H7=0,"...",N7/$N$28) -> #DIV/0! | T7: TSLA | U7: =IF(T7=0, "...", SUMIF($A$4:$A$27, T7, $C$4:$C$27)) -> 6 | V7: =IF(T7=0,"...",IFERROR(VLOOKUP(T7,'Info CEDEARs'!$A$1:$H$340,5,0),1)) -> 15 | W7: =IF(T7=0,"...",U7/V7) -> 0.4 | X7: =IF(T7=0,"...",Y7/W7) -> 250.76003 | Y7: =IF(T7=0,"...",(SUMIF($A$4:$A$27,T7,$J$4:$J$27))) -> 100.30401 | Z7: =IFERROR(__xludf.DUMMYFUNCTION("IF(T7=0, ""..."", IF(W7=""No Aplica"", GOOGLEFINANCE(T7)/#REF!, IF(T7=""BBAR"", GOOGLEFINANCE(""BCBA:""&T7)/#REF!*V7, GOOGLEFINANCE(T7)*(1-$H$2)) ))"),388.8528) -> 388.8528 | AA7: =IF(T7=0,"...",(SUMIF($A$4:$A$27,T7,$M$4:$M$27))) -> 0 | AB7: =IF(T7=0,"...",(SUMIF($A$4:$A$27,T7,$N$4:$N$27))) -> 155.54112 | AC7: =IF(T7=0,"...",AB7/Y7-1) -> 0.55069691 | AD7: =IF(T7=0,"...",AB7-Y7) -> 55.237109 | AE7: =IFERROR(AB7/$AB$20,0) -> 0
A8: QQQ | B8: BALANZ | C8: 1 | D8: =IF(A8=0,"...",VLOOKUP(A8,'Info CEDEARs'!$A$1:$H$340,5,0)) -> 20 | E8: =IF(A8=0,"...",C8/D8) -> 0.05 | F8: 45537 | G8: 1304 | H8: 31375 | I8: =IF(H8=0,"...",H8*(1+$H$2)/G8*D8) -> 484.09893 | J8: =IF(H8=0,"...",I8*E8) -> 24.204946 | K8: =IF(A8=0,"...",TODAY()) -> 46096 | L8: =IFERROR(__xludf.DUMMYFUNCTION("IF(A8=0, ""..."", (GOOGLEFINANCE(A8)*(1-$H$2) ))"),590.15768) -> 590.15768 | N8: =IF(A8=0,"...",(L8)*E8+M8) -> 29.507884 | O8: =IF(H8=0,"...",(K8-F8)) -> 559 | P8: =IF(H8=0,"...",N8/J8-1) -> 0.21908488 | Q8: =IF(H8=0,"...",N8-J8) -> 5.3029377 | R8: =IF(H8=0,"...",N8/$N$28) -> #DIV/0! | T8: NU | U8: =IF(T8=0, "...", SUMIF($A$4:$A$27, T8, $C$4:$C$27)) -> 6 | V8: =IF(T8=0,"...",IFERROR(VLOOKUP(T8,'Info CEDEARs'!$A$1:$H$340,5,0),1)) | W8: =IF(T8=0,"...",U8/V8) -> #DIV/0! | X8: =IF(T8=0,"...",Y8/W8) -> #DIV/0! | Y8: =IF(T8=0,"...",(SUMIF($A$4:$A$27,T8,$J$4:$J$27))) -> 0 | Z8: =IFERROR(__xludf.DUMMYFUNCTION("IF(T8=0, ""..."", IF(W8=""No Aplica"", GOOGLEFINANCE(T8)/#REF!, IF(T8=""BBAR"", GOOGLEFINANCE(""BCBA:""&T8)/#REF!*V8, GOOGLEFINANCE(T8)*(1-$H$2)) ))"),"#DIV/0!") -> #DIV/0! | AA8: =IF(T8=0,"...",(SUMIF($A$4:$A$27,T8,$M$4:$M$27))) -> 0 | AB8: =IF(T8=0,"...",(SUMIF($A$4:$A$27,T8,$N$4:$N$27))) -> #DIV/0! | AC8: =IF(T8=0,"...",AB8/Y8-1) -> #DIV/0! | AD8: =IF(T8=0,"...",AB8-Y8) -> #DIV/0! | AE8: =IFERROR(AB8/$AB$20,0) -> 0
A9: TSLA | B9: BALANZ | C9: 4 | D9: =IF(A9=0,"...",VLOOKUP(A9,'Info CEDEARs'!$A$1:$H$340,5,0)) -> 15 | E9: =IF(A9=0,"...",C9/D9) -> 0.26666667 | F9: 45729 | G9: 1235 | H9: 19450 | I9: =IF(H9=0,"...",H9*(1+$H$2)/G9*D9) -> 237.65223 | J9: =IF(H9=0,"...",I9*E9) -> 63.373927 | K9: =IF(A9=0,"...",TODAY()) -> 46096 | L9: =IFERROR(__xludf.DUMMYFUNCTION("IF(A9=0, ""..."", (GOOGLEFINANCE(A9)*(1-$H$2) ))"),388.8528) -> 388.8528 | N9: =IF(A9=0,"...",(L9)*E9+M9) -> 103.69408 | O9: =IF(H9=0,"...",(K9-F9)) -> 367 | P9: =IF(H9=0,"...",N9/J9-1) -> 0.6362262 | Q9: =IF(H9=0,"...",N9-J9) -> 40.320153 | R9: =IF(H9=0,"...",N9/$N$28) -> #DIV/0! | U9: =IF(T9=0, "...", SUMIF($A$4:$A$27, T9, $C$4:$C$27)) -> ... | V9: =IF(T9=0,"...",IFERROR(VLOOKUP(T9,'Info CEDEARs'!$A$1:$H$340,5,0),1)) -> ... | W9: =IF(T9=0,"...",U9/V9) -> ... | X9: =IF(T9=0,"...",Y9/W9) -> ... | Y9: =IF(T9=0,"...",(SUMIF($A$4:$A$27,T9,$J$4:$J$27))) -> ... | Z9: =IFERROR(__xludf.DUMMYFUNCTION("IF(T9=0, ""..."", IF(W9=""No Aplica"", GOOGLEFINANCE(T9)/#REF!, IF(T9=""BBAR"", GOOGLEFINANCE(""BCBA:""&T9)/#REF!*V9, GOOGLEFINANCE(T9)*(1-$H$2)) ))"),"...") -> ... | AA9: =IF(T9=0,"...",(SUMIF($A$4:$A$27,T9,$M$4:$M$27))) -> ... | AB9: =IF(T9=0,"...",(SUMIF($A$4:$A$27,T9,$N$4:$N$27))) -> ... | AC9: =IF(T9=0,"...",AB9/Y9-1) -> ... | AD9: =IF(T9=0,"...",AB9-Y9) -> ... | AE9: =IFERROR(AB9/$AB$20,0) -> 0
A10: TSLA | B10: BALANZ | C10: 2 | D10: =IF(A10=0,"...",VLOOKUP(A10,'Info CEDEARs'!$A$1:$H$340,5,0)) -> 15 | E10: =IF(A10=0,"...",C10/D10) -> 0.13333333 | F10: Abr 1, 2025 | G10: 1313 | H10: 24100 | I10: =IF(H10=0,"...",H10*(1+$H$2)/G10*D10) -> 276.97563 | J10: =IF(H10=0,"...",I10*E10) -> 36.930084 | K10: =IF(A10=0,"...",TODAY()) -> 46096 | L10: =IFERROR(__xludf.DUMMYFUNCTION("IF(A10=0, ""..."", (GOOGLEFINANCE(A10)*(1-$H$2) ))"),388.8528) -> 388.8528 | N10: =IF(A10=0,"...",(L10)*E10+M10) -> 51.84704 | O10: =IF(H10=0,"...",(K10-F10)) -> #VALUE! | P10: =IF(H10=0,"...",N10/J10-1) -> 0.40392425 | Q10: =IF(H10=0,"...",N10-J10) -> 14.916956 | R10: =IF(H10=0,"...",N10/$N$28) -> #DIV/0! | U10: =IF(T10=0, "...", SUMIF($A$4:$A$27, T10, $C$4:$C$27)) -> ... | V10: =IF(T10=0,"...",IFERROR(VLOOKUP(T10,'Info CEDEARs'!$A$1:$H$340,5,0),1)) -> ... | W10: =IF(T10=0,"...",U10/V10) -> ... | X10: =IF(T10=0,"...",Y10/W10) -> ... | Y10: =IF(T10=0,"...",(SUMIF($A$4:$A$27,T10,$J$4:$J$27))) -> ... | Z10: =IFERROR(__xludf.DUMMYFUNCTION("IF(T10=0, ""..."", IF(W10=""No Aplica"", GOOGLEFINANCE(T10)/#REF!, IF(T10=""BBAR"", GOOGLEFINANCE(""BCBA:""&T10)/#REF!*V10, GOOGLEFINANCE(T10)*(1-$H$2)) ))"),"...") -> ... | AA10: =IF(T10=0,"...",(SUMIF($A$4:$A$27,T10,$M$4:$M$27))) -> ... | AB10: =IF(T10=0,"...",(SUMIF($A$4:$A$27,T10,$N$4:$N$27))) -> ... | AC10: =IF(T10=0,"...",AB10/Y10-1) -> ... | AD10: =IF(T10=0,"...",AB10-Y10) -> ... | AE10: =IFERROR(AB10/$AB$20,0) -> 0
A11: NU | B11: BALANZ | C11: 6 | D11: =IF(A11=0,"...",VLOOKUP(A11,'Info CEDEARs'!$A$1:$H$340,5,0)) | E11: =IF(A11=0,"...",C11/D11) -> #DIV/0! | I11: =IF(H11=0,"...",H11*(1+$H$2)/G11*D11) -> ... | J11: =IF(H11=0,"...",I11*E11) -> ... | K11: =IF(A11=0,"...",TODAY()) -> 46096 | L11: =IFERROR(__xludf.DUMMYFUNCTION("IF(A11=0, ""..."", (GOOGLEFINANCE(A11)*(1-$H$2) ))"),13.80666) -> 13.80666 | N11: =IF(A11=0,"...",(L11)*E11+M11) -> #DIV/0! | O11: =IF(H11=0,"...",(K11-F11)) -> ... | P11: =IF(H11=0,"...",N11/J11-1) -> ... | Q11: =IF(H11=0,"...",N11-J11) -> ... | R11: =IF(H11=0,"...",N11/$N$28) -> ... | U11: =IF(T11=0, "...", SUMIF($A$4:$A$27, T11, $C$4:$C$27)) -> ... | V11: =IF(T11=0,"...",IFERROR(VLOOKUP(T11,'Info CEDEARs'!$A$1:$H$340,5,0),1)) -> ... | W11: =IF(T11=0,"...",U11/V11) -> ... | X11: =IF(T11=0,"...",Y11/W11) -> ... | Y11: =IF(T11=0,"...",(SUMIF($A$4:$A$27,T11,$J$4:$J$27))) -> ... | Z11: =IFERROR(__xludf.DUMMYFUNCTION("IF(T11=0, ""..."", IF(W11=""No Aplica"", GOOGLEFINANCE(T11)/#REF!, IF(T11=""BBAR"", GOOGLEFINANCE(""BCBA:""&T11)/#REF!*V11, GOOGLEFINANCE(T11)*(1-$H$2)) ))"),"...") -> ... | AA11: =IF(T11=0,"...",(SUMIF($A$4:$A$27,T11,$M$4:$M$27))) -> ... | AB11: =IF(T11=0,"...",(SUMIF($A$4:$A$27,T11,$N$4:$N$27))) -> ... | AC11: =IF(T11=0,"...",AB11/Y11-1) -> ... | AD11: =IF(T11=0,"...",AB11-Y11) -> ... | AE11: =IFERROR(AB11/$AB$20,0) -> 0
D12: =IF(A12=0,"...",VLOOKUP(A12,'Info CEDEARs'!$A$1:$H$340,5,0)) -> ... | E12: =IF(A12=0,"...",C12/D12) -> ... | I12: =IF(H12=0,"...",H12*(1+$H$2)/G12*D12) -> ... | J12: =IF(H12=0,"...",I12*E12) -> ... | K12: =IF(A12=0,"...",TODAY()) -> ... | L12: =IFERROR(__xludf.DUMMYFUNCTION("IF(A12=0, ""..."", (GOOGLEFINANCE(A12)*(1-$H$2) ))"),"...") -> ... | N12: =IF(A12=0,"...",(L12)*E12+M12) -> ... | O12: =IF(H12=0,"...",(K12-F12)) -> ... | P12: =IF(H12=0,"...",N12/J12-1) -> ... | Q12: =IF(H12=0,"...",N12-J12) -> ... | R12: =IF(H12=0,"...",N12/$N$28) -> ... | U12: =IF(T12=0, "...", SUMIF($A$4:$A$27, T12, $C$4:$C$27)) -> ... | V12: =IF(T12=0,"...",IFERROR(VLOOKUP(T12,'Info CEDEARs'!$A$1:$H$340,5,0),1)) -> ... | W12: =IF(T12=0,"...",U12/V12) -> ... | X12: =IF(T12=0,"...",Y12/W12) -> ... | Y12: =IF(T12=0,"...",(SUMIF($A$4:$A$27,T12,$J$4:$J$27))) -> ... | Z12: =IFERROR(__xludf.DUMMYFUNCTION("IF(T12=0, ""..."", IF(W12=""No Aplica"", GOOGLEFINANCE(T12)/#REF!, IF(T12=""BBAR"", GOOGLEFINANCE(""BCBA:""&T12)/#REF!*V12, GOOGLEFINANCE(T12)*(1-$H$2)) ))"),"...") -> ... | AA12: =IF(T12=0,"...",(SUMIF($A$4:$A$27,T12,$M$4:$M$27))) -> ... | AB12: =IF(T12=0,"...",(SUMIF($A$4:$A$27,T12,$N$4:$N$27))) -> ... | AC12: =IF(T12=0,"...",AB12/Y12-1) -> ... | AD12: =IF(T12=0,"...",AB12-Y12) -> ... | AE12: =IFERROR(AB12/$AB$20,0) -> 0
D13: =IF(A13=0,"...",VLOOKUP(A13,'Info CEDEARs'!$A$1:$H$340,5,0)) -> ... | E13: =IF(A13=0,"...",C13/D13) -> ... | I13: =IF(H13=0,"...",H13*(1+$H$2)/G13*D13) -> ... | J13: =IF(H13=0,"...",I13*E13) -> ... | K13: =IF(A13=0,"...",TODAY()) -> ... | L13: =IFERROR(__xludf.DUMMYFUNCTION("IF(A13=0, ""..."", (GOOGLEFINANCE(A13)*(1-$H$2) ))"),"...") -> ... | N13: =IF(A13=0,"...",(L13)*E13+M13) -> ... | O13: =IF(H13=0,"...",(K13-F13)) -> ... | P13: =IF(H13=0,"...",N13/J13-1) -> ... | Q13: =IF(H13=0,"...",N13-J13) -> ... | R13: =IF(H13=0,"...",N13/$N$28) -> ... | U13: =IF(T13=0, "...", SUMIF($A$4:$A$27, T13, $C$4:$C$27)) -> ... | V13: =IF(T13=0,"...",IFERROR(VLOOKUP(T13,'Info CEDEARs'!$A$1:$H$340,5,0),1)) -> ... | W13: =IF(T13=0,"...",U13/V13) -> ... | X13: =IF(T13=0,"...",Y13/W13) -> ... | Y13: =IF(T13=0,"...",(SUMIF($A$4:$A$27,T13,$J$4:$J$27))) -> ... | Z13: =IFERROR(__xludf.DUMMYFUNCTION("IF(T13=0, ""..."", IF(W13=""No Aplica"", GOOGLEFINANCE(T13)/#REF!, IF(T13=""BBAR"", GOOGLEFINANCE(""BCBA:""&T13)/#REF!*V13, GOOGLEFINANCE(T13)*(1-$H$2)) ))"),"...") -> ... | AA13: =IF(T13=0,"...",(SUMIF($A$4:$A$27,T13,$M$4:$M$27))) -> ... | AB13: =IF(T13=0,"...",(SUMIF($A$4:$A$27,T13,$N$4:$N$27))) -> ... | AC13: =IF(T13=0,"...",AB13/Y13-1) -> ... | AD13: =IF(T13=0,"...",AB13-Y13) -> ... | AE13: =IFERROR(AB13/$AB$20,0) -> 0
D14: =IF(A14=0,"...",VLOOKUP(A14,'Info CEDEARs'!$A$1:$H$340,5,0)) -> ... | E14: =IF(A14=0,"...",C14/D14) -> ... | I14: =IF(H14=0,"...",H14*(1+$H$2)/G14*D14) -> ... | J14: =IF(H14=0,"...",I14*E14) -> ... | K14: =IF(A14=0,"...",TODAY()) -> ... | L14: =IFERROR(__xludf.DUMMYFUNCTION("IF(A14=0, ""..."", (GOOGLEFINANCE(A14)*(1-$H$2) ))"),"...") -> ... | N14: =IF(A14=0,"...",(L14)*E14+M14) -> ... | O14: =IF(H14=0,"...",(K14-F14)) -> ... | P14: =IF(H14=0,"...",N14/J14-1) -> ... | Q14: =IF(H14=0,"...",N14-J14) -> ... | R14: =IF(H14=0,"...",N14/$N$28) -> ... | U14: =IF(T14=0, "...", SUMIF($A$4:$A$27, T14, $C$4:$C$27)) -> ... | V14: =IF(T14=0,"...",IFERROR(VLOOKUP(T14,'Info CEDEARs'!$A$1:$H$340,5,0),1)) -> ... | W14: =IF(T14=0,"...",U14/V14) -> ... | X14: =IF(T14=0,"...",Y14/W14) -> ... | Y14: =IF(T14=0,"...",(SUMIF($A$4:$A$27,T14,$J$4:$J$27))) -> ... | Z14: =IFERROR(__xludf.DUMMYFUNCTION("IF(T14=0, ""..."", IF(W14=""No Aplica"", GOOGLEFINANCE(T14)/#REF!, IF(T14=""BBAR"", GOOGLEFINANCE(""BCBA:""&T14)/#REF!*V14, GOOGLEFINANCE(T14)*(1-$H$2)) ))"),"...") -> ... | AA14: =IF(T14=0,"...",(SUMIF($A$4:$A$27,T14,$M$4:$M$27))) -> ... | AB14: =IF(T14=0,"...",(SUMIF($A$4:$A$27,T14,$N$4:$N$27))) -> ... | AC14: =IF(T14=0,"...",AB14/Y14-1) -> ... | AD14: =IF(T14=0,"...",AB14-Y14) -> ... | AE14: =IFERROR(AB14/$AB$20,0) -> 0
D15: =IF(A15=0,"...",VLOOKUP(A15,'Info CEDEARs'!$A$1:$H$340,5,0)) -> ... | E15: =IF(A15=0,"...",C15/D15) -> ... | I15: =IF(H15=0,"...",H15*(1+$H$2)/G15*D15) -> ... | J15: =IF(H15=0,"...",I15*E15) -> ... | K15: =IF(A15=0,"...",TODAY()) -> ... | L15: =IFERROR(__xludf.DUMMYFUNCTION("IF(A15=0, ""..."", (GOOGLEFINANCE(A15)*(1-$H$2) ))"),"...") -> ... | N15: =IF(A15=0,"...",(L15)*E15+M15) -> ... | O15: =IF(H15=0,"...",(K15-F15)) -> ... | P15: =IF(H15=0,"...",N15/J15-1) -> ... | Q15: =IF(H15=0,"...",N15-J15) -> ... | R15: =IF(H15=0,"...",N15/$N$28) -> ... | U15: =IF(T15=0, "...", SUMIF($A$4:$A$27, T15, $C$4:$C$27)) -> ... | V15: =IF(T15=0,"...",IFERROR(VLOOKUP(T15,'Info CEDEARs'!$A$1:$H$340,5,0),1)) -> ... | W15: =IF(T15=0,"...",U15/V15) -> ... | X15: =IF(T15=0,"...",Y15/W15) -> ... | Y15: =IF(T15=0,"...",(SUMIF($A$4:$A$27,T15,$J$4:$J$27))) -> ... | Z15: =IFERROR(__xludf.DUMMYFUNCTION("IF(T15=0, ""..."", IF(W15=""No Aplica"", GOOGLEFINANCE(T15)/#REF!, IF(T15=""BBAR"", GOOGLEFINANCE(""BCBA:""&T15)/#REF!*V15, GOOGLEFINANCE(T15)*(1-$H$2)) ))"),"...") -> ... | AA15: =IF(T15=0,"...",(SUMIF($A$4:$A$27,T15,$M$4:$M$27))) -> ... | AB15: =IF(T15=0,"...",(SUMIF($A$4:$A$27,T15,$N$4:$N$27))) -> ... | AC15: =IF(T15=0,"...",AB15/Y15-1) -> ... | AD15: =IF(T15=0,"...",AB15-Y15) -> ... | AE15: =IFERROR(AB15/$AB$20,0) -> 0
D16: =IF(A16=0,"...",VLOOKUP(A16,'Info CEDEARs'!$A$1:$H$340,5,0)) -> ... | E16: =IF(A16=0,"...",C16/D16) -> ... | I16: =IF(H16=0,"...",H16*(1+$H$2)/G16*D16) -> ... | J16: =IF(H16=0,"...",I16*E16) -> ... | K16: =IF(A16=0,"...",TODAY()) -> ... | L16: =IFERROR(__xludf.DUMMYFUNCTION("IF(A16=0, ""..."", (GOOGLEFINANCE(A16)*(1-$H$2) ))"),"...") -> ... | N16: =IF(A16=0,"...",(L16)*E16+M16) -> ... | O16: =IF(H16=0,"...",(K16-F16)) -> ... | P16: =IF(H16=0,"...",N16/J16-1) -> ... | Q16: =IF(H16=0,"...",N16-J16) -> ... | R16: =IF(H16=0,"...",N16/$N$28) -> ... | U16: =IF(T16=0, "...", SUMIF($A$4:$A$27, T16, $C$4:$C$27)) -> ... | V16: =IF(T16=0,"...",IFERROR(VLOOKUP(T16,'Info CEDEARs'!$A$1:$H$340,5,0),1)) -> ... | W16: =IF(T16=0,"...",U16/V16) -> ... | X16: =IF(T16=0,"...",Y16/W16) -> ... | Y16: =IF(T16=0,"...",(SUMIF($A$4:$A$27,T16,$J$4:$J$27))) -> ... | Z16: =IFERROR(__xludf.DUMMYFUNCTION("IF(T16=0, ""..."", IF(W16=""No Aplica"", GOOGLEFINANCE(T16)/#REF!, IF(T16=""BBAR"", GOOGLEFINANCE(""BCBA:""&T16)/#REF!*V16, GOOGLEFINANCE(T16)*(1-$H$2)) ))"),"...") -> ... | AA16: =IF(T16=0,"...",(SUMIF($A$4:$A$27,T16,$M$4:$M$27))) -> ... | AB16: =IF(T16=0,"...",(SUMIF($A$4:$A$27,T16,$N$4:$N$27))) -> ... | AC16: =IF(T16=0,"...",AB16/Y16-1) -> ... | AD16: =IF(T16=0,"...",AB16-Y16) -> ... | AE16: =IFERROR(AB16/$AB$20,0) -> 0
D17: =IF(A17=0,"...",VLOOKUP(A17,'Info CEDEARs'!$A$1:$H$340,5,0)) -> ... | E17: =IF(A17=0,"...",C17/D17) -> ... | I17: =IF(H17=0,"...",H17*(1+$H$2)/G17*D17) -> ... | J17: =IF(H17=0,"...",I17*E17) -> ... | K17: =IF(A17=0,"...",TODAY()) -> ... | L17: =IFERROR(__xludf.DUMMYFUNCTION("IF(A17=0, ""..."", (GOOGLEFINANCE(A17)*(1-$H$2) ))"),"...") -> ... | N17: =IF(A17=0,"...",(L17)*E17+M17) -> ... | O17: =IF(H17=0,"...",(K17-F17)) -> ... | P17: =IF(H17=0,"...",N17/J17-1) -> ... | Q17: =IF(H17=0,"...",N17-J17) -> ... | R17: =IF(H17=0,"...",N17/$N$28) -> ... | U17: =IF(T17=0, "...", SUMIF($A$4:$A$27, T17, $C$4:$C$27)) -> ... | V17: =IF(T17=0,"...",IFERROR(VLOOKUP(T17,'Info CEDEARs'!$A$1:$H$340,5,0),1)) -> ... | W17: =IF(T17=0,"...",U17/V17) -> ... | X17: =IF(T17=0,"...",Y17/W17) -> ... | Y17: =IF(T17=0,"...",(SUMIF($A$4:$A$27,T17,$J$4:$J$27))) -> ... | Z17: =IFERROR(__xludf.DUMMYFUNCTION("IF(T17=0, ""..."", IF(W17=""No Aplica"", GOOGLEFINANCE(T17)/#REF!, IF(T17=""BBAR"", GOOGLEFINANCE(""BCBA:""&T17)/#REF!*V17, GOOGLEFINANCE(T17)*(1-$H$2)) ))"),"...") -> ... | AA17: =IF(T17=0,"...",(SUMIF($A$4:$A$27,T17,$M$4:$M$27))) -> ... | AB17: =IF(T17=0,"...",(SUMIF($A$4:$A$27,T17,$N$4:$N$27))) -> ... | AC17: =IF(T17=0,"...",AB17/Y17-1) -> ... | AD17: =IF(T17=0,"...",AB17-Y17) -> ... | AE17: =IFERROR(AB17/$AB$20,0) -> 0
D18: =IF(A18=0,"...",VLOOKUP(A18,'Info CEDEARs'!$A$1:$H$340,5,0)) -> ... | E18: =IF(A18=0,"...",C18/D18) -> ... | I18: =IF(H18=0,"...",H18*(1+$H$2)/G18*D18) -> ... | J18: =IF(H18=0,"...",I18*E18) -> ... | K18: =IF(A18=0,"...",TODAY()) -> ... | L18: =IFERROR(__xludf.DUMMYFUNCTION("IF(A18=0, ""..."", (GOOGLEFINANCE(A18)*(1-$H$2) ))"),"...") -> ... | N18: =IF(A18=0,"...",(L18)*E18+M18) -> ... | O18: =IF(H18=0,"...",(K18-F18)) -> ... | P18: =IF(H18=0,"...",N18/J18-1) -> ... | Q18: =IF(H18=0,"...",N18-J18) -> ... | R18: =IF(H18=0,"...",N18/$N$28) -> ... | U18: =IF(T18=0, "...", SUMIF($A$4:$A$27, T18, $C$4:$C$27)) -> ... | V18: =IF(T18=0,"...",IFERROR(VLOOKUP(T18,'Info CEDEARs'!$A$1:$H$340,5,0),1)) -> ... | W18: =IF(T18=0,"...",U18/V18) -> ... | X18: =IF(T18=0,"...",Y18/W18) -> ... | Y18: =IF(T18=0,"...",(SUMIF($A$4:$A$27,T18,$J$4:$J$27))) -> ... | Z18: =IFERROR(__xludf.DUMMYFUNCTION("IF(T18=0, ""..."", IF(W18=""No Aplica"", GOOGLEFINANCE(T18)/#REF!, IF(T18=""BBAR"", GOOGLEFINANCE(""BCBA:""&T18)/#REF!*V18, GOOGLEFINANCE(T18)*(1-$H$2)) ))"),"...") -> ... | AA18: =IF(T18=0,"...",(SUMIF($A$4:$A$27,T18,$M$4:$M$27))) -> ... | AB18: =IF(T18=0,"...",(SUMIF($A$4:$A$27,T18,$N$4:$N$27))) -> ... | AC18: =IF(T18=0,"...",AB18/Y18-1) -> ... | AD18: =IF(T18=0,"...",AB18-Y18) -> ... | AE18: =IFERROR(AB18/$AB$20,0) -> 0
D19: =IF(A19=0,"...",VLOOKUP(A19,'Info CEDEARs'!$A$1:$H$340,5,0)) -> ... | E19: =IF(A19=0,"...",C19/D19) -> ... | I19: =IF(H19=0,"...",H19*(1+$H$2)/G19*D19) -> ... | J19: =IF(H19=0,"...",I19*E19) -> ... | K19: =IF(A19=0,"...",TODAY()) -> ... | L19: =IFERROR(__xludf.DUMMYFUNCTION("IF(A19=0, ""..."", (GOOGLEFINANCE(A19)*(1-$H$2) ))"),"...") -> ... | N19: =IF(A19=0,"...",(L19)*E19+M19) -> ... | O19: =IF(H19=0,"...",(K19-F19)) -> ... | P19: =IF(H19=0,"...",N19/J19-1) -> ... | Q19: =IF(H19=0,"...",N19-J19) -> ... | R19: =IF(H19=0,"...",N19/$N$28) -> ... | U19: =IF(T19=0, "...", SUMIF($A$4:$A$27, T19, $C$4:$C$27)) -> ... | V19: =IF(T19=0,"...",IFERROR(VLOOKUP(T19,'Info CEDEARs'!$A$1:$H$340,5,0),1)) -> ... | W19: =IF(T19=0,"...",U19/V19) -> ... | X19: =IF(T19=0,"...",Y19/W19) -> ... | Y19: =IF(T19=0,"...",(SUMIF($A$4:$A$27,T19,$J$4:$J$27))) -> ... | Z19: =IFERROR(__xludf.DUMMYFUNCTION("IF(T19=0, ""..."", IF(W19=""No Aplica"", GOOGLEFINANCE(T19)/#REF!, IF(T19=""BBAR"", GOOGLEFINANCE(""BCBA:""&T19)/#REF!*V19, GOOGLEFINANCE(T19)*(1-$H$2)) ))"),"...") -> ... | AA19: =IF(T19=0,"...",(SUMIF($A$4:$A$27,T19,$M$4:$M$27))) -> ... | AB19: =IF(T19=0,"...",(SUMIF($A$4:$A$27,T19,$N$4:$N$27))) -> ... | AC19: =IF(T19=0,"...",AB19/Y19-1) -> ... | AD19: =IF(T19=0,"...",AB19-Y19) -> ... | AE19: =IFERROR(AB19/$AB$20,0) -> 0
D20: =IF(A20=0,"...",VLOOKUP(A20,'Info CEDEARs'!$A$1:$H$340,5,0)) -> ... | E20: =IF(A20=0,"...",C20/D20) -> ... | I20: =IF(H20=0,"...",H20*(1+$H$2)/G20*D20) -> ... | J20: =IF(H20=0,"...",I20*E20) -> ... | K20: =IF(A20=0,"...",TODAY()) -> ... | L20: =IFERROR(__xludf.DUMMYFUNCTION("IF(A20=0, ""..."", (GOOGLEFINANCE(A20)*(1-$H$2) ))"),"...") -> ... | N20: =IF(A20=0,"...",(L20)*E20+M20) -> ... | O20: =IF(H20=0,"...",(K20-F20)) -> ... | P20: =IF(H20=0,"...",N20/J20-1) -> ... | Q20: =IF(H20=0,"...",N20-J20) -> ... | R20: =IF(H20=0,"...",N20/$N$28) -> ... | T20: TOTAL | Y20: =IF(SUM(Y$4:Y19)=0,"...",SUM(Y$4:Y19)) -> 235.91095 | AA20: =IF(Y20="...","...",SUM($AB$4:$AB19)) -> #DIV/0! | AB20: =IF(Y20="...","...",SUM($AB$4:$AB19)) -> #DIV/0! | AC20: =IF(Y20="...","...",AB20/Y20-1) -> #DIV/0! | AD20: =IF(Y20="...","...",SUM(AD$4:AD19)) -> #DIV/0! | AE20: =IF(Y20="...","...",AB20/AB20) -> #DIV/0!
D21: =IF(A21=0,"...",VLOOKUP(A21,'Info CEDEARs'!$A$1:$H$340,5,0)) -> ... | E21: =IF(A21=0,"...",C21/D21) -> ... | I21: =IF(H21=0,"...",H21*(1+$H$2)/G21*D21) -> ... | J21: =IF(H21=0,"...",I21*E21) -> ... | K21: =IF(A21=0,"...",TODAY()) -> ... | L21: =IFERROR(__xludf.DUMMYFUNCTION("IF(A21=0, ""..."", (GOOGLEFINANCE(A21)*(1-$H$2) ))"),"...") -> ... | N21: =IF(A21=0,"...",(L21)*E21+M21) -> ... | O21: =IF(H21=0,"...",(K21-F21)) -> ... | P21: =IF(H21=0,"...",N21/J21-1) -> ... | Q21: =IF(H21=0,"...",N21-J21) -> ... | R21: =IF(H21=0,"...",N21/$N$28) -> ...
D22: =IF(A22=0,"...",VLOOKUP(A22,'Info CEDEARs'!$A$1:$H$340,5,0)) -> ... | E22: =IF(A22=0,"...",C22/D22) -> ... | I22: =IF(H22=0,"...",H22*(1+$H$2)/G22*D22) -> ... | J22: =IF(H22=0,"...",I22*E22) -> ... | K22: =IF(A22=0,"...",TODAY()) -> ... | L22: =IFERROR(__xludf.DUMMYFUNCTION("IF(A22=0, ""..."", (GOOGLEFINANCE(A22)*(1-$H$2) ))"),"...") -> ... | N22: =IF(A22=0,"...",(L22)*E22+M22) -> ... | O22: =IF(H22=0,"...",(K22-F22)) -> ... | P22: =IF(H22=0,"...",N22/J22-1) -> ... | Q22: =IF(H22=0,"...",N22-J22) -> ... | R22: =IF(H22=0,"...",N22/$N$28) -> ...
D23: =IF(A23=0,"...",VLOOKUP(A23,'Info CEDEARs'!$A$1:$H$340,5,0)) -> ... | E23: =IF(A23=0,"...",C23/D23) -> ... | I23: =IF(H23=0,"...",H23*(1+$H$2)/G23*D23) -> ... | J23: =IF(H23=0,"...",I23*E23) -> ... | K23: =IF(A23=0,"...",TODAY()) -> ... | L23: =IFERROR(__xludf.DUMMYFUNCTION("IF(A23=0, ""..."", (GOOGLEFINANCE(A23)*(1-$H$2) ))"),"...") -> ... | N23: =IF(A23=0,"...",(L23)*E23+M23) -> ... | O23: =IF(H23=0,"...",(K23-F23)) -> ... | P23: =IF(H23=0,"...",N23/J23-1) -> ... | Q23: =IF(H23=0,"...",N23-J23) -> ... | R23: =IF(H23=0,"...",N23/$N$28) -> ...
D24: =IF(A24=0,"...",VLOOKUP(A24,'Info CEDEARs'!$A$1:$H$340,5,0)) -> ... | E24: =IF(A24=0,"...",C24/D24) -> ... | I24: =IF(H24=0,"...",H24*(1+$H$2)/G24*D24) -> ... | J24: =IF(H24=0,"...",I24*E24) -> ... | K24: =IF(A24=0,"...",TODAY()) -> ... | L24: =IFERROR(__xludf.DUMMYFUNCTION("IF(A24=0, ""..."", (GOOGLEFINANCE(A24)*(1-$H$2) ))"),"...") -> ... | N24: =IF(A24=0,"...",(L24)*E24+M24) -> ... | O24: =IF(H24=0,"...",(K24-F24)) -> ... | P24: =IF(H24=0,"...",N24/J24-1) -> ... | Q24: =IF(H24=0,"...",N24-J24) -> ... | R24: =IF(H24=0,"...",N24/$N$28) -> ...
D25: =IF(A25=0,"...",VLOOKUP(A25,'Info CEDEARs'!$A$1:$H$340,5,0)) -> ... | E25: =IF(A25=0,"...",C25/D25) -> ... | I25: =IF(H25=0,"...",H25*(1+$H$2)/G25*D25) -> ... | J25: =IF(H25=0,"...",I25*E25) -> ... | K25: =IF(A25=0,"...",TODAY()) -> ... | L25: =IFERROR(__xludf.DUMMYFUNCTION("IF(A25=0, ""..."", (GOOGLEFINANCE(A25)*(1-$H$2) ))"),"...") -> ... | N25: =IF(A25=0,"...",(L25)*E25+M25) -> ... | O25: =IF(H25=0,"...",(K25-F25)) -> ... | P25: =IF(H25=0,"...",N25/J25-1) -> ... | Q25: =IF(H25=0,"...",N25-J25) -> ... | R25: =IF(H25=0,"...",N25/$N$28) -> ...
D26: =IF(A26=0,"...",VLOOKUP(A26,'Info CEDEARs'!$A$1:$H$340,5,0)) -> ... | E26: =IF(A26=0,"...",C26/D26) -> ... | I26: =IF(H26=0,"...",H26*(1+$H$2)/G26*D26) -> ... | J26: =IF(H26=0,"...",I26*E26) -> ... | K26: =IF(A26=0,"...",TODAY()) -> ... | L26: =IFERROR(__xludf.DUMMYFUNCTION("IF(A26=0, ""..."", (GOOGLEFINANCE(A26)*(1-$H$2) ))"),"...") -> ... | N26: =IF(A26=0,"...",(L26)*E26+M26) -> ... | O26: =IF(H26=0,"...",(K26-F26)) -> ... | P26: =IF(H26=0,"...",N26/J26-1) -> ... | Q26: =IF(H26=0,"...",N26-J26) -> ... | R26: =IF(H26=0,"...",N26/$N$28) -> ...
D27: =IF(A27=0,"...",VLOOKUP(A27,'Info CEDEARs'!$A$1:$H$340,5,0)) -> ... | E27: =IF(A27=0,"...",C27/D27) -> ... | I27: =IF(H27=0,"...",H27*(1+$H$2)/G27*D27) -> ... | J27: =IF(H27=0,"...",I27*E27) -> ... | K27: =IF(A27=0,"...",TODAY()) -> ... | L27: =IFERROR(__xludf.DUMMYFUNCTION("IF(A27=0, ""..."", (GOOGLEFINANCE(A27)*(1-$H$2) ))"),"...") -> ... | N27: =IF(A27=0,"...",(L27)*E27+M27) -> ... | O27: =IF(H27=0,"...",(K27-F27)) -> ... | P27: =IF(H27=0,"...",N27/J27-1) -> ... | Q27: =IF(H27=0,"...",N27-J27) -> ... | R27: =IF(H27=0,"...",N27/$N$28) -> ...
A28: TOTAL | J28: =IF(SUM(J$4:J27)=0,"...",SUM(J$4:J27)) -> 235.91095 | M28: =IF(J28="...","...",SUM(M$4:M27)) -> 0 | N28: =IF(J28="...","...",SUM(N$4:N27)) -> #DIV/0! | P28: =IF(J28="...","...",N28/J28-1) -> #DIV/0! | Q28: =IF(J28="...","...",SUM(Q$4:Q27)) -> 64.402789 | R28: =IF(J28="...","...",N28/N28) -> #DIV/0!
A31: OPERACIONES CERRADAS
A33: Ticker | B33: Broker | C33: Cantidad | D33: Ratio | E33: Cantidad (Real) | F33: Fecha compra | G33: Dólar compra | H33: Precio compra | I33: Precio (USD) | J33: Valor compra | K33: Fecha cierre | L33: Precio cierre (USD) | M33: Dividendos | N33: Valor actual | O33: Días | P33: Variación (%) | Q33: Variación ($)
A57: TOTAL | J57: =IF(SUM(J$34:J56)=0,"...",SUM(J$34:J56)) -> ... | N57: =IF(J57="...","...",SUM(N$34:N56)) -> ... | P57: =IF(J57="...","...",N57/J57-1) -> ... | Q57: =IF(J57="...","...",SUM(Q$34:Q56)) -> ...

Sheet Info CEDEARs
A1: Ticker US | B1: Ticker AR | C1: Precio USD | D1: Precio ARS | E1: Ratio | F1: Dolar CCL | G1: Diferencia Promedio($) | H1: Diferencia Promedio(%) | J1: Dolar CCL Promedio
A2: SPY | B2: SPY | C2: =IFERROR(__xludf.DUMMYFUNCTION("IFERROR(googlefinance(A2),""No Disponible"")"),662.29) -> 662.29 | D2: =iferror(vlookup(A2,'Info Pesos'!$A$1:N453,2,0),"No Disponible") -> 15.25 | E2: 20 | F2: =IF(C2=0, "...", IF(C2="No Disponible", "No Disponible", IF(D2="No Disponible", "No Disponible", IF(A2=0, "...", D2/C2*E2)))) -> 0.46052334 | G2: =IFERROR(F2-$J$3,"No Disponible") -> -1471.7881 | H2: =IFERROR(IF(A2= 0,"...",(F2-$J$3)/$J$3),"No Disponible") -> -0.9996872
A3: QQQ | B3: QQQ | C3: =IFERROR(__xludf.DUMMYFUNCTION("IFERROR(googlefinance(A3),""No Disponible"")"),593.72) -> 593.72 | D3: =iferror(vlookup(A3,'Info Pesos'!$A$1:N454,2,0),"No Disponible") -> 23,730.00 | E3: 20 | F3: =IF(C3=0, "...", IF(C3="No Disponible", "No Disponible", IF(D3="No Disponible", "No Disponible", IF(A3=0, "...", D3/C3*E3)))) -> 799.3667 | G3: =IFERROR(F3-$J$3,"No Disponible") -> -672.88192 | H3: =IFERROR(IF(A3= 0,"...",(F3-$J$3)/$J$3),"No Disponible") -> -0.45704367 | J3: =(F21+F112+F170+F172+F171)/5 -> 1472.2486
A4: DIA | B4: DIA | C4: =IFERROR(__xludf.DUMMYFUNCTION("IFERROR(googlefinance(A4),""No Disponible"")"),466.41) -> 466.41 | D4: =iferror(vlookup(A4,'Info Pesos'!$A$1:N455,2,0),"No Disponible") -> 11,270.00 | E4: 20 | F4: =IF(C4=0, "...", IF(C4="No Disponible", "No Disponible", IF(D4="No Disponible", "No Disponible", IF(A4=0, "...", D4/C4*E4)))) -> 483.2658 | G4: =IFERROR(F4-$J$3,"No Disponible") -> -988.98283 | H4: =IFERROR(IF(A4= 0,"...",(F4-$J$3)/$J$3),"No Disponible") -> -0.67174987
A5: IWM | B5: IWM | C5: =IFERROR(__xludf.DUMMYFUNCTION("IFERROR(googlefinance(A5),""No Disponible"")"),246.59) -> 246.59 | D5: =iferror(vlookup(A5,'Info Pesos'!$A$1:N456,2,0),"No Disponible") -> 8,405.00 | E5: 10 | F5: =IF(C5=0, "...", IF(C5="No Disponible", "No Disponible", IF(D5="No Disponible", "No Disponible", IF(A5=0, "...", D5/C5*E5)))) -> 340.84918 | G5: =IFERROR(F5-$J$3,"No Disponible") -> -1131.3994 | H5: =IFERROR(IF(A5= 0,"...",(F5-$J$3)/$J$3),"No Disponible") -> -0.76848395
A6: EEM | B6: EEM | C6: =IFERROR(__xludf.DUMMYFUNCTION("IFERROR(googlefinance(A6),""No Disponible"")"),56.8) -> 56.8 | D6: =iferror(vlookup(A6,'Info Pesos'!$A$1:N457,2,0),"No Disponible") -> 36.86 | E6: 5 | F6: =IF(C6=0, "...", IF(C6="No Disponible", "No Disponible", IF(D6="No Disponible", "No Disponible", IF(A6=0, "...", D6/C6*E6)))) -> 3.2447183 | G6: =IFERROR(F6-$J$3,"No Disponible") -> -1469.0039 | H6: =IFERROR(IF(A6= 0,"...",(F6-$J$3)/$J$3),"No Disponible") -> -0.99779608
A7: XLF | B7: XLF | C7: =IFERROR(__xludf.DUMMYFUNCTION("IFERROR(googlefinance(A7),""No Disponible"")"),48.89) -> 48.89 | D7: =iferror(vlookup(A7,'Info Pesos'!$A$1:N458,2,0),"No Disponible") -> 39.21 | E7: 2 | F7: =IF(C7=0, "...", IF(C7="No Disponible", "No Disponible", IF(D7="No Disponible", "No Disponible", IF(A7=0, "...", D7/C7*E7)))) -> 1.604009 | G7: =IFERROR(F7-$J$3,"No Disponible") -> -1470.6446 | H7: =IFERROR(IF(A7= 0,"...",(F7-$J$3)/$J$3),"No Disponible") -> -0.9989105
A8: XLE | B8: XLE | C8: =IFERROR(__xludf.DUMMYFUNCTION("IFERROR(googlefinance(A8),""No Disponible"")"),57.7) -> 57.7 | D8: =iferror(vlookup(A8,'Info Pesos'!$A$1:N459,2,0),"No Disponible") -> 7.76 | E8: 2 | F8: =IF(C8=0, "...", IF(C8="No Disponible", "No Disponible", IF(D8="No Disponible", "No Disponible", IF(A8=0, "...", D8/C8*E8)))) -> 0.26897747 | G8: =IFERROR(F8-$J$3,"No Disponible") -> -1471.9796 | H8: =IFERROR(IF(A8= 0,"...",(F8-$J$3)/$J$3),"No Disponible") -> -0.9998173
A9: EWZ | B9: EWZ | C9: =IFERROR(__xludf.DUMMYFUNCTION("IFERROR(googlefinance(A9),""No Disponible"")"),35.49) -> 35.49 | D9: =iferror(vlookup(A9,'Info Pesos'!$A$1:N460,2,0),"No Disponible") -> 8.51 | E9: 2 | F9: =IF(C9=0, "...", IF(C9="No Disponible", "No Disponible", IF(D9="No Disponible", "No Disponible", IF(A9=0, "...", D9/C9*E9)))) -> 0.47957171 | G9: =IFERROR(F9-$J$3,"No Disponible") -> -1471.7691 | H9: =IFERROR(IF(A9= 0,"...",(F9-$J$3)/$J$3),"No Disponible") -> -0.99967426
A10: ARKK | B10: ARKK | C10: =IFERROR(__xludf.DUMMYFUNCTION("IFERROR(googlefinance(A10),""No Disponible"")"),7.44) -> 7.44 | D10: =iferror(vlookup(A10,'Info Pesos'!$A$1:N461,2,0),"No Disponible") -> 2,602.50 | E10: 10 | F10: =IF(C10=0, "...", IF(C10="No Disponible", "No Disponible", IF(D10="No Disponible", "No Disponible", IF(A10=0, "...", D10/C10*E10)))) -> 3497.9839 | G10: =IFERROR(F10-$J$3,"No Disponible") -> 2025.7352 | H10: =IFERROR(IF(A10= 0,"...",(F10-$J$3)/$J$3),"No Disponible") -> 1.3759464
A11: ABT | B11: ABT | C11: =IFERROR(__xludf.DUMMYFUNCTION("IFERROR(googlefinance(A11),""No Disponible"")"),108.03) -> 108.03 | D11: =iferror(vlookup(A11,'Info Pesos'!$A$1:N462,2,0),"No Disponible") -> 39,580.00 | E11: 4 | F11: =IF(C11=0, "...", IF(C11="No Disponible", "No Disponible", IF(D11="No Disponible", "No Disponible", IF(A11=0, "...", D11/C11*E11)))) -> 1465.5188 | G11: =IFERROR(F11-$J$3,"No Disponible") -> -6.7297857 | H11: =IFERROR(IF(A11= 0,"...",(F11-$J$3)/$J$3),"No Disponible") -> -0.0045710932
A12: HWM | B12: HWM | C12: =IFERROR(__xludf.DUMMYFUNCTION("IFERROR(googlefinance(A12),""No Disponible"")"),236.75) -> 236.75 | D12: =iferror(vlookup(A12,'Info Pesos'!$A$1:N463,2,0),"No Disponible") -> 348,450.00 | E12: 1 | F12: =IF(C12=0, "...", IF(C12="No Disponible", "No Disponible", IF(D12="No Disponible", "No Disponible", IF(A12=0, "...", D12/C12*E12)))) -> 1471.8057 | G12: =IFERROR(F12-$J$3,"No Disponible") -> -0.44292086 | H12: =IFERROR(IF(A12= 0,"...",(F12-$J$3)/$J$3),"No Disponible") -> -0.00030084651
A13: AEG | B13: AEG | C13: =IFERROR(__xludf.DUMMYFUNCTION("IFERROR(googlefinance(A13),""No Disponible"")"),6.79) -> 6.79 | D13: =iferror(vlookup(A13,'Info Pesos'!$A$1:N464,2,0),"No Disponible") -> 10,020.00 | E13: 1 | F13: =IF(C13=0, "...", IF(C13="No Disponible", "No Disponible", IF(D13="No Disponible", "No Disponible", IF(A13=0, "...", D13/C13*E13)))) -> 1475.6996 | G13: =IFERROR(F13-$J$3,"No Disponible") -> 3.4509351 | H13: =IFERROR(IF(A13= 0,"...",(F13-$J$3)/$J$3),"No Disponible") -> 0.0023439893
A14: MO | B14: MO | C14: =IFERROR(__xludf.DUMMYFUNCTION("IFERROR(googlefinance(A14),""No Disponible"")"),67.89) -> 67.89 | D14: =iferror(vlookup(A14,'Info Pesos'!$A$1:N465,2,0),"No Disponible") -> 25,080.00 | E14: 4 | F14: =IF(C14=0, "...", IF(C14="No Disponible", "No Disponible", IF(D14="No Disponible", "No Disponible", IF(A14=0, "...", D14/C14*E14)))) -> 1477.6845 | G14: =IFERROR(F14-$J$3,"No Disponible") -> 5.4358665 | H14: =IFERROR(IF(A14= 0,"...",(F14-$J$3)/$J$3),"No Disponible") -> 0.0036922205
A15: AEM | B15: AEM | C15: =IFERROR(__xludf.DUMMYFUNCTION("IFERROR(googlefinance(A15),""No Disponible"")"),207.54) -> 207.54 | D15: =iferror(vlookup(A15,'Info Pesos'!$A$1:N466,2,0),"No Disponible") -> 50,850.00 | E15: 6 | F15: =IF(C15=0, "...", IF(C15="No Disponible", "No Disponible", IF(D15="No Disponible", "No Disponible", IF(A15=0, "...", D15/C15*E15)))) -> 1470.0781 | G15: =IFERROR(F15-$J$3,"No Disponible") -> -2.1705658 | H15: =IFERROR(IF(A15= 0,"...",(F15-$J$3)/$J$3),"No Disponible") -> -0.0014743202
A16: AMX | B16: AMX | C16: =IFERROR(__xludf.DUMMYFUNCTION("IFERROR(googlefinance(A16),""No Disponible"")"),22.99) -> 22.99 | D16: =iferror(vlookup(A16,'Info Pesos'!$A$1:N467,2,0),"No Disponible") -> 33,680.00 | E16: 1 | F16: =IF(C16=0, "...", IF(C16="No Disponible", "No Disponible", IF(D16="No Disponible", "No Disponible", IF(A16=0, "...", D16/C16*E16)))) -> 1464.9848 | G16: =IFERROR(F16-$J$3,"No Disponible") -> -7.2638471 | H16: =IFERROR(IF(A16= 0,"...",(F16-$J$3)/$J$3),"No Disponible") -> -0.0049338454
A17: AXP | B17: AXP | C17: =IFERROR(__xludf.DUMMYFUNCTION("IFERROR(googlefinance(A17),""No Disponible"")"),299.96) -> 299.96 | D17: =iferror(vlookup(A17,'Info Pesos'!$A$1:N468,2,0),"No Disponible") -> 29,360.00 | E17: 15 | F17: =IF(C17=0, "...", IF(C17="No Disponible", "No Disponible", IF(D17="No Disponible", "No Disponible", IF(A17=0, "...", D17/C17*E17)))) -> 1468.1958 | G17: =IFERROR(F17-$J$3,"No Disponible") -> -4.0528636 | H17: =IFERROR(IF(A17= 0,"...",(F17-$J$3)/$J$3),"No Disponible") -> -0.0027528391
A18: AIG | B18: AIG | C18: =IFERROR(__xludf.DUMMYFUNCTION("IFERROR(googlefinance(A18),""No Disponible"")"),76.74) -> 76.74 | D18: =iferror(vlookup(A18,'Info Pesos'!$A$1:N469,2,0),"No Disponible") -> No Disponible | E18: 5 | F18: =IF(C18=0, "...", IF(C18="No Disponible", "No Disponible", IF(D18="No Disponible", "No Disponible", IF(A18=0, "...", D18/C18*E18)))) -> No Disponible | G18: =IFERROR(F18-$J$3,"No Disponible") -> No Disponible | H18: =IFERROR(IF(A18= 0,"...",(F18-$J$3)/$J$3),"No Disponible") -> No Disponible
A19: AMGN | B19: AMGN | C19: =IFERROR(__xludf.DUMMYFUNCTION("IFERROR(googlefinance(A19),""No Disponible"")"),366.21) -> 366.21 | D19: =iferror(vlookup(A19,'Info Pesos'!$A$1:N470,2,0),"No Disponible") -> 17,990.00 | E19: 30 | F19: =IF(C19=0, "...", IF(C19="No Disponible", "No Disponible", IF(D19="No Disponible", "No Disponible", IF(A19=0, "...", D19/C19*E19)))) -> 1473.7446 | G19: =IFERROR(F19-$J$3,"No Disponible") -> 1.4959497 | H19: =IFERROR(IF(A19= 0,"...",(F19-$J$3)/$J$3),"No Disponible") -> 0.0010160986
A20: ADI | B20: ADI | C20: =IFERROR(__xludf.DUMMYFUNCTION("IFERROR(googlefinance(A20),""No Disponible"")"),306.07) -> 306.07 | D20: =iferror(vlookup(A20,'Info Pesos'!$A$1:N471,2,0),"No Disponible") -> 29,880.00 | E20: 15 | F20: =IF(C20=0, "...", IF(C20="No Disponible", "No Disponible", IF(D20="No Disponible", "No Disponible", IF(A20=0, "...", D20/C20*E20)))) -> 1464.3709 | G20: =IFERROR(F20-$J$3,"No Disponible") -> -7.8777275 | H20: =IFERROR(IF(A20= 0,"...",(F20-$J$3)/$J$3),"No Disponible") -> -0.0053508133
A21: AAPL | B21: AAPL | C21: =IFERROR(__xludf.DUMMYFUNCTION("IFERROR(googlefinance(A21),""No Disponible"")"),250.12) -> 250.12 | D21: =iferror(vlookup(A21,'Info Pesos'!$A$1:N472,2,0),"No Disponible") -> 18,410.00 | E21: 20 | F21: =IF(C21=0, "...", IF(C21="No Disponible", "No Disponible", IF(D21="No Disponible", "No Disponible", IF(A21=0, "...", D21/C21*E21)))) -> 1472.0934 | G21: =IFERROR(F21-$J$3,"No Disponible") -> -0.15522791 | H21: =IFERROR(IF(A21= 0,"...",(F21-$J$3)/$J$3),"No Disponible") -> -0.00010543593
A22: AMAT | B22: AMAT | C22: =IFERROR(__xludf.DUMMYFUNCTION("IFERROR(googlefinance(A22),""No Disponible"")"),341.53) -> 341.53 | D22: =iferror(vlookup(A22,'Info Pesos'!$A$1:N473,2,0),"No Disponible") -> 100,300.00 | E22: 5 | F22: =IF(C22=0, "...", IF(C22="No Disponible", "No Disponible", IF(D22="No Disponible", "No Disponible", IF(A22=0, "...", D22/C22*E22)))) -> 1468.3922 | G22: =IFERROR(F22-$J$3,"No Disponible") -> -3.8563881 | H22: =IFERROR(IF(A22= 0,"...",(F22-$J$3)/$J$3),"No Disponible") -> -0.0026193865
A23: T | B23: T | C23: =IFERROR(__xludf.DUMMYFUNCTION("IFERROR(googlefinance(A23),""No Disponible"")"),27.72) -> 27.72 | D23: =iferror(vlookup(A23,'Info Pesos'!$A$1:N474,2,0),"No Disponible") -> No Disponible | E23: 3 | F23: =IF(C23=0, "...", IF(C23="No Disponible", "No Disponible", IF(D23="No Disponible", "No Disponible", IF(A23=0, "...", D23/C23*E23)))) -> No Disponible | G23: =IFERROR(F23-$J$3,"No Disponible") -> No Disponible | H23: =IFERROR(IF(A23= 0,"...",(F23-$J$3)/$J$3),"No Disponible") -> No Disponible
A24: ADP | B24: ADP | C24: =IFERROR(__xludf.DUMMYFUNCTION("IFERROR(googlefinance(A24),""No Disponible"")"),208.52) -> 208.52 | D24: =iferror(vlookup(A24,'Info Pesos'!$A$1:N475,2,0),"No Disponible") -> 51,225.00 | E24: 6 | F24: =IF(C24=0, "...", IF(C24="No Disponible", "No Disponible", IF(D24="No Disponible", "No Disponible", IF(A24=0, "...", D24/C24*E24)))) -> 1473.9593 | G24: =IFERROR(F24-$J$3,"No Disponible") -> 1.7107094 | H24: =IFERROR(IF(A24= 0,"...",(F24-$J$3)/$J$3),"No Disponible") -> 0.0011619704
A25: AVY | B25: AVY | C25: =IFERROR(__xludf.DUMMYFUNCTION("IFERROR(googlefinance(A25),""No Disponible"")"),170.77) -> 170.77 | D25: =iferror(vlookup(A25,'Info Pesos'!$A$1:N476,2,0),"No Disponible") -> 13,980.00 | E25: 18 | F25: =IF(C25=0, "...", IF(C25="No Disponible", "No Disponible", IF(D25="No Disponible", "No Disponible", IF(A25=0, "...", D25/C25*E25)))) -> 1473.5609 | G25: =IFERROR(F25-$J$3,"No Disponible") -> 1.3123068 | H25: =IFERROR(IF(A25= 0,"...",(F25-$J$3)/$J$3),"No Disponible") -> 0.00089136224
A26: CAR | B26: CAR | C26: =IFERROR(__xludf.DUMMYFUNCTION("IFERROR(googlefinance(A26),""No Disponible"")"),100.71) -> 100.71 | D26: =iferror(vlookup(A26,'Info Pesos'!$A$1:N477,2,0),"No Disponible") -> 5,665.00 | E26: 26 | F26: =IF(C26=0, "...", IF(C26="No Disponible", "No Disponible", IF(D26="No Disponible", "No Disponible", IF(A26=0, "...", D26/C26*E26)))) -> 1462.5161 | G26: =IFERROR(F26-$J$3,"No Disponible") -> -9.7324876 | H26: =IFERROR(IF(A26= 0,"...",(F26-$J$3)/$J$3),"No Disponible") -> -0.0066106278
A27: AZN | B27: AZN | C27: =IFERROR(__xludf.DUMMYFUNCTION("IFERROR(googlefinance(A27),""No Disponible"")"),189.9) -> 189.9 | D27: =iferror(vlookup(A27,'Info Pesos'!$A$1:N478,2,0),"No Disponible") -> 70,025.00 | E27: 2 | F27: =IF(C27=0, "...", IF(C27="No Disponible", "No Disponible", IF(D27="No Disponible", "No Disponible", IF(A27=0, "...", D27/C27*E27)))) -> 737.49342 | G27: =IFERROR(F27-$J$3,"No Disponible") -> -734.75521 | H27: =IFERROR(IF(A27= 0,"...",(F27-$J$3)/$J$3),"No Disponible") -> -0.49907006
A28: BBVA | B28: BBVA | C28: =IFERROR(__xludf.DUMMYFUNCTION("IFERROR(googlefinance(A28),""No Disponible"")"),20.45) -> 20.45 | D28: =iferror(vlookup(A28,'Info Pesos'!$A$1:N479,2,0),"No Disponible") -> No Disponible | E28: 1 | F28: =IF(C28=0, "...", IF(C28="No Disponible", "No Disponible", IF(D28="No Disponible", "No Disponible", IF(A28=0, "...", D28/C28*E28)))) -> No Disponible | G28: =IFERROR(F28-$J$3,"No Disponible") -> No Disponible | H28: =IFERROR(IF(A28= 0,"...",(F28-$J$3)/$J$3),"No Disponible") -> No Disponible
A29: BBD | B29: BBD | C29: =IFERROR(__xludf.DUMMYFUNCTION("IFERROR(googlefinance(A29),""No Disponible"")"),3.53) -> 3.53 | D29: =iferror(vlookup(A29,'Info Pesos'!$A$1:N480,2,0),"No Disponible") -> 5,200.00 | E29: 1 | F29: =IF(C29=0, "...", IF(C29="No Disponible", "No Disponible", IF(D29="No Disponible", "No Disponible", IF(A29=0, "...", D29/C29*E29)))) -> 1473.0878 | G29: =IFERROR(F29-$J$3,"No Disponible") -> 0.83919562 | H29: =IFERROR(IF(A29= 0,"...",(F29-$J$3)/$J$3),"No Disponible") -> 0.00057000944
A30: BSBR | B30: BSBR | C30: =IFERROR(__xludf.DUMMYFUNCTION("IFERROR(googlefinance(A30),""No Disponible"")"),5.72) -> 5.72 | D30: =iferror(vlookup(A30,'Info Pesos'!$A$1:N481,2,0),"No Disponible") -> 8,480.00 | E30: 1 | F30: =IF(C30=0, "...", IF(C30="No Disponible", "No Disponible", IF(D30="No Disponible", "No Disponible", IF(A30=0, "...", D30/C30*E30)))) -> 1482.5175 | G30: =IFERROR(F30-$J$3,"No Disponible") -> 10.268859 | H30: =IFERROR(IF(A30= 0,"...",(F30-$J$3)/$J$3),"No Disponible") -> 0.0069749493
A31: BAC | B31: BAC | C31: =IFERROR(__xludf.DUMMYFUNCTION("IFERROR(googlefinance(A31),""No Disponible"")"),46.72) -> 46.72 | D31: =iferror(vlookup(A31,'Info Pesos'!$A$1:N482,2,0),"No Disponible") -> No Disponible | E31: 4 | F31: =IF(C31=0, "...", IF(C31="No Disponible", "No Disponible", IF(D31="No Disponible", "No Disponible", IF(A31=0, "...", D31/C31*E31)))) -> No Disponible | G31: =IFERROR(F31-$J$3,"No Disponible") -> No Disponible | H31: =IFERROR(IF(A31= 0,"...",(F31-$J$3)/$J$3),"No Disponible") -> No Disponible
A32: BCS | B32: BCS | C32: =IFERROR(__xludf.DUMMYFUNCTION("IFERROR(googlefinance(A32),""No Disponible"")"),20.47) -> 20.47 | D32: =iferror(vlookup(A32,'Info Pesos'!$A$1:N483,2,0),"No Disponible") -> 30,080.00 | E32: 1 | F32: =IF(C32=0, "...", IF(C32="No Disponible", "No Disponible", IF(D32="No Disponible", "No Disponible", IF(A32=0, "...", D32/C32*E32)))) -> 1469.4675 | G32: =IFERROR(F32-$J$3,"No Disponible") -> -2.7811096 | H32: =IFERROR(IF(A32= 0,"...",(F32-$J$3)/$J$3),"No Disponible") -> -0.0018890217
A33: GOLD | B33: GOLD | C33: =IFERROR(__xludf.DUMMYFUNCTION("IFERROR(googlefinance(A33),""No Disponible"")"),47.47) -> 47.47 | D33: =iferror(vlookup(A33,'Info Pesos'!$A$1:N484,2,0),"No Disponible") -> No Disponible | E33: 2 | F33: =IF(C33=0, "...", IF(C33="No Disponible", "No Disponible", IF(D33="No Disponible", "No Disponible", IF(A33=0, "...", D33/C33*E33)))) -> No Disponible | G33: =IFERROR(F33-$J$3,"No Disponible") -> No Disponible | H33: =IFERROR(IF(A33= 0,"...",(F33-$J$3)/$J$3),"No Disponible") -> No Disponible
A34: BAS GR | B34: BAS GR | C34: =IFERROR(__xludf.DUMMYFUNCTION("IFERROR(googlefinance(A34),""No Disponible"")"),"No Disponible") -> No Disponible | D34: =iferror(vlookup(A34,'Info Pesos'!$A$1:N485,2,0),"No Disponible") -> No Disponible | E34: 2 | F34: =IF(C34=0, "...", IF(C34="No Disponible", "No Disponible", IF(D34="No Disponible", "No Disponible", IF(A34=0, "...", D34/C34*E34)))) -> No Disponible | G34: =IFERROR(F34-$J$3,"No Disponible") -> No Disponible | H34: =IFERROR(IF(A34= 0,"...",(F34-$J$3)/$J$3),"No Disponible") -> No Disponible
A35: BAYN GR | B35: BAYN GR | C35: =IFERROR(__xludf.DUMMYFUNCTION("IFERROR(googlefinance(A35),""No Disponible"")"),"No Disponible") -> No Disponible | D35: =iferror(vlookup(A35,'Info Pesos'!$A$1:N486,2,0),"No Disponible") -> No Disponible | E35: 3 | F35: =IF(C35=0, "...", IF(C35="No Disponible", "No Disponible", IF(D35="No Disponible", "No Disponible", IF(A35=0, "...", D35/C35*E35)))) -> No Disponible | G35: =IFERROR(F35-$J$3,"No Disponible") -> No Disponible | H35: =IFERROR(IF(A35= 0,"...",(F35-$J$3)/$J$3),"No Disponible") -> No Disponible
A36: BHP | B36: BHP | C36: =IFERROR(__xludf.DUMMYFUNCTION("IFERROR(googlefinance(A36),""No Disponible"")"),68.74) -> 68.74 | D36: =iferror(vlookup(A36,'Info Pesos'!$A$1:N487,2,0),"No Disponible") -> 50,600.00 | E36: 2 | F36: =IF(C36=0, "...", IF(C36="No Disponible", "No Disponible", IF(D36="No Disponible", "No Disponible", IF(A36=0, "...", D36/C36*E36)))) -> 1472.2141 | G36: =IFERROR(F36-$J$3,"No Disponible") -> -0.034482842 | H36: =IFERROR(IF(A36= 0,"...",(F36-$J$3)/$J$3),"No Disponible") -> -2.3421887e-05
A37: BA | B37: BA | C37: =IFERROR(__xludf.DUMMYFUNCTION("IFERROR(googlefinance(A37),""No Disponible"")"),209.89) -> 209.89 | D37: =iferror(vlookup(A37,'Info Pesos'!$A$1:N488,2,0),"No Disponible") -> 12,830.00 | E37: 24 | F37: =IF(C37=0, "...", IF(C37="No Disponible", "No Disponible", IF(D37="No Disponible", "No Disponible", IF(A37=0, "...", D37/C37*E37)))) -> 1467.0542 | G37: =IFERROR(F37-$J$3,"No Disponible") -> -5.1944518 | H37: =IFERROR(IF(A37= 0,"...",(F37-$J$3)/$J$3),"No Disponible") -> -0.0035282436
A38: BP | B38: BP | C38: =IFERROR(__xludf.DUMMYFUNCTION("IFERROR(googlefinance(A38),""No Disponible"")"),42.67) -> 42.67 | D38: =iferror(vlookup(A38,'Info Pesos'!$A$1:N489,2,0),"No Disponible") -> 12,500.00 | E38: 5 | F38: =IF(C38=0, "...", IF(C38="No Disponible", "No Disponible", IF(D38="No Disponible", "No Disponible", IF(A38=0, "...", D38/C38*E38)))) -> 1464.7293 | G38: =IFERROR(F38-$J$3,"No Disponible") -> -7.5193051 | H38: =IFERROR(IF(A38= 0,"...",(F38-$J$3)/$J$3),"No Disponible") -> -0.0051073609
A39: BMY | B39: BMY | C39: =IFERROR(__xludf.DUMMYFUNCTION("IFERROR(googlefinance(A39),""No Disponible"")"),59.08) -> 59.08 | D39: =iferror(vlookup(A39,'Info Pesos'!$A$1:N490,2,0),"No Disponible") -> No Disponible | E39: 3 | F39: =IF(C39=0, "...", IF(C39="No Disponible", "No Disponible", IF(D39="No Disponible", "No Disponible", IF(A39=0, "...", D39/C39*E39)))) -> No Disponible | G39: =IFERROR(F39-$J$3,"No Disponible") -> No Disponible | H39: =IFERROR(IF(A39= 0,"...",(F39-$J$3)/$J$3),"No Disponible") -> No Disponible
A40: BG | B40: BG | C40: =IFERROR(__xludf.DUMMYFUNCTION("IFERROR(googlefinance(A40),""No Disponible"")"),124.73) -> 124.73 | D40: =iferror(vlookup(A40,'Info Pesos'!$A$1:N491,2,0),"No Disponible") -> No Disponible | E40: 5 | F40: =IF(C40=0, "...", IF(C40="No Disponible", "No Disponible", IF(D40="No Disponible", "No Disponible", IF(A40=0, "...", D40/C40*E40)))) -> No Disponible | G40: =IFERROR(F40-$J$3,"No Disponible") -> No Disponible | H40: =IFERROR(IF(A40= 0,"...",(F40-$J$3)/$J$3),"No Disponible") -> No Disponible
A41: CAH | B41: CAH | C41: =IFERROR(__xludf.DUMMYFUNCTION("IFERROR(googlefinance(A41),""No Disponible"")"),217.08) -> 217.08 | D41: =iferror(vlookup(A41,'Info Pesos'!$A$1:N492,2,0),"No Disponible") -> 106,250.00 | E41: 3 | F41: =IF(C41=0, "...", IF(C41="No Disponible", "No Disponible", IF(D41="No Disponible", "No Disponible", IF(A41=0, "...", D41/C41*E41)))) -> 1468.3527 | G41: =IFERROR(F41-$J$3,"No Disponible") -> -3.895942 | H41: =IFERROR(IF(A41= 0,"...",(F41-$J$3)/$J$3),"No Disponible") -> -0.0026462528
A42: CAT | B42: CAT | C42: =IFERROR(__xludf.DUMMYFUNCTION("IFERROR(googlefinance(A42),""No Disponible"")"),693.99) -> 693.99 | D42: =iferror(vlookup(A42,'Info Pesos'!$A$1:N493,2,0),"No Disponible") -> 51,100.00 | E42: 20 | F42: =IF(C42=0, "...", IF(C42="No Disponible", "No Disponible", IF(D42="No Disponible", "No Disponible", IF(A42=0, "...", D42/C42*E42)))) -> 1472.6437 | G42: =IFERROR(F42-$J$3,"No Disponible") -> 0.39507496 | H42: =IFERROR(IF(A42= 0,"...",(F42-$J$3)/$J$3),"No Disponible") -> 0.00026834799
A43: CX | B43: CX | C43: =IFERROR(__xludf.DUMMYFUNCTION("IFERROR(googlefinance(A43),""No Disponible"")"),10.41) -> 10.41 | D43: =iferror(vlookup(A43,'Info Pesos'!$A$1:N494,2,0),"No Disponible") -> 15,180.00 | E43: 1 | F43: =IF(C43=0, "...", IF(C43="No Disponible", "No Disponible", IF(D43="No Disponible", "No Disponible", IF(A43=0, "...", D43/C43*E43)))) -> 1458.2133 | G43: =IFERROR(F43-$J$3,"No Disponible") -> -14.035367 | H43: =IFERROR(IF(A43= 0,"...",(F43-$J$3)/$J$3),"No Disponible") -> -0.0095332856
A44: CVX | B44: CVX | C44: =IFERROR(__xludf.DUMMYFUNCTION("IFERROR(googlefinance(A44),""No Disponible"")"),196.82) -> 196.82 | D44: =iferror(vlookup(A44,'Info Pesos'!$A$1:N495,2,0),"No Disponible") -> 18,090.00 | E44: 16 | F44: =IF(C44=0, "...", IF(C44="No Disponible", "No Disponible", IF(D44="No Disponible", "No Disponible", IF(A44=0, "...", D44/C44*E44)))) -> 1470.5823 | G44: =IFERROR(F44-$J$3,"No Disponible") -> -1.6663652 | H44: =IFERROR(IF(A44= 0,"...",(F44-$J$3)/$J$3),"No Disponible") -> -0.0011318504
A45: CSCO | B45: CSCO | C45: =IFERROR(__xludf.DUMMYFUNCTION("IFERROR(googlefinance(A45),""No Disponible"")"),78.33) -> 78.33 | D45: =iferror(vlookup(A45,'Info Pesos'!$A$1:N496,2,0),"No Disponible") -> 23,020.00 | E45: 5 | F45: =IF(C45=0, "...", IF(C45="No Disponible", "No Disponible", IF(D45="No Disponible", "No Disponible", IF(A45=0, "...", D45/C45*E45)))) -> 1469.4242 | G45: =IFERROR(F45-$J$3,"No Disponible") -> -2.8243923 | H45: =IFERROR(IF(A45= 0,"...",(F45-$J$3)/$J$3),"No Disponible") -> -0.0019184207
A46: C | B46: C | C46: =IFERROR(__xludf.DUMMYFUNCTION("IFERROR(googlefinance(A46),""No Disponible"")"),105.69) -> 105.69 | D46: =iferror(vlookup(A46,'Info Pesos'!$A$1:N497,2,0),"No Disponible") -> 51,700.00 | E46: 3 | F46: =IF(C46=0, "...", IF(C46="No Disponible", "No Disponible", IF(D46="No Disponible", "No Disponible", IF(A46=0, "...", D46/C46*E46)))) -> 1467.4993 | G46: =IFERROR(F46-$J$3,"No Disponible") -> -4.7493327 | H46: =IFERROR(IF(A46= 0,"...",(F46-$J$3)/$J$3),"No Disponible") -> -0.003225904
A47: KO | B47: KO | C47: =IFERROR(__xludf.DUMMYFUNCTION("IFERROR(googlefinance(A47),""No Disponible"")"),77.34) -> 77.34 | D47: =iferror(vlookup(A47,'Info Pesos'!$A$1:N498,2,0),"No Disponible") -> 22,700.00 | E47: 5 | F47: =IF(C47=0, "...", IF(C47="No Disponible", "No Disponible", IF(D47="No Disponible", "No Disponible", IF(A47=0, "...", D47/C47*E47)))) -> 1467.5459 | G47: =IFERROR(F47-$J$3,"No Disponible") -> -4.7027219 | H47: =IFERROR(IF(A47= 0,"...",(F47-$J$3)/$J$3),"No Disponible") -> -0.0031942444
A48: KOF | B48: KOF | C48: =IFERROR(__xludf.DUMMYFUNCTION("IFERROR(googlefinance(A48),""No Disponible"")"),97.16) -> 97.16 | D48: =iferror(vlookup(A48,'Info Pesos'!$A$1:N499,2,0),"No Disponible") -> No Disponible | E48: 2 | F48: =IF(C48=0, "...", IF(C48="No Disponible", "No Disponible", IF(D48="No Disponible", "No Disponible", IF(A48=0, "...", D48/C48*E48)))) -> No Disponible | G48: =IFERROR(F48-$J$3,"No Disponible") -> No Disponible | H48: =IFERROR(IF(A48= 0,"...",(F48-$J$3)/$J$3),"No Disponible") -> No Disponible
A49: CDE | B49: CDE | C49: =IFERROR(__xludf.DUMMYFUNCTION("IFERROR(googlefinance(A49),""No Disponible"")"),20.19) -> 20.19 | D49: =iferror(vlookup(A49,'Info Pesos'!$A$1:N500,2,0),"No Disponible") -> No Disponible | E49: 1 | F49: =IF(C49=0, "...", IF(C49="No Disponible", "No Disponible", IF(D49="No Disponible", "No Disponible", IF(A49=0, "...", D49/C49*E49)))) -> No Disponible | G49: =IFERROR(F49-$J$3,"No Disponible") -> No Disponible | H49: =IFERROR(IF(A49= 0,"...",(F49-$J$3)/$J$3),"No Disponible") -> No Disponible
A50: CL | B50: CL | C50: =IFERROR(__xludf.DUMMYFUNCTION("IFERROR(googlefinance(A50),""No Disponible"")"),88.84) -> 88.84 | D50: =iferror(vlookup(A50,'Info Pesos'!$A$1:N501,2,0),"No Disponible") -> 43,640.00 | E50: 3 | F50: =IF(C50=0, "...", IF(C50="No Disponible", "No Disponible", IF(D50="No Disponible", "No Disponible", IF(A50=0, "...", D50/C50*E50)))) -> 1473.6605 | G50: =IFERROR(F50-$J$3,"No Disponible") -> 1.4118902 | H50: =IFERROR(IF(A50= 0,"...",(F50-$J$3)/$J$3),"No Disponible") -> 0.00095900256
A51: VALE | B51: VALE | C51: =IFERROR(__xludf.DUMMYFUNCTION("IFERROR(googlefinance(A51),""No Disponible"")"),14.68) -> 14.68 | D51: =iferror(vlookup(A51,'Info Pesos'!$A$1:N502,2,0),"No Disponible") -> No Disponible | E51: 2 | F51: =IF(C51=0, "...", IF(C51="No Disponible", "No Disponible", IF(D51="No Disponible", "No Disponible", IF(A51=0, "...", D51/C51*E51)))) -> No Disponible | G51: =IFERROR(F51-$J$3,"No Disponible") -> No Disponible | H51: =IFERROR(IF(A51= 0,"...",(F51-$J$3)/$J$3),"No Disponible") -> No Disponible
A52: GLW | B52: GLW | C52: =IFERROR(__xludf.DUMMYFUNCTION("IFERROR(googlefinance(A52),""No Disponible"")"),129.12) -> 129.12 | D52: =iferror(vlookup(A52,'Info Pesos'!$A$1:N503,2,0),"No Disponible") -> 47,440.00 | E52: 4 | F52: =IF(C52=0, "...", IF(C52="No Disponible", "No Disponible", IF(D52="No Disponible", "No Disponible", IF(A52=0, "...", D52/C52*E52)))) -> 1469.6406 | G52: =IFERROR(F52-$J$3,"No Disponible") -> -2.6079787 | H52: =IFERROR(IF(A52= 0,"...",(F52-$J$3)/$J$3),"No Disponible") -> -0.0017714255
A53: COST | B53: COST | C53: =IFERROR(__xludf.DUMMYFUNCTION("IFERROR(googlefinance(A53),""No Disponible"")"),1008.43) -> 1008.43 | D53: =iferror(vlookup(A53,'Info Pesos'!$A$1:N504,2,0),"No Disponible") -> 30,820.00 | E53: 48 | F53: =IF(C53=0, "...", IF(C53="No Disponible", "No Disponible", IF(D53="No Disponible", "No Disponible", IF(A53=0, "...", D53/C53*E53)))) -> 1466.9932 | G53: =IFERROR(F53-$J$3,"No Disponible") -> -5.2553762 | H53: =IFERROR(IF(A53= 0,"...",(F53-$J$3)/$J$3),"No Disponible") -> -0.0035696254
A54: MBG GR | B54: MBG GR | C54: =IFERROR(__xludf.DUMMYFUNCTION("IFERROR(googlefinance(A54),""No Disponible"")"),"No Disponible") -> No Disponible | D54: =iferror(vlookup(A54,'Info Pesos'!$A$1:N505,2,0),"No Disponible") -> No Disponible | E54: 4 | F54: =IF(C54=0, "...", IF(C54="No Disponible", "No Disponible", IF(D54="No Disponible", "No Disponible", IF(A54=0, "...", D54/C54*E54)))) -> No Disponible | G54: =IFERROR(F54-$J$3,"No Disponible") -> No Disponible | H54: =IFERROR(IF(A54= 0,"...",(F54-$J$3)/$J$3),"No Disponible") -> No Disponible
A55: DE | B55: DE | C55: =IFERROR(__xludf.DUMMYFUNCTION("IFERROR(googlefinance(A55),""No Disponible"")"),577.5) -> 577.5 | D55: =iferror(vlookup(A55,'Info Pesos'!$A$1:N506,2,0),"No Disponible") -> 21,160.00 | E55: 40 | F55: =IF(C55=0, "...", IF(C55="No Disponible", "No Disponible", IF(D55="No Disponible", "No Disponible", IF(A55=0, "...", D55/C55*E55)))) -> 1465.6277 | G55: =IFERROR(F55-$J$3,"No Disponible") -> -6.6209175 | H55: =IFERROR(IF(A55= 0,"...",(F55-$J$3)/$J$3),"No Disponible") -> -0.0044971463
A56: DTEA GR | B56: DTEA GR | C56: =IFERROR(__xludf.DUMMYFUNCTION("IFERROR(googlefinance(A56),""No Disponible"")"),"No Disponible") -> No Disponible | D56: =iferror(vlookup(A56,'Info Pesos'!$A$1:N507,2,0),"No Disponible") -> No Disponible | E56: 3 | F56: =IF(C56=0, "...", IF(C56="No Disponible", "No Disponible", IF(D56="No Disponible", "No Disponible", IF(A56=0, "...", D56/C56*E56)))) -> No Disponible | G56: =IFERROR(F56-$J$3,"No Disponible") -> No Disponible | H56: =IFERROR(IF(A56= 0,"...",(F56-$J$3)/$J$3),"No Disponible") -> No Disponible
A57: DEO | B57: DEO | C57: =IFERROR(__xludf.DUMMYFUNCTION("IFERROR(googlefinance(A57),""No Disponible"")"),77.37) -> 77.37 | D57: =iferror(vlookup(A57,'Info Pesos'!$A$1:N508,2,0),"No Disponible") -> 19,050.00 | E57: 6 | F57: =IF(C57=0, "...", IF(C57="No Disponible", "No Disponible", IF(D57="No Disponible", "No Disponible", IF(A57=0, "...", D57/C57*E57)))) -> 1477.3168 | G57: =IFERROR(F57-$J$3,"No Disponible") -> 5.0681664 | H57: =IFERROR(IF(A57= 0,"...",(F57-$J$3)/$J$3),"No Disponible") -> 0.0034424664
A58: DIS | B58: DIS | C58: =IFERROR(__xludf.DUMMYFUNCTION("IFERROR(googlefinance(A58),""No Disponible"")"),99.29) -> 99.29 | D58: =iferror(vlookup(A58,'Info Pesos'!$A$1:N509,2,0),"No Disponible") -> No Disponible | E58: 12 | F58: =IF(C58=0, "...", IF(C58="No Disponible", "No Disponible", IF(D58="No Disponible", "No Disponible", IF(A58=0, "...", D58/C58*E58)))) -> No Disponible | G58: =IFERROR(F58-$J$3,"No Disponible") -> No Disponible | H58: =IFERROR(IF(A58= 0,"...",(F58-$J$3)/$J$3),"No Disponible") -> No Disponible
A59: DD | B59: DD | C59: =IFERROR(__xludf.DUMMYFUNCTION("IFERROR(googlefinance(A59),""No Disponible"")"),44.9) -> 44.9 | D59: =iferror(vlookup(A59,'Info Pesos'!$A$1:N510,2,0),"No Disponible") -> 13,210.00 | E59: 5 | F59: =IF(C59=0, "...", IF(C59="No Disponible", "No Disponible", IF(D59="No Disponible", "No Disponible", IF(A59=0, "...", D59/C59*E59)))) -> 1471.0468 | G59: =IFERROR(F59-$J$3,"No Disponible") -> -1.2018525 | H59: =IFERROR(IF(A59= 0,"...",(F59-$J$3)/$J$3),"No Disponible") -> -0.00081633799
A60: EBAY | B60: EBAY | C60: =IFERROR(__xludf.DUMMYFUNCTION("IFERROR(googlefinance(A60),""No Disponible"")"),91.34) -> 91.34 | D60: =iferror(vlookup(A60,'Info Pesos'!$A$1:N511,2,0),"No Disponible") -> 66,875.00 | E60: 2 | F60: =IF(C60=0, "...", IF(C60="No Disponible", "No Disponible", IF(D60="No Disponible", "No Disponible", IF(A60=0, "...", D60/C60*E60)))) -> 1464.3092 | G60: =IFERROR(F60-$J$3,"No Disponible") -> -7.9394486 | H60: =IFERROR(IF(A60= 0,"...",(F60-$J$3)/$J$3),"No Disponible") -> -0.0053927363
A61: EOAN GR | B61: EOAN GR | C61: =IFERROR(__xludf.DUMMYFUNCTION("IFERROR(googlefinance(A61),""No Disponible"")"),"No Disponible") -> No Disponible | D61: =iferror(vlookup(A61,'Info Pesos'!$A$1:N512,2,0),"No Disponible") -> No Disponible | E61: 6 | F61: =IF(C61=0, "...", IF(C61="No Disponible", "No Disponible", IF(D61="No Disponible", "No Disponible", IF(A61=0, "...", D61/C61*E61)))) -> No Disponible | G61: =IFERROR(F61-$J$3,"No Disponible") -> No Disponible | H61: =IFERROR(IF(A61= 0,"...",(F61-$J$3)/$J$3),"No Disponible") -> No Disponible
A62: LLY | B62: LLY | C62: =IFERROR(__xludf.DUMMYFUNCTION("IFERROR(googlefinance(A62),""No Disponible"")"),985.08) -> 985.08 | D62: =iferror(vlookup(A62,'Info Pesos'!$A$1:N513,2,0),"No Disponible") -> 25,820.00 | E62: 56 | F62: =IF(C62=0, "...", IF(C62="No Disponible", "No Disponible", IF(D62="No Disponible", "No Disponible", IF(A62=0, "...", D62/C62*E62)))) -> 1467.8199 | G62: =IFERROR(F62-$J$3,"No Disponible") -> -4.4287506 | H62: =IFERROR(IF(A62= 0,"...",(F62-$J$3)/$J$3),"No Disponible") -> -0.003008154
A63: E | B63: E | C63: =IFERROR(__xludf.DUMMYFUNCTION("IFERROR(googlefinance(A63),""No Disponible"")"),51.36) -> 51.36 | D63: =iferror(vlookup(A63,'Info Pesos'!$A$1:N514,2,0),"No Disponible") -> 18,900.00 | E63: 4 | F63: =IF(C63=0, "...", IF(C63="No Disponible", "No Disponible", IF(D63="No Disponible", "No Disponible", IF(A63=0, "...", D63/C63*E63)))) -> 1471.9626 | G63: =IFERROR(F63-$J$3,"No Disponible") -> -0.28600626 | H63: =IFERROR(IF(A63= 0,"...",(F63-$J$3)/$J$3),"No Disponible") -> -0.00019426492
A64: XOM | B64: XOM | C64: =IFERROR(__xludf.DUMMYFUNCTION("IFERROR(googlefinance(A64),""No Disponible"")"),156.12) -> 156.12 | D64: =iferror(vlookup(A64,'Info Pesos'!$A$1:N515,2,0),"No Disponible") -> No Disponible | E64: 10 | F64: =IF(C64=0, "...", IF(C64="No Disponible", "No Disponible", IF(D64="No Disponible", "No Disponible", IF(A64=0, "...", D64/C64*E64)))) -> No Disponible | G64: =IFERROR(F64-$J$3,"No Disponible") -> No Disponible | H64: =IFERROR(IF(A64= 0,"...",(F64-$J$3)/$J$3),"No Disponible") -> No Disponible
A65: FNMA | B65: FNMA | C65: =IFERROR(__xludf.DUMMYFUNCTION("IFERROR(googlefinance(A65),""No Disponible"")"),6.1) -> 6.1 | D65: =iferror(vlookup(A65,'Info Pesos'!$A$1:N516,2,0),"No Disponible") -> No Disponible | E65: 1 | F65: =IF(C65=0, "...", IF(C65="No Disponible", "No Disponible", IF(D65="No Disponible", "No Disponible", IF(A65=0, "...", D65/C65*E65)))) -> No Disponible | G65: =IFERROR(F65-$J$3,"No Disponible") -> No Disponible | H65: =IFERROR(IF(A65= 0,"...",(F65-$J$3)/$J$3),"No Disponible") -> No Disponible
A66: FDX | B66: FDX | C66: =IFERROR(__xludf.DUMMYFUNCTION("IFERROR(googlefinance(A66),""No Disponible"")"),351.68) -> 351.68 | D66: =iferror(vlookup(A66,'Info Pesos'!$A$1:N517,2,0),"No Disponible") -> 51,900.00 | E66: 10 | F66: =IF(C66=0, "...", IF(C66="No Disponible", "No Disponible", IF(D66="No Disponible", "No Disponible", IF(A66=0, "...", D66/C66*E66)))) -> 1475.7734 | G66: =IFERROR(F66-$J$3,"No Disponible") -> 3.5248073 | H66: =IFERROR(IF(A66= 0,"...",(F66-$J$3)/$J$3),"No Disponible") -> 0.0023941658
A67: FSLR | B67: FSLR | C67: =IFERROR(__xludf.DUMMYFUNCTION("IFERROR(googlefinance(A67),""No Disponible"")"),196.07) -> 196.07 | D67: =iferror(vlookup(A67,'Info Pesos'!$A$1:N518,2,0),"No Disponible") -> 15,960.00 | E67: 18 | F67: =IF(C67=0, "...", IF(C67="No Disponible", "No Disponible", IF(D67="No Disponible", "No Disponible", IF(A67=0, "...", D67/C67*E67)))) -> 1465.191 | G67: =IFERROR(F67-$J$3,"No Disponible") -> -7.0576199 | H67: =IFERROR(IF(A67= 0,"...",(F67-$J$3)/$J$3),"No Disponible") -> -0.004793769
A68: FMX | B68: FMX | C68: =IFERROR(__xludf.DUMMYFUNCTION("IFERROR(googlefinance(A68),""No Disponible"")"),106.18) -> 106.18 | D68: =iferror(vlookup(A68,'Info Pesos'!$A$1:N519,2,0),"No Disponible") -> 26,060.00 | E68: 6 | F68: =IF(C68=0, "...", IF(C68="No Disponible", "No Disponible", IF(D68="No Disponible", "No Disponible", IF(A68=0, "...", D68/C68*E68)))) -> 1472.5937 | G68: =IFERROR(F68-$J$3,"No Disponible") -> 0.34508572 | H68: =IFERROR(IF(A68= 0,"...",(F68-$J$3)/$J$3),"No Disponible") -> 0.00023439364
A69: ORAN | B69: ORAN | C69: =IFERROR(__xludf.DUMMYFUNCTION("IFERROR(googlefinance(A69),""No Disponible"")"),"No Disponible") -> No Disponible | D69: =iferror(vlookup(A69,'Info Pesos'!$A$1:N520,2,0),"No Disponible") -> No Disponible | E69: 1 | F69: =IF(C69=0, "...", IF(C69="No Disponible", "No Disponible", IF(D69="No Disponible", "No Disponible", IF(A69=0, "...", D69/C69*E69)))) -> No Disponible | G69: =IFERROR(F69-$J$3,"No Disponible") -> No Disponible | H69: =IFERROR(IF(A69= 0,"...",(F69-$J$3)/$J$3),"No Disponible") -> No Disponible
A70: FMCC | B70: FMCC | C70: =IFERROR(__xludf.DUMMYFUNCTION("IFERROR(googlefinance(A70),""No Disponible"")"),5.28) -> 5.28 | D70: =iferror(vlookup(A70,'Info Pesos'!$A$1:N521,2,0),"No Disponible") -> No Disponible | E70: 1 | F70: =IF(C70=0, "...", IF(C70="No Disponible", "No Disponible", IF(D70="No Disponible", "No Disponible", IF(A70=0, "...", D70/C70*E70)))) -> No Disponible | G70: =IFERROR(F70-$J$3,"No Disponible") -> No Disponible | H70: =IFERROR(IF(A70= 0,"...",(F70-$J$3)/$J$3),"No Disponible") -> No Disponible
A71: FCX | B71: FCX | C71: =IFERROR(__xludf.DUMMYFUNCTION("IFERROR(googlefinance(A71),""No Disponible"")"),56.38) -> 56.38 | D71: =iferror(vlookup(A71,'Info Pesos'!$A$1:N522,2,0),"No Disponible") -> 27,520.00 | E71: 3 | F71: =IF(C71=0, "...", IF(C71="No Disponible", "No Disponible", IF(D71="No Disponible", "No Disponible", IF(A71=0, "...", D71/C71*E71)))) -> 1464.3491 | G71: =IFERROR(F71-$J$3,"No Disponible") -> -7.8995631 | H71: =IFERROR(IF(A71= 0,"...",(F71-$J$3)/$J$3),"No Disponible") -> -0.0053656448
A72: GE | B72: GE | C72: =IFERROR(__xludf.DUMMYFUNCTION("IFERROR(googlefinance(A72),""No Disponible"")"),299.69) -> 299.69 | D72: =iferror(vlookup(A72,'Info Pesos'!$A$1:N523,2,0),"No Disponible") -> 55,150.00 | E72: 8 | F72: =IF(C72=0, "...", IF(C72="No Disponible", "No Disponible", IF(D72="No Disponible", "No Disponible", IF(A72=0, "...", D72/C72*E72)))) -> 1472.1879 | G72: =IFERROR(F72-$J$3,"No Disponible") -> -0.060695555 | H72: =IFERROR(IF(A72= 0,"...",(F72-$J$3)/$J$3),"No Disponible") -> -4.122643e-05
A73: GSK | B73: GSK | C73: =IFERROR(__xludf.DUMMYFUNCTION("IFERROR(googlefinance(A73),""No Disponible"")"),53.39) -> 53.39 | D73: =iferror(vlookup(A73,'Info Pesos'!$A$1:N524,2,0),"No Disponible") -> 19,610.00 | E73: 4 | F73: =IF(C73=0, "...", IF(C73="No Disponible", "No Disponible", IF(D73="No Disponible", "No Disponible", IF(A73=0, "...", D73/C73*E73)))) -> 1469.189 | G73: =IFERROR(F73-$J$3,"No Disponible") -> -3.0596364 | H73: =IFERROR(IF(A73= 0,"...",(F73-$J$3)/$J$3),"No Disponible") -> -0.0020782063
A74: GFI | B74: GFI | C74: =IFERROR(__xludf.DUMMYFUNCTION("IFERROR(googlefinance(A74),""No Disponible"")"),45.54) -> 45.54 | D74: =iferror(vlookup(A74,'Info Pesos'!$A$1:N525,2,0),"No Disponible") -> 67,200.00 | E74: 1 | F74: =IF(C74=0, "...", IF(C74="No Disponible", "No Disponible", IF(D74="No Disponible", "No Disponible", IF(A74=0, "...", D74/C74*E74)))) -> 1475.6258 | G74: =IFERROR(F74-$J$3,"No Disponible") -> 3.3772004 | H74: =IFERROR(IF(A74= 0,"...",(F74-$J$3)/$J$3),"No Disponible") -> 0.0022939063
A75: GOOGL | B75: GOOGL | C75: =IFERROR(__xludf.DUMMYFUNCTION("IFERROR(googlefinance(A75),""No Disponible"")"),302.28) -> 302.28 | D75: =iferror(vlookup(A75,'Info Pesos'!$A$1:N526,2,0),"No Disponible") -> 7,670.00 | E75: 58 | F75: =IF(C75=0, "...", IF(C75="No Disponible", "No Disponible", IF(D75="No Disponible", "No Disponible", IF(A75=0, "...", D75/C75*E75)))) -> 1471.6819 | G75: =IFERROR(F75-$J$3,"No Disponible") -> -0.56673873 | H75: =IFERROR(IF(A75= 0,"...",(F75-$J$3)/$J$3),"No Disponible") -> -0.00038494771
A76: PAC | B76: PAC | C76: =IFERROR(__xludf.DUMMYFUNCTION("IFERROR(googlefinance(A76),""No Disponible"")"),224.37) -> 224.37 | D76: =iferror(vlookup(A76,'Info Pesos'!$A$1:N527,2,0),"No Disponible") -> 20,760.00 | E76: 16 | F76: =IF(C76=0, "...", IF(C76="No Disponible", "No Disponible", IF(D76="No Disponible", "No Disponible", IF(A76=0, "...", D76/C76*E76)))) -> 1480.4118 | G76: =IFERROR(F76-$J$3,"No Disponible") -> 8.1631967 | H76: =IFERROR(IF(A76= 0,"...",(F76-$J$3)/$J$3),"No Disponible") -> 0.0055447134
A77: ASR | B77: ASR | C77: =IFERROR(__xludf.DUMMYFUNCTION("IFERROR(googlefinance(A77),""No Disponible"")"),317.27) -> 317.27 | D77: =iferror(vlookup(A77,'Info Pesos'!$A$1:N528,2,0),"No Disponible") -> 23,470.00 | E77: 20 | F77: =IF(C77=0, "...", IF(C77="No Disponible", "No Disponible", IF(D77="No Disponible", "No Disponible", IF(A77=0, "...", D77/C77*E77)))) -> 1479.497 | G77: =IFERROR(F77-$J$3,"No Disponible") -> 7.2483353 | H77: =IFERROR(IF(A77= 0,"...",(F77-$J$3)/$J$3),"No Disponible") -> 0.0049233093
A78: TV | B78: TV | C78: =IFERROR(__xludf.DUMMYFUNCTION("IFERROR(googlefinance(A78),""No Disponible"")"),2.85) -> 2.85 | D78: =iferror(vlookup(A78,'Info Pesos'!$A$1:N529,2,0),"No Disponible") -> No Disponible | E78: 3 | F78: =IF(C78=0, "...", IF(C78="No Disponible", "No Disponible", IF(D78="No Disponible", "No Disponible", IF(A78=0, "...", D78/C78*E78)))) -> No Disponible | G78: =IFERROR(F78-$J$3,"No Disponible") -> No Disponible | H78: =IFERROR(IF(A78= 0,"...",(F78-$J$3)/$J$3),"No Disponible") -> No Disponible
A79: BSN GR | B79: BSN GR | C79: =IFERROR(__xludf.DUMMYFUNCTION("IFERROR(googlefinance(A79),""No Disponible"")"),"No Disponible") -> No Disponible | D79: =iferror(vlookup(A79,'Info Pesos'!$A$1:N530,2,0),"No Disponible") -> No Disponible | E79: 20 | F79: =IF(C79=0, "...", IF(C79="No Disponible", "No Disponible", IF(D79="No Disponible", "No Disponible", IF(A79=0, "...", D79/C79*E79)))) -> No Disponible | G79: =IFERROR(F79-$J$3,"No Disponible") -> No Disponible | H79: =IFERROR(IF(A79= 0,"...",(F79-$J$3)/$J$3),"No Disponible") -> No Disponible
A80: HOG | B80: HOG | C80: =IFERROR(__xludf.DUMMYFUNCTION("IFERROR(googlefinance(A80),""No Disponible"")"),17.63) -> 17.63 | D80: =iferror(vlookup(A80,'Info Pesos'!$A$1:N531,2,0),"No Disponible") -> 8,650.00 | E80: 3 | F80: =IF(C80=0, "...", IF(C80="No Disponible", "No Disponible", IF(D80="No Disponible", "No Disponible", IF(A80=0, "...", D80/C80*E80)))) -> 1471.9229 | G80: =IFERROR(F80-$J$3,"No Disponible") -> -0.32576432 | H80: =IFERROR(IF(A80= 0,"...",(F80-$J$3)/$J$3),"No Disponible") -> -0.00022126991
A81: HMY | B81: HMY | C81: =IFERROR(__xludf.DUMMYFUNCTION("IFERROR(googlefinance(A81),""No Disponible"")"),15.13) -> 15.13 | D81: =iferror(vlookup(A81,'Info Pesos'!$A$1:N532,2,0),"No Disponible") -> 22,210.00 | E81: 1 | F81: =IF(C81=0, "...", IF(C81="No Disponible", "No Disponible", IF(D81="No Disponible", "No Disponible", IF(A81=0, "...", D81/C81*E81)))) -> 1467.9445 | G81: =IFERROR(F81-$J$3,"No Disponible") -> -4.3041419 | H81: =IFERROR(IF(A81= 0,"...",(F81-$J$3)/$J$3),"No Disponible") -> -0.0029235157
A82: HDB | B82: HDB | C82: =IFERROR(__xludf.DUMMYFUNCTION("IFERROR(googlefinance(A82),""No Disponible"")"),28.23) -> 28.23 | D82: =iferror(vlookup(A82,'Info Pesos'!$A$1:N533,2,0),"No Disponible") -> 20,800.00 | E82: 2 | F82: =IF(C82=0, "...", IF(C82="No Disponible", "No Disponible", IF(D82="No Disponible", "No Disponible", IF(A82=0, "...", D82/C82*E82)))) -> 1473.6096 | G82: =IFERROR(F82-$J$3,"No Disponible") -> 1.3610121 | H82: =IFERROR(IF(A82= 0,"...",(F82-$J$3)/$J$3),"No Disponible") -> 0.00092444444
A83: HL | B83: HL | C83: =IFERROR(__xludf.DUMMYFUNCTION("IFERROR(googlefinance(A83),""No Disponible"")"),19.61) -> 19.61 | D83: =iferror(vlookup(A83,'Info Pesos'!$A$1:N534,2,0),"No Disponible") -> 28,860.00 | E83: 1 | F83: =IF(C83=0, "...", IF(C83="No Disponible", "No Disponible", IF(D83="No Disponible", "No Disponible", IF(A83=0, "...", D83/C83*E83)))) -> 1471.6981 | G83: =IFERROR(F83-$J$3,"No Disponible") -> -0.55050987 | H83: =IFERROR(IF(A83= 0,"...",(F83-$J$3)/$J$3),"No Disponible") -> -0.00037392453
A84: HPQ | B84: HPQ | C84: =IFERROR(__xludf.DUMMYFUNCTION("IFERROR(googlefinance(A84),""No Disponible"")"),18.93) -> 18.93 | D84: =iferror(vlookup(A84,'Info Pesos'!$A$1:N535,2,0),"No Disponible") -> 27,720.00 | E84: 1 | F84: =IF(C84=0, "...", IF(C84="No Disponible", "No Disponible", IF(D84="No Disponible", "No Disponible", IF(A84=0, "...", D84/C84*E84)))) -> 1464.3423 | G84: =IFERROR(F84-$J$3,"No Disponible") -> -7.9063093 | H84: =IFERROR(IF(A84= 0,"...",(F84-$J$3)/$J$3),"No Disponible") -> -0.005370227
A85: HMC | B85: HMC | C85: =IFERROR(__xludf.DUMMYFUNCTION("IFERROR(googlefinance(A85),""No Disponible"")"),25.78) -> 25.78 | D85: =iferror(vlookup(A85,'Info Pesos'!$A$1:N536,2,0),"No Disponible") -> 38,000.00 | E85: 1 | F85: =IF(C85=0, "...", IF(C85="No Disponible", "No Disponible", IF(D85="No Disponible", "No Disponible", IF(A85=0, "...", D85/C85*E85)))) -> 1474.0109 | G85: =IFERROR(F85-$J$3,"No Disponible") -> 1.7622381 | H85: =IFERROR(IF(A85= 0,"...",(F85-$J$3)/$J$3),"No Disponible") -> 0.0011969704
A86: HHPD LI | B86: HHPD LI | C86: =IFERROR(__xludf.DUMMYFUNCTION("IFERROR(googlefinance(A86),""No Disponible"")"),"No Disponible") -> No Disponible | D86: =iferror(vlookup(A86,'Info Pesos'!$A$1:N537,2,0),"No Disponible") -> No Disponible | E86: 2 | F86: =IF(C86=0, "...", IF(C86="No Disponible", "No Disponible", IF(D86="No Disponible", "No Disponible", IF(A86=0, "...", D86/C86*E86)))) -> No Disponible | G86: =IFERROR(F86-$J$3,"No Disponible") -> No Disponible | H86: =IFERROR(IF(A86= 0,"...",(F86-$J$3)/$J$3),"No Disponible") -> No Disponible
A87: HON | B87: HON | C87: =IFERROR(__xludf.DUMMYFUNCTION("IFERROR(googlefinance(A87),""No Disponible"")"),234.5) -> 234.5 | D87: =iferror(vlookup(A87,'Info Pesos'!$A$1:N538,2,0),"No Disponible") -> 43,220.00 | E87: 8 | F87: =IF(C87=0, "...", IF(C87="No Disponible", "No Disponible", IF(D87="No Disponible", "No Disponible", IF(A87=0, "...", D87/C87*E87)))) -> 1474.4563 | G87: =IFERROR(F87-$J$3,"No Disponible") -> 2.2076669 | H87: =IFERROR(IF(A87= 0,"...",(F87-$J$3)/$J$3),"No Disponible") -> 0.0014995204
A88: HSBC | B88: HSBC | C88: =IFERROR(__xludf.DUMMYFUNCTION("IFERROR(googlefinance(A88),""No Disponible"")"),78.19) -> 78.19 | D88: =iferror(vlookup(A88,'Info Pesos'!$A$1:N539,2,0),"No Disponible") -> 57,350.00 | E88: 2 | F88: =IF(C88=0, "...", IF(C88="No Disponible", "No Disponible", IF(D88="No Disponible", "No Disponible", IF(A88=0, "...", D88/C88*E88)))) -> 1466.9395 | G88: =IFERROR(F88-$J$3,"No Disponible") -> -5.3091167 | H88: =IFERROR(IF(A88= 0,"...",(F88-$J$3)/$J$3),"No Disponible") -> -0.0036061278
A89: IBM | B89: IBM | C89: =IFERROR(__xludf.DUMMYFUNCTION("IFERROR(googlefinance(A89),""No Disponible"")"),246.28) -> 246.28 | D89: =iferror(vlookup(A89,'Info Pesos'!$A$1:N540,2,0),"No Disponible") -> 24,100.00 | E89: 15 | F89: =IF(C89=0, "...", IF(C89="No Disponible", "No Disponible", IF(D89="No Disponible", "No Disponible", IF(A89=0, "...", D89/C89*E89)))) -> 1467.8415 | G89: =IFERROR(F89-$J$3,"No Disponible") -> -4.4071418 | H89: =IFERROR(IF(A89= 0,"...",(F89-$J$3)/$J$3),"No Disponible") -> -0.0029934766
A90: IBN | B90: IBN | C90: =IFERROR(__xludf.DUMMYFUNCTION("IFERROR(googlefinance(A90),""No Disponible"")"),26.58) -> 26.58 | D90: =iferror(vlookup(A90,'Info Pesos'!$A$1:N541,2,0),"No Disponible") -> No Disponible | E90: 1 | F90: =IF(C90=0, "...", IF(C90="No Disponible", "No Disponible", IF(D90="No Disponible", "No Disponible", IF(A90=0, "...", D90/C90*E90)))) -> No Disponible | G90: =IFERROR(F90-$J$3,"No Disponible") -> No Disponible | H90: =IFERROR(IF(A90= 0,"...",(F90-$J$3)/$J$3),"No Disponible") -> No Disponible
A91: INFY | B91: INFY | C91: =IFERROR(__xludf.DUMMYFUNCTION("IFERROR(googlefinance(A91),""No Disponible"")"),13.27) -> 13.27 | D91: =iferror(vlookup(A91,'Info Pesos'!$A$1:N542,2,0),"No Disponible") -> 19,530.00 | E91: 1 | F91: =IF(C91=0, "...", IF(C91="No Disponible", "No Disponible", IF(D91="No Disponible", "No Disponible", IF(A91=0, "...", D91/C91*E91)))) -> 1471.7408 | G91: =IFERROR(F91-$J$3,"No Disponible") -> -0.50785443 | H91: =IFERROR(IF(A91= 0,"...",(F91-$J$3)/$J$3),"No Disponible") -> -0.00034495154
A92: ING | B92: ING | C92: =IFERROR(__xludf.DUMMYFUNCTION("IFERROR(googlefinance(A92),""No Disponible"")"),25.52) -> 25.52 | D92: =iferror(vlookup(A92,'Info Pesos'!$A$1:N543,2,0),"No Disponible") -> 12,470.00 | E92: 3 | F92: =IF(C92=0, "...", IF(C92="No Disponible", "No Disponible", IF(D92="No Disponible", "No Disponible", IF(A92=0, "...", D92/C92*E92)))) -> 1465.9091 | G92: =IFERROR(F92-$J$3,"No Disponible") -> -6.3395322 | H92: =IFERROR(IF(A92= 0,"...",(F92-$J$3)/$J$3),"No Disponible") -> -0.0043060201
A93: INTC | B93: INTC | C93: =IFERROR(__xludf.DUMMYFUNCTION("IFERROR(googlefinance(A93),""No Disponible"")"),45.77) -> 45.77 | D93: =iferror(vlookup(A93,'Info Pesos'!$A$1:N544,2,0),"No Disponible") -> 13,430.00 | E93: 5 | F93: =IF(C93=0, "...", IF(C93="No Disponible", "No Disponible", IF(D93="No Disponible", "No Disponible", IF(A93=0, "...", D93/C93*E93)))) -> 1467.1182 | G93: =IFERROR(F93-$J$3,"No Disponible") -> -5.1304234 | H93: =IFERROR(IF(A93= 0,"...",(F93-$J$3)/$J$3),"No Disponible") -> -0.0034847534
A94: IFF | B94: IFF | C94: =IFERROR(__xludf.DUMMYFUNCTION("IFERROR(googlefinance(A94),""No Disponible"")"),69.61) -> 69.61 | D94: =iferror(vlookup(A94,'Info Pesos'!$A$1:N545,2,0),"No Disponible") -> 8,550.00 | E94: 12 | F94: =IF(C94=0, "...", IF(C94="No Disponible", "No Disponible", IF(D94="No Disponible", "No Disponible", IF(A94=0, "...", D94/C94*E94)))) -> 1473.9262 | G94: =IFERROR(F94-$J$3,"No Disponible") -> 1.677537 | H94: =IFERROR(IF(A94= 0,"...",(F94-$J$3)/$J$3),"No Disponible") -> 0.0011394386
A95: IP | B95: IP | C95: =IFERROR(__xludf.DUMMYFUNCTION("IFERROR(googlefinance(A95),""No Disponible"")"),37.25) -> 37.25 | D95: =iferror(vlookup(A95,'Info Pesos'!$A$1:N546,2,0),"No Disponible") -> 13,670.00 | E95: 4 | F95: =IF(C95=0, "...", IF(C95="No Disponible", "No Disponible", IF(D95="No Disponible", "No Disponible", IF(A95=0, "...", D95/C95*E95)))) -> 1467.9195 | G95: =IFERROR(F95-$J$3,"No Disponible") -> -4.32916 | H95: =IFERROR(IF(A95= 0,"...",(F95-$J$3)/$J$3),"No Disponible") -> -0.0029405088
A96: JPM | B96: JPM | C96: =IFERROR(__xludf.DUMMYFUNCTION("IFERROR(googlefinance(A96),""No Disponible"")"),283.44) -> 283.44 | D96: =iferror(vlookup(A96,'Info Pesos'!$A$1:N547,2,0),"No Disponible") -> 27,820.00 | E96: 15 | F96: =IF(C96=0, "...", IF(C96="No Disponible", "No Disponible", IF(D96="No Disponible", "No Disponible", IF(A96=0, "...", D96/C96*E96)))) -> 1472.2693 | G96: =IFERROR(F96-$J$3,"No Disponible") -> 0.020640256 | H96: =IFERROR(IF(A96= 0,"...",(F96-$J$3)/$J$3),"No Disponible") -> 1.4019545e-05
A97: JNJ | B97: JNJ | C97: =IFERROR(__xludf.DUMMYFUNCTION("IFERROR(googlefinance(A97),""No Disponible"")"),241.52) -> 241.52 | D97: =iferror(vlookup(A97,'Info Pesos'!$A$1:N548,2,0),"No Disponible") -> No Disponible | E97: 15 | F97: =IF(C97=0, "...", IF(C97="No Disponible", "No Disponible", IF(D97="No Disponible", "No Disponible", IF(A97=0, "...", D97/C97*E97)))) -> No Disponible | G97: =IFERROR(F97-$J$3,"No Disponible") -> No Disponible | H97: =IFERROR(IF(A97= 0,"...",(F97-$J$3)/$J$3),"No Disponible") -> No Disponible
A98: KMB | B98: KMB | C98: =IFERROR(__xludf.DUMMYFUNCTION("IFERROR(googlefinance(A98),""No Disponible"")"),98.84) -> 98.84 | D98: =iferror(vlookup(A98,'Info Pesos'!$A$1:N549,2,0),"No Disponible") -> 24,260.00 | E98: 6 | F98: =IF(C98=0, "...", IF(C98="No Disponible", "No Disponible", IF(D98="No Disponible", "No Disponible", IF(A98=0, "...", D98/C98*E98)))) -> 1472.6831 | G98: =IFERROR(F98-$J$3,"No Disponible") -> 0.43450116 | H98: =IFERROR(IF(A98= 0,"...",(F98-$J$3)/$J$3),"No Disponible") -> 0.00029512757
A99: KGC | B99: KGC | C99: =IFERROR(__xludf.DUMMYFUNCTION("IFERROR(googlefinance(A99),""No Disponible"")"),30.57) -> 30.57 | D99: =iferror(vlookup(A99,'Info Pesos'!$A$1:N550,2,0),"No Disponible") -> 45,080.00 | E99: 1 | F99: =IF(C99=0, "...", IF(C99="No Disponible", "No Disponible", IF(D99="No Disponible", "No Disponible", IF(A99=0, "...", D99/C99*E99)))) -> 1474.6483 | G99: =IFERROR(F99-$J$3,"No Disponible") -> 2.399725 | H99: =IFERROR(IF(A99= 0,"...",(F99-$J$3)/$J$3),"No Disponible") -> 0.0016299726
A100: KB | B100: KB | C100: =IFERROR(__xludf.DUMMYFUNCTION("IFERROR(googlefinance(A100),""No Disponible"")"),99.47) -> 99.47 | D100: =iferror(vlookup(A100,'Info Pesos'!$A$1:N551,2,0),"No Disponible") -> No Disponible | E100: 2 | F100: =IF(C100=0, "...", IF(C100="No Disponible", "No Disponible", IF(D100="No Disponible", "No Disponible", IF(A100=0, "...", D100/C100*E100)))) -> No Disponible | G100: =IFERROR(F100-$J$3,"No Disponible") -> No Disponible | H100: =IFERROR(IF(A100= 0,"...",(F100-$J$3)/$J$3),"No Disponible") -> No Disponible
...

Sheet Info Pesos
A1: Ticker | C1: =IFERROR(__xludf.DUMMYFUNCTION("IMPORTHTML(""https://iol.invertironline.com/mercado/cotizaciones/argentina/cedears/todos"",""TABLE"",1)"),"Símbolo") -> Símbolo | D1: =IFERROR(__xludf.DUMMYFUNCTION("""COMPUTED_VALUE"""),"Último Operado") -> Último Operado | E1: =IFERROR(__xludf.DUMMYFUNCTION("""COMPUTED_VALUE"""),"Variación Diaria") -> Variación Diaria | F1: =IFERROR(__xludf.DUMMYFUNCTION("""COMPUTED_VALUE"""),"Cantidad Compra") -> Cantidad Compra | G1: =IFERROR(__xludf.DUMMYFUNCTION("""COMPUTED_VALUE"""),"Precio Compra") -> Precio Compra | H1: =IFERROR(__xludf.DUMMYFUNCTION("""COMPUTED_VALUE"""),"Precio Venta") -> Precio Venta | I1: =IFERROR(__xludf.DUMMYFUNCTION("""COMPUTED_VALUE"""),"Cantidad Venta") -> Cantidad Venta | J1: =IFERROR(__xludf.DUMMYFUNCTION("""COMPUTED_VALUE"""),"Apertura") -> Apertura | K1: =IFERROR(__xludf.DUMMYFUNCTION("""COMPUTED_VALUE"""),"Mínimo") -> Mínimo | L1: =IFERROR(__xludf.DUMMYFUNCTION("""COMPUTED_VALUE"""),"Máximo") -> Máximo | M1: =IFERROR(__xludf.DUMMYFUNCTION("""COMPUTED_VALUE"""),"Último Cierre") -> Último Cierre | N1: =IFERROR(__xludf.DUMMYFUNCTION("""COMPUTED_VALUE"""),"Monto Operado") -> Monto Operado
A2: =MID(C2, FIND("* ", C2) + 2, FIND(" *", C2, FIND("* ", C2) + 2) - FIND("* ", C2) - 2) -> AAL | B2: =SUBSTITUTE(SUBSTITUTE(SUBSTITUTE(D2, ".", "\\"), ",", "."), "\\", ",") -> 7,600.00 | C2: =IFERROR(__xludf.DUMMYFUNCTION("""COMPUTED_VALUE"""),"* AAL * Cedear American...") -> * AAL * Cedear American... | D2: =IFERROR(__xludf.DUMMYFUNCTION("""COMPUTED_VALUE"""),"7.600,00") -> 7.600,00 | E2: =IFERROR(__xludf.DUMMYFUNCTION("""COMPUTED_VALUE"""),"-1,29%") -> -1,29% | F2: =IFERROR(__xludf.DUMMYFUNCTION("""COMPUTED_VALUE"""),"-") -> - | G2: =IFERROR(__xludf.DUMMYFUNCTION("""COMPUTED_VALUE"""),"-") -> - | H2: =IFERROR(__xludf.DUMMYFUNCTION("""COMPUTED_VALUE"""),"-") -> - | I2: =IFERROR(__xludf.DUMMYFUNCTION("""COMPUTED_VALUE"""),"-") -> - | J2: =IFERROR(__xludf.DUMMYFUNCTION("""COMPUTED_VALUE"""),"7.690,00") -> 7.690,00 | K2: =IFERROR(__xludf.DUMMYFUNCTION("""COMPUTED_VALUE"""),"7.545,00") -> 7.545,00 | L2: =IFERROR(__xludf.DUMMYFUNCTION("""COMPUTED_VALUE"""),"7.750,00") -> 7.750,00 | M2: =IFERROR(__xludf.DUMMYFUNCTION("""COMPUTED_VALUE"""),"7.600,00") -> 7.600,00 | N2: =IFERROR(__xludf.DUMMYFUNCTION("""COMPUTED_VALUE"""),"180.301.175") -> 180.301.175
A3: =MID(C3, FIND("* ", C3) + 2, FIND(" *", C3, FIND("* ", C3) + 2) - FIND("* ", C3) - 2) -> AALC | B3: =SUBSTITUTE(SUBSTITUTE(SUBSTITUTE(D3, ".", "\\"), ",", "."), "\\", ",") -> 5.38 | C3: =IFERROR(__xludf.DUMMYFUNCTION("""COMPUTED_VALUE"""),"* AALC * Cedear American...") -> * AALC * Cedear American... | D3: =IFERROR(__xludf.DUMMYFUNCTION("""COMPUTED_VALUE"""),"5,38") -> 5,38 | E3: =IFERROR(__xludf.DUMMYFUNCTION("""COMPUTED_VALUE"""),"-3,06%") -> -3,06% | F3: =IFERROR(__xludf.DUMMYFUNCTION("""COMPUTED_VALUE"""),"-") -> - | G3: =IFERROR(__xludf.DUMMYFUNCTION("""COMPUTED_VALUE"""),"-") -> - | H3: =IFERROR(__xludf.DUMMYFUNCTION("""COMPUTED_VALUE"""),"-") -> - | I3: =IFERROR(__xludf.DUMMYFUNCTION("""COMPUTED_VALUE"""),"-") -> - | J3: =IFERROR(__xludf.DUMMYFUNCTION("""COMPUTED_VALUE"""),"5,22") -> 5,22 | K3: =IFERROR(__xludf.DUMMYFUNCTION("""COMPUTED_VALUE"""),"5,22") -> 5,22 | L3: =IFERROR(__xludf.DUMMYFUNCTION("""COMPUTED_VALUE"""),"5,22") -> 5,22 | M3: =IFERROR(__xludf.DUMMYFUNCTION("""COMPUTED_VALUE"""),"5,38") -> 5,38 | N3: =IFERROR(__xludf.DUMMYFUNCTION("""COMPUTED_VALUE"""),47.0) -> 47
A4: =MID(C4, FIND("* ", C4) + 2, FIND(" *", C4, FIND("* ", C4) + 2) - FIND("* ", C4) - 2) -> AALD | B4: =SUBSTITUTE(SUBSTITUTE(SUBSTITUTE(D4, ".", "\\"), ",", "."), "\\", ",") -> 5.29 | C4: =IFERROR(__xludf.DUMMYFUNCTION("""COMPUTED_VALUE"""),"* AALD * Cedear American...") -> * AALD * Cedear American... | D4: =IFERROR(__xludf.DUMMYFUNCTION("""COMPUTED_VALUE"""),"5,29") -> 5,29 | E4: =IFERROR(__xludf.DUMMYFUNCTION("""COMPUTED_VALUE"""),"-3,64%") -> -3,64% | F4: =IFERROR(__xludf.DUMMYFUNCTION("""COMPUTED_VALUE"""),"-") -> - | G4: =IFERROR(__xludf.DUMMYFUNCTION("""COMPUTED_VALUE"""),"-") -> - | H4: =IFERROR(__xludf.DUMMYFUNCTION("""COMPUTED_VALUE"""),"-") -> - | I4: =IFERROR(__xludf.DUMMYFUNCTION("""COMPUTED_VALUE"""),"-") -> - | J4: =IFERROR(__xludf.DUMMYFUNCTION("""COMPUTED_VALUE"""),"5,51") -> 5,51 | K4: =IFERROR(__xludf.DUMMYFUNCTION("""COMPUTED_VALUE"""),"5,31") -> 5,31 | L4: =IFERROR(__xludf.DUMMYFUNCTION("""COMPUTED_VALUE"""),"5,59") -> 5,59 | M4: =IFERROR(__xludf.DUMMYFUNCTION("""COMPUTED_VALUE"""),"5,29") -> 5,29 | N4: =IFERROR(__xludf.DUMMYFUNCTION("""COMPUTED_VALUE"""),13.742) -> 13.742
A5: =MID(C5, FIND("* ", C5) + 2, FIND(" *", C5, FIND("* ", C5) + 2) - FIND("* ", C5) - 2) -> AAP | B5: =SUBSTITUTE(SUBSTITUTE(SUBSTITUTE(D5, ".", "\\"), ",", "."), "\\", ",") -> 5,410.00 | C5: =IFERROR(__xludf.DUMMYFUNCTION("""COMPUTED_VALUE"""),"* AAP * Cedear Advance ...") -> * AAP * Cedear Advance ... | D5: =IFERROR(__xludf.DUMMYFUNCTION("""COMPUTED_VALUE"""),"5.410,00") -> 5.410,00 | E5: =IFERROR(__xludf.DUMMYFUNCTION("""COMPUTED_VALUE"""),"-1,63%") -> -1,63% | F5: =IFERROR(__xludf.DUMMYFUNCTION("""COMPUTED_VALUE"""),"-") -> - | G5: =IFERROR(__xludf.DUMMYFUNCTION("""COMPUTED_VALUE"""),"-") -> - | H5: =IFERROR(__xludf.DUMMYFUNCTION("""COMPUTED_VALUE"""),"-") -> - | I5: =IFERROR(__xludf.DUMMYFUNCTION("""COMPUTED_VALUE"""),"-") -> - | J5: =IFERROR(__xludf.DUMMYFUNCTION("""COMPUTED_VALUE"""),"5.455,00") -> 5.455,00 | K5: =IFERROR(__xludf.DUMMYFUNCTION("""COMPUTED_VALUE"""),"5.275,00") -> 5.275,00 | L5: =IFERROR(__xludf.DUMMYFUNCTION("""COMPUTED_VALUE"""),"5.580,00") -> 5.580,00 | M5: =IFERROR(__xludf.DUMMYFUNCTION("""COMPUTED_VALUE"""),"5.410,00") -> 5.410,00 | N5: =IFERROR(__xludf.DUMMYFUNCTION("""COMPUTED_VALUE"""),"5.998.520") -> 5.998.520
A6: =MID(C6, FIND("* ", C6) + 2, FIND(" *", C6, FIND("* ", C6) + 2) - FIND("* ", C6) - 2) -> AAPL | B6: =SUBSTITUTE(SUBSTITUTE(SUBSTITUTE(D6, ".", "\\"), ",", "."), "\\", ",") -> 18,410.00 | C6: =IFERROR(__xludf.DUMMYFUNCTION("""COMPUTED_VALUE"""),"* AAPL * Cedear Apple Inc.") -> * AAPL * Cedear Apple Inc. | D6: =IFERROR(__xludf.DUMMYFUNCTION("""COMPUTED_VALUE"""),"18.410,00") -> 18.410,00 | E6: =IFERROR(__xludf.DUMMYFUNCTION("""COMPUTED_VALUE"""),"-1,12%") -> -1,12% | F6: =IFERROR(__xludf.DUMMYFUNCTION("""COMPUTED_VALUE"""),"-") -> - | G6: =IFERROR(__xludf.DUMMYFUNCTION("""COMPUTED_VALUE"""),"-") -> - | H6: =IFERROR(__xludf.DUMMYFUNCTION("""COMPUTED_VALUE"""),"-") -> - | I6: =IFERROR(__xludf.DUMMYFUNCTION("""COMPUTED_VALUE"""),"-") -> - | J6: =IFERROR(__xludf.DUMMYFUNCTION("""COMPUTED_VALUE"""),"18.650,00") -> 18.650,00 | K6: =IFERROR(__xludf.DUMMYFUNCTION("""COMPUTED_VALUE"""),"18.300,00") -> 18.300,00 | L6: =IFERROR(__xludf.DUMMYFUNCTION("""COMPUTED_VALUE"""),"18.680,00") -> 18.680,00 | M6: =IFERROR(__xludf.DUMMYFUNCTION("""COMPUTED_VALUE"""),"18.620,00") -> 18.620,00 | N6: =IFERROR(__xludf.DUMMYFUNCTION("""COMPUTED_VALUE"""),"724.994.300") -> 724.994.300
A7: =MID(C7, FIND("* ", C7) + 2, FIND(" *", C7, FIND("* ", C7) + 2) - FIND("* ", C7) - 2) -> AAPLC | B7: =SUBSTITUTE(SUBSTITUTE(SUBSTITUTE(D7, ".", "\\"), ",", "."), "\\", ",") -> 12.58 | C7: =IFERROR(__xludf.DUMMYFUNCTION("""COMPUTED_VALUE"""),"* AAPLC * Cedear Apple Inc.") -> * AAPLC * Cedear Apple Inc. | D7: =IFERROR(__xludf.DUMMYFUNCTION("""COMPUTED_VALUE"""),"12,58") -> 12,58 | E7: =IFERROR(__xludf.DUMMYFUNCTION("""COMPUTED_VALUE"""),"-1,64%") -> -1,64% | F7: =IFERROR(__xludf.DUMMYFUNCTION("""COMPUTED_VALUE"""),"-") -> - | G7: =IFERROR(__xludf.DUMMYFUNCTION("""COMPUTED_VALUE"""),"-") -> - | H7: =IFERROR(__xludf.DUMMYFUNCTION("""COMPUTED_VALUE"""),"-") -> - | I7: =IFERROR(__xludf.DUMMYFUNCTION("""COMPUTED_VALUE"""),"-") -> - | J7: =IFERROR(__xludf.DUMMYFUNCTION("""COMPUTED_VALUE"""),"12,72") -> 12,72 | K7: =IFERROR(__xludf.DUMMYFUNCTION("""COMPUTED_VALUE"""),"12,59") -> 12,59 | L7: =IFERROR(__xludf.DUMMYFUNCTION("""COMPUTED_VALUE"""),"12,72") -> 12,72 | M7: =IFERROR(__xludf.DUMMYFUNCTION("""COMPUTED_VALUE"""),"12,58") -> 12,58 | N7: =IFERROR(__xludf.DUMMYFUNCTION("""COMPUTED_VALUE"""),51.0) -> 51
A8: =MID(C8, FIND("* ", C8) + 2, FIND(" *", C8, FIND("* ", C8) + 2) - FIND("* ", C8) - 2) -> AAPLD | B8: =SUBSTITUTE(SUBSTITUTE(SUBSTITUTE(D8, ".", "\\"), ",", "."), "\\", ",") -> 12.92 | C8: =IFERROR(__xludf.DUMMYFUNCTION("""COMPUTED_VALUE"""),"* AAPLD * Cedear Apple Inc.") -> * AAPLD * Cedear Apple Inc. | D8: =IFERROR(__xludf.DUMMYFUNCTION("""COMPUTED_VALUE"""),"12,92") -> 12,92 | E8: =IFERROR(__xludf.DUMMYFUNCTION("""COMPUTED_VALUE"""),"-1,89%") -> -1,89% | F8: =IFERROR(__xludf.DUMMYFUNCTION("""COMPUTED_VALUE"""),"-") -> - | G8: =IFERROR(__xludf.DUMMYFUNCTION("""COMPUTED_VALUE"""),"-") -> - | H8: =IFERROR(__xludf.DUMMYFUNCTION("""COMPUTED_VALUE"""),"-") -> - | I8: =IFERROR(__xludf.DUMMYFUNCTION("""COMPUTED_VALUE"""),"-") -> - | J8: =IFERROR(__xludf.DUMMYFUNCTION("""COMPUTED_VALUE"""),"13,35") -> 13,35 | K8: =IFERROR(__xludf.DUMMYFUNCTION("""COMPUTED_VALUE"""),"12,92") -> 12,92 | L8: =IFERROR(__xludf.DUMMYFUNCTION("""COMPUTED_VALUE"""),"13,35") -> 13,35 | M8: =IFERROR(__xludf.DUMMYFUNCTION("""COMPUTED_VALUE"""),"12,92") -> 12,92 | N8: =IFERROR(__xludf.DUMMYFUNCTION("""COMPUTED_VALUE"""),39.289) -> 39.289
A9: =MID(C9, FIND("* ", C9) + 2, FIND(" *", C9, FIND("* ", C9) + 2) - FIND("* ", C9) - 2) -> ABBV | B9: =SUBSTITUTE(SUBSTITUTE(SUBSTITUTE(D9, ".", "\\"), ",", "."), "\\", ",") -> 32,400.00 | C9: =IFERROR(__xludf.DUMMYFUNCTION("""COMPUTED_VALUE"""),"* ABBV * Cedear Abbvie Inc.") -> * ABBV * Cedear Abbvie Inc. | D9: =IFERROR(__xludf.DUMMYFUNCTION("""COMPUTED_VALUE"""),"32.400,00") -> 32.400,00 | E9: =IFERROR(__xludf.DUMMYFUNCTION("""COMPUTED_VALUE"""),"-1,15%") -> -1,15% | F9: =IFERROR(__xludf.DUMMYFUNCTION("""COMPUTED_VALUE"""),"-") -> - | G9: =IFERROR(__xludf.DUMMYFUNCTION("""COMPUTED_VALUE"""),"-") -> - | H9: =IFERROR(__xludf.DUMMYFUNCTION("""COMPUTED_VALUE"""),"-") -> - | I9: =IFERROR(__xludf.DUMMYFUNCTION("""COMPUTED_VALUE"""),"-") -> - | J9: =IFERROR(__xludf.DUMMYFUNCTION("""COMPUTED_VALUE"""),"33.220,00") -> 33.220,00 | K9: =IFERROR(__xludf.DUMMYFUNCTION("""COMPUTED_VALUE"""),"32.240,00") -> 32.240,00 | L9: =IFERROR(__xludf.DUMMYFUNCTION("""COMPUTED_VALUE"""),"33.220,00") -> 33.220,00 | M9: =IFERROR(__xludf.DUMMYFUNCTION("""COMPUTED_VALUE"""),"32.400,00") -> 32.400,00 | N9: =IFERROR(__xludf.DUMMYFUNCTION("""COMPUTED_VALUE"""),"16.948.040") -> 16.948.040
A10: =MID(C10, FIND("* ", C10) + 2, FIND(" *", C10, FIND("* ", C10) + 2) - FIND("* ", C10) - 2) -> ABBVC | B10: =SUBSTITUTE(SUBSTITUTE(SUBSTITUTE(D10, ".", "\\"), ",", "."), "\\", ",") -> 22.23 | C10: =IFERROR(__xludf.DUMMYFUNCTION("""COMPUTED_VALUE"""),"* ABBVC * Cedear Abbvie Inc.") -> * ABBVC * Cedear Abbvie Inc. | D10: =IFERROR(__xludf.DUMMYFUNCTION("""COMPUTED_VALUE"""),"22,23") -> 22,23 | E10: =IFERROR(__xludf.DUMMYFUNCTION("""COMPUTED_VALUE"""),0.0) -> 0 | F10: =IFERROR(__xludf.DUMMYFUNCTION("""COMPUTED_VALUE"""),"-") -> - | G10: =IFERROR(__xludf.DUMMYFUNCTION("""COMPUTED_VALUE"""),"-") -> - | H10: =IFERROR(__xludf.DUMMYFUNCTION("""COMPUTED_VALUE"""),"-") -> - | I10: =IFERROR(__xludf.DUMMYFUNCTION("""COMPUTED_VALUE"""),"-") -> - | J10: =IFERROR(__xludf.DUMMYFUNCTION("""COMPUTED_VALUE"""),"22,99") -> 22,99 | K10: =IFERROR(__xludf.DUMMYFUNCTION("""COMPUTED_VALUE"""),"0,00") -> 0,00 | L10: =IFERROR(__xludf.DUMMYFUNCTION("""COMPUTED_VALUE"""),"0,00") -> 0,00 | M10: =IFERROR(__xludf.DUMMYFUNCTION("""COMPUTED_VALUE"""),"22,23") -> 22,23 | N10: =IFERROR(__xludf.DUMMYFUNCTION("""COMPUTED_VALUE"""),0.0) -> 0
A11: =MID(C11, FIND("* ", C11) + 2, FIND(" *", C11, FIND("* ", C11) + 2) - FIND("* ", C11) - 2) -> ABBVD | B11: =SUBSTITUTE(SUBSTITUTE(SUBSTITUTE(D11, ".", "\\"), ",", "."), "\\", ",") -> 22.95 | C11: =IFERROR(__xludf.DUMMYFUNCTION("""COMPUTED_VALUE"""),"* ABBVD * Cedear Abbvie Inc.") -> * ABBVD * Cedear Abbvie Inc. | D11: =IFERROR(__xludf.DUMMYFUNCTION("""COMPUTED_VALUE"""),"22,95") -> 22,95 | E11: =IFERROR(__xludf.DUMMYFUNCTION("""COMPUTED_VALUE"""),"-0,52%") -> -0,52% | F11: =IFERROR(__xludf.DUMMYFUNCTION("""COMPUTED_VALUE"""),"-") -> - | G11: =IFERROR(__xludf.DUMMYFUNCTION("""COMPUTED_VALUE"""),"-") -> - | H11: =IFERROR(__xludf.DUMMYFUNCTION("""COMPUTED_VALUE"""),"-") -> - | I11: =IFERROR(__xludf.DUMMYFUNCTION("""COMPUTED_VALUE"""),"-") -> - | J11: =IFERROR(__xludf.DUMMYFUNCTION("""COMPUTED_VALUE"""),"22,98") -> 22,98 | K11: =IFERROR(__xludf.DUMMYFUNCTION("""COMPUTED_VALUE"""),"22,98") -> 22,98 | L11: =IFERROR(__xludf.DUMMYFUNCTION("""COMPUTED_VALUE"""),"23,00") -> 23,00 | M11: =IFERROR(__xludf.DUMMYFUNCTION("""COMPUTED_VALUE"""),"22,95") -> 22,95 | N11: =IFERROR(__xludf.DUMMYFUNCTION("""COMPUTED_VALUE"""),621.0) -> 621
A12: =MID(C12, FIND("* ", C12) + 2, FIND(" *", C12, FIND("* ", C12) + 2) - FIND("* ", C12) - 2) -> ABEV | B12: =SUBSTITUTE(SUBSTITUTE(SUBSTITUTE(D12, ".", "\\"), ",", "."), "\\", ",") -> 12,650.00 | C12: =IFERROR(__xludf.DUMMYFUNCTION("""COMPUTED_VALUE"""),"* ABEV * Cedear Ambev S.A.") -> * ABEV * Cedear Ambev S.A. | D12: =IFERROR(__xludf.DUMMYFUNCTION("""COMPUTED_VALUE"""),"12.650,00") -> 12.650,00 | E12: =IFERROR(__xludf.DUMMYFUNCTION("""COMPUTED_VALUE"""),"1,52%") -> 1,52% | F12: =IFERROR(__xludf.DUMMYFUNCTION("""COMPUTED_VALUE"""),"-") -> - | G12: =IFERROR(__xludf.DUMMYFUNCTION("""COMPUTED_VALUE"""),"-") -> - | H12: =IFERROR(__xludf.DUMMYFUNCTION("""COMPUTED_VALUE"""),"-") -> - | I12: =IFERROR(__xludf.DUMMYFUNCTION("""COMPUTED_VALUE"""),"-") -> - | J12: =IFERROR(__xludf.DUMMYFUNCTION("""COMPUTED_VALUE"""),"12.600,00") -> 12.600,00 | K12: =IFERROR(__xludf.DUMMYFUNCTION("""COMPUTED_VALUE"""),"12.510,00") -> 12.510,00 | L12: =IFERROR(__xludf.DUMMYFUNCTION("""COMPUTED_VALUE"""),"12.800,00") -> 12.800,00 | M12: =IFERROR(__xludf.DUMMYFUNCTION("""COMPUTED_VALUE"""),"12.650,00") -> 12.650,00 | N12: =IFERROR(__xludf.DUMMYFUNCTION("""COMPUTED_VALUE"""),"16.157.700") -> 16.157.700
A13: =MID(C13, FIND("* ", C13) + 2, FIND(" *", C13, FIND("* ", C13) + 2) - FIND("* ", C13) - 2) -> ABEVD | B13: =SUBSTITUTE(SUBSTITUTE(SUBSTITUTE(D13, ".", "\\"), ",", "."), "\\", ",") -> 9.00 | C13: =IFERROR(__xludf.DUMMYFUNCTION("""COMPUTED_VALUE"""),"* ABEVD * Cedear Ambev S.A.") -> * ABEVD * Cedear Ambev S.A. | D13: =IFERROR(__xludf.DUMMYFUNCTION("""COMPUTED_VALUE"""),"9,00") -> 9,00 | E13: =IFERROR(__xludf.DUMMYFUNCTION("""COMPUTED_VALUE"""),"0,55%") -> 0,55% | F13: =IFERROR(__xludf.DUMMYFUNCTION("""COMPUTED_VALUE"""),"-") -> - | G13: =IFERROR(__xludf.DUMMYFUNCTION("""COMPUTED_VALUE"""),"-") -> - | H13: =IFERROR(__xludf.DUMMYFUNCTION("""COMPUTED_VALUE"""),"-") -> - | I13: =IFERROR(__xludf.DUMMYFUNCTION("""COMPUTED_VALUE"""),"-") -> - | J13: =IFERROR(__xludf.DUMMYFUNCTION("""COMPUTED_VALUE"""),"9,00") -> 9,00 | K13: =IFERROR(__xludf.DUMMYFUNCTION("""COMPUTED_VALUE"""),"9,00") -> 9,00 | L13: =IFERROR(__xludf.DUMMYFUNCTION("""COMPUTED_VALUE"""),"9,01") -> 9,01 | M13: =IFERROR(__xludf.DUMMYFUNCTION("""COMPUTED_VALUE"""),"9,00") -> 9,00 | N13: =IFERROR(__xludf.DUMMYFUNCTION("""COMPUTED_VALUE"""),414.0) -> 414
A14: =MID(C14, FIND("* ", C14) + 2, FIND(" *", C14, FIND("* ", C14) + 2) - FIND("* ", C14) - 2) -> ABNB | B14: =SUBSTITUTE(SUBSTITUTE(SUBSTITUTE(D14, ".", "\\"), ",", "."), "\\", ",") -> 12,380.00 | C14: =IFERROR(__xludf.DUMMYFUNCTION("""COMPUTED_VALUE"""),"* ABNB * Cedear Airbnb Inc.") -> * ABNB * Cedear Airbnb Inc. | D14: =IFERROR(__xludf.DUMMYFUNCTION("""COMPUTED_VALUE"""),"12.380,00") -> 12.380,00 | E14: =IFERROR(__xludf.DUMMYFUNCTION("""COMPUTED_VALUE"""),"-0,24%") -> -0,24% | F14: =IFERROR(__xludf.DUMMYFUNCTION("""COMPUTED_VALUE"""),"-") -> - | G14: =IFERROR(__xludf.DUMMYFUNCTION("""COMPUTED_VALUE"""),"-") -> - | H14: =IFERROR(__xludf.DUMMYFUNCTION("""COMPUTED_VALUE"""),"-") -> - | I14: =IFERROR(__xludf.DUMMYFUNCTION("""COMPUTED_VALUE"""),"-") -> - | J14: =IFERROR(__xludf.DUMMYFUNCTION("""COMPUTED_VALUE"""),"12.470,00") -> 12.470,00 | K14: =IFERROR(__xludf.DUMMYFUNCTION("""COMPUTED_VALUE"""),"12.230,00") -> 12.230,00 | L14: =IFERROR(__xludf.DUMMYFUNCTION("""COMPUTED_VALUE"""),"12.490,00") -> 12.490,00 | M14: =IFERROR(__xludf.DUMMYFUNCTION("""COMPUTED_VALUE"""),"12.380,00") -> 12.380,00 | N14: =IFERROR(__xludf.DUMMYFUNCTION("""COMPUTED_VALUE"""),"75.978.100") -> 75.978.100
A15: =MID(C15, FIND("* ", C15) + 2, FIND(" *", C15, FIND("* ", C15) + 2) - FIND("* ", C15) - 2) -> ABNBC | B15: =SUBSTITUTE(SUBSTITUTE(SUBSTITUTE(D15, ".", "\\"), ",", "."), "\\", ",") -> 9.14 | C15: =IFERROR(__xludf.DUMMYFUNCTION("""COMPUTED_VALUE"""),"* ABNBC * Cedear Airbnb Inc.") -> * ABNBC * Cedear Airbnb Inc. | D15: =IFERROR(__xludf.DUMMYFUNCTION("""COMPUTED_VALUE"""),"9,14") -> 9,14 | E15: =IFERROR(__xludf.DUMMYFUNCTION("""COMPUTED_VALUE"""),0.0) -> 0 | F15: =IFERROR(__xludf.DUMMYFUNCTION("""COMPUTED_VALUE"""),"-") -> - | G15: =IFERROR(__xludf.DUMMYFUNCTION("""COMPUTED_VALUE"""),"-") -> - | H15: =IFERROR(__xludf.DUMMYFUNCTION("""COMPUTED_VALUE"""),"-") -> - | I15: =IFERROR(__xludf.DUMMYFUNCTION("""COMPUTED_VALUE"""),"-") -> - | J15: =IFERROR(__xludf.DUMMYFUNCTION("""COMPUTED_VALUE"""),"8,78") -> 8,78 | K15: =IFERROR(__xludf.DUMMYFUNCTION("""COMPUTED_VALUE"""),"8,78") -> 8,78 | L15: =IFERROR(__xludf.DUMMYFUNCTION("""COMPUTED_VALUE"""),"8,78") -> 8,78 | M15: =IFERROR(__xludf.DUMMYFUNCTION("""COMPUTED_VALUE"""),"9,14") -> 9,14 | N15: =IFERROR(__xludf.DUMMYFUNCTION("""COMPUTED_VALUE"""),0.0) -> 0
A16: =MID(C16, FIND("* ", C16) + 2, FIND(" *", C16, FIND("* ", C16) + 2) - FIND("* ", C16) - 2) -> ABNBD | B16: =SUBSTITUTE(SUBSTITUTE(SUBSTITUTE(D16, ".", "\\"), ",", "."), "\\", ",") -> 8.65 | C16: =IFERROR(__xludf.DUMMYFUNCTION("""COMPUTED_VALUE"""),"* ABNBD * Cedear Airbnb Inc.") -> * ABNBD * Cedear Airbnb Inc. | D16: =IFERROR(__xludf.DUMMYFUNCTION("""COMPUTED_VALUE"""),"8,65") -> 8,65 | E16: =IFERROR(__xludf.DUMMYFUNCTION("""COMPUTED_VALUE"""),"-2,59%") -> -2,59% | F16: =IFERROR(__xludf.DUMMYFUNCTION("""COMPUTED_VALUE"""),"-") -> - | G16: =IFERROR(__xludf.DUMMYFUNCTION("""COMPUTED_VALUE"""),"-") -> - | H16: =IFERROR(__xludf.DUMMYFUNCTION("""COMPUTED_VALUE"""),"-") -> - | I16: =IFERROR(__xludf.DUMMYFUNCTION("""COMPUTED_VALUE"""),"-") -> - | J16: =IFERROR(__xludf.DUMMYFUNCTION("""COMPUTED_VALUE"""),"8,75") -> 8,75 | K16: =IFERROR(__xludf.DUMMYFUNCTION("""COMPUTED_VALUE"""),"8,74") -> 8,74 | L16: =IFERROR(__xludf.DUMMYFUNCTION("""COMPUTED_VALUE"""),"8,88") -> 8,88 | M16: =IFERROR(__xludf.DUMMYFUNCTION("""COMPUTED_VALUE"""),"8,65") -> 8,65 | N16: =IFERROR(__xludf.DUMMYFUNCTION("""COMPUTED_VALUE"""),796.0) -> 796
A17: =MID(C17, FIND("* ", C17) + 2, FIND(" *", C17, FIND("* ", C17) + 2) - FIND("* ", C17) - 2) -> ABT | B17: =SUBSTITUTE(SUBSTITUTE(SUBSTITUTE(D17, ".", "\\"), ",", "."), "\\", ",") -> 39,580.00 | C17: =IFERROR(__xludf.DUMMYFUNCTION("""COMPUTED_VALUE"""),"* ABT * Cedear Abbott L...") -> * ABT * Cedear Abbott L... | D17: =IFERROR(__xludf.DUMMYFUNCTION("""COMPUTED_VALUE"""),"39.580,00") -> 39.580,00 | E17: =IFERROR(__xludf.DUMMYFUNCTION("""COMPUTED_VALUE"""),"0,25%") -> 0,25% | F17: =IFERROR(__xludf.DUMMYFUNCTION("""COMPUTED_VALUE"""),"-") -> - | G17: =IFERROR(__xludf.DUMMYFUNCTION("""COMPUTED_VALUE"""),"-") -> - | H17: =IFERROR(__xludf.DUMMYFUNCTION("""COMPUTED_VALUE"""),"-") -> - | I17: =IFERROR(__xludf.DUMMYFUNCTION("""COMPUTED_VALUE"""),"-") -> - | J17: =IFERROR(__xludf.DUMMYFUNCTION("""COMPUTED_VALUE"""),"40.000,00") -> 40.000,00 | K17: =IFERROR(__xludf.DUMMYFUNCTION("""COMPUTED_VALUE"""),"39.320,00") -> 39.320,00 | L17: =IFERROR(__xludf.DUMMYFUNCTION("""COMPUTED_VALUE"""),"40.000,00") -> 40.000,00 | M17: =IFERROR(__xludf.DUMMYFUNCTION("""COMPUTED_VALUE"""),"39.580,00") -> 39.580,00 | N17: =IFERROR(__xludf.DUMMYFUNCTION("""COMPUTED_VALUE"""),"3.133.780") -> 3.133.780
A18: =MID(C18, FIND("* ", C18) + 2, FIND(" *", C18, FIND("* ", C18) + 2) - FIND("* ", C18) - 2) -> ABTD | B18: =SUBSTITUTE(SUBSTITUTE(SUBSTITUTE(D18, ".", "\\"), ",", "."), "\\", ",") -> 28.38 | C18: =IFERROR(__xludf.DUMMYFUNCTION("""COMPUTED_VALUE"""),"* ABTD * Cedear Abbott L...") -> * ABTD * Cedear Abbott L... | D18: =IFERROR(__xludf.DUMMYFUNCTION("""COMPUTED_VALUE"""),"28,38") -> 28,38 | E18: =IFERROR(__xludf.DUMMYFUNCTION("""COMPUTED_VALUE"""),"2,41%") -> 2,41% | F18: =IFERROR(__xludf.DUMMYFUNCTION("""COMPUTED_VALUE"""),"-") -> - | G18: =IFERROR(__xludf.DUMMYFUNCTION("""COMPUTED_VALUE"""),"-") -> - | H18: =IFERROR(__xludf.DUMMYFUNCTION("""COMPUTED_VALUE"""),"-") -> - | I18: =IFERROR(__xludf.DUMMYFUNCTION("""COMPUTED_VALUE"""),"-") -> - | J18: =IFERROR(__xludf.DUMMYFUNCTION("""COMPUTED_VALUE"""),"27,75") -> 27,75 | K18: =IFERROR(__xludf.DUMMYFUNCTION("""COMPUTED_VALUE"""),"27,75") -> 27,75 | L18: =IFERROR(__xludf.DUMMYFUNCTION("""COMPUTED_VALUE"""),"27,75") -> 27,75 | M18: =IFERROR(__xludf.DUMMYFUNCTION("""COMPUTED_VALUE"""),"28,38") -> 28,38 | N18: =IFERROR(__xludf.DUMMYFUNCTION("""COMPUTED_VALUE"""),56.0) -> 56
A19: =MID(C19, FIND("* ", C19) + 2, FIND(" *", C19, FIND("* ", C19) + 2) - FIND("* ", C19) - 2) -> ACN | B19: =SUBSTITUTE(SUBSTITUTE(SUBSTITUTE(D19, ".", "\\"), ",", "."), "\\", ",") -> 3,815.00 | C19: =IFERROR(__xludf.DUMMYFUNCTION("""COMPUTED_VALUE"""),"* ACN * Cedear Accentur...") -> * ACN * Cedear Accentur... | D19: =IFERROR(__xludf.DUMMYFUNCTION("""COMPUTED_VALUE"""),"3.815,00") -> 3.815,00 | E19: =IFERROR(__xludf.DUMMYFUNCTION("""COMPUTED_VALUE"""),"-0,39%") -> -0,39% | F19: =IFERROR(__xludf.DUMMYFUNCTION("""COMPUTED_VALUE"""),"-") -> - | G19: =IFERROR(__xludf.DUMMYFUNCTION("""COMPUTED_VALUE"""),"-") -> - | H19: =IFERROR(__xludf.DUMMYFUNCTION("""COMPUTED_VALUE"""),"-") -> - | I19: =IFERROR(__xludf.DUMMYFUNCTION("""COMPUTED_VALUE"""),"-") -> - | J19: =IFERROR(__xludf.DUMMYFUNCTION("""COMPUTED_VALUE"""),"3.802,50") -> 3.802,50 | K19: =IFERROR(__xludf.DUMMYFUNCTION("""COMPUTED_VALUE"""),"3.787,50") -> 3.787,50 | L19: =IFERROR(__xludf.DUMMYFUNCTION("""COMPUTED_VALUE"""),"3.872,50") -> 3.872,50 | M19: =IFERROR(__xludf.DUMMYFUNCTION("""COMPUTED_VALUE"""),"3.815,00") -> 3.815,00 | N19: =IFERROR(__xludf.DUMMYFUNCTION("""COMPUTED_VALUE"""),"60.255.753") -> 60.255.753
A20: =MID(C20, FIND("* ", C20) + 2, FIND(" *", C20, FIND("* ", C20) + 2) - FIND("* ", C20) - 2) -> ACND | B20: =SUBSTITUTE(SUBSTITUTE(SUBSTITUTE(D20, ".", "\\"), ",", "."), "\\", ",") -> 2.74 | C20: =IFERROR(__xludf.DUMMYFUNCTION("""COMPUTED_VALUE"""),"* ACND * Cedear Accentur...") -> * ACND * Cedear Accentur... | D20: =IFERROR(__xludf.DUMMYFUNCTION("""COMPUTED_VALUE"""),"2,74") -> 2,74 | E20: =IFERROR(__xludf.DUMMYFUNCTION("""COMPUTED_VALUE"""),"0,36%") -> 0,36% | F20: =IFERROR(__xludf.DUMMYFUNCTION("""COMPUTED_VALUE"""),"-") -> - | G20: =IFERROR(__xludf.DUMMYFUNCTION("""COMPUTED_VALUE"""),"-") -> - | H20: =IFERROR(__xludf.DUMMYFUNCTION("""COMPUTED_VALUE"""),"-") -> - | I20: =IFERROR(__xludf.DUMMYFUNCTION("""COMPUTED_VALUE"""),"-") -> - | J20: =IFERROR(__xludf.DUMMYFUNCTION("""COMPUTED_VALUE"""),"2,69") -> 2,69 | K20: =IFERROR(__xludf.DUMMYFUNCTION("""COMPUTED_VALUE"""),"2,68") -> 2,68 | L20: =IFERROR(__xludf.DUMMYFUNCTION("""COMPUTED_VALUE"""),"2,77") -> 2,77 | M20: =IFERROR(__xludf.DUMMYFUNCTION("""COMPUTED_VALUE"""),"2,74") -> 2,74 | N20: =IFERROR(__xludf.DUMMYFUNCTION("""COMPUTED_VALUE"""),3.128) -> 3.128
A21: =MID(C21, FIND("* ", C21) + 2, FIND(" *", C21, FIND("* ", C21) + 2) - FIND("* ", C21) - 2) -> ACWI | B21: =SUBSTITUTE(SUBSTITUTE(SUBSTITUTE(D21, ".", "\\"), ",", "."), "\\", ",") -> 7,900.00 | C21: =IFERROR(__xludf.DUMMYFUNCTION("""COMPUTED_VALUE"""),"* ACWI * Cedear Ishares ...") -> * ACWI * Cedear Ishares ... | D21: =IFERROR(__xludf.DUMMYFUNCTION("""COMPUTED_VALUE"""),"7.900,00") -> 7.900,00 | E21: =IFERROR(__xludf.DUMMYFUNCTION("""COMPUTED_VALUE"""),0.0) -> 0 | F21: =IFERROR(__xludf.DUMMYFUNCTION("""COMPUTED_VALUE"""),"-") -> - | G21: =IFERROR(__xludf.DUMMYFUNCTION("""COMPUTED_VALUE"""),"-") -> - | H21: =IFERROR(__xludf.DUMMYFUNCTION("""COMPUTED_VALUE"""),"-") -> - | I21: =IFERROR(__xludf.DUMMYFUNCTION("""COMPUTED_VALUE"""),"-") -> - | J21: =IFERROR(__xludf.DUMMYFUNCTION("""COMPUTED_VALUE"""),"7.900,00") -> 7.900,00 | K21: =IFERROR(__xludf.DUMMYFUNCTION("""COMPUTED_VALUE"""),"7.830,00") -> 7.830,00 | L21: =IFERROR(__xludf.DUMMYFUNCTION("""COMPUTED_VALUE"""),"7.945,00") -> 7.945,00 | M21: =IFERROR(__xludf.DUMMYFUNCTION("""COMPUTED_VALUE"""),"7.900,00") -> 7.900,00 | N21: =IFERROR(__xludf.DUMMYFUNCTION("""COMPUTED_VALUE"""),"63.409.595") -> 63.409.595
A22: =MID(C22, FIND("* ", C22) + 2, FIND(" *", C22, FIND("* ", C22) + 2) - FIND("* ", C22) - 2) -> ADBE | B22: =SUBSTITUTE(SUBSTITUTE(SUBSTITUTE(D22, ".", "\\"), ",", "."), "\\", ",") -> 8,345.00 | C22: =IFERROR(__xludf.DUMMYFUNCTION("""COMPUTED_VALUE"""),"* ADBE * Cedear Adobe S...") -> * ADBE * Cedear Adobe S... | D22: =IFERROR(__xludf.DUMMYFUNCTION("""COMPUTED_VALUE"""),"8.345,00") -> 8.345,00 | E22: =IFERROR(__xludf.DUMMYFUNCTION("""COMPUTED_VALUE"""),"-7,01%") -> -7,01% | F22: =IFERROR(__xludf.DUMMYFUNCTION("""COMPUTED_VALUE"""),"-") -> - | G22: =IFERROR(__xludf.DUMMYFUNCTION("""COMPUTED_VALUE"""),"-") -> - | H22: =IFERROR(__xludf.DUMMYFUNCTION("""COMPUTED_VALUE"""),"-") -> - | I22: =IFERROR(__xludf.DUMMYFUNCTION("""COMPUTED_VALUE"""),"-") -> - | J22: =IFERROR(__xludf.DUMMYFUNCTION("""COMPUTED_VALUE"""),"8.515,00") -> 8.515,00 | K22: =IFERROR(__xludf.DUMMYFUNCTION("""COMPUTED_VALUE"""),"8.280,00") -> 8.280,00 | L22: =IFERROR(__xludf.DUMMYFUNCTION("""COMPUTED_VALUE"""),"8.950,00") -> 8.950,00 | M22: =IFERROR(__xludf.DUMMYFUNCTION("""COMPUTED_VALUE"""),"8.975,00") -> 8.975,00 | N22: =IFERROR(__xludf.DUMMYFUNCTION("""COMPUTED_VALUE"""),"1.942.754.400") -> 1.942.754.400
A23: =MID(C23, FIND("* ", C23) + 2, FIND(" *", C23, FIND("* ", C23) + 2) - FIND("* ", C23) - 2) -> ADBED | B23: =SUBSTITUTE(SUBSTITUTE(SUBSTITUTE(D23, ".", "\\"), ",", "."), "\\", ",") -> 5.87 | C23: =IFERROR(__xludf.DUMMYFUNCTION("""COMPUTED_VALUE"""),"* ADBED * Cedear Adobe S...") -> * ADBED * Cedear Adobe S... | D23: =IFERROR(__xludf.DUMMYFUNCTION("""COMPUTED_VALUE"""),"5,87") -> 5,87 | E23: =IFERROR(__xludf.DUMMYFUNCTION("""COMPUTED_VALUE"""),"-7,70%") -> -7,70% | F23: =IFERROR(__xludf.DUMMYFUNCTION("""COMPUTED_VALUE"""),"-") -> - | G23: =IFERROR(__xludf.DUMMYFUNCTION("""COMPUTED_VALUE"""),"-") -> - | H23: =IFERROR(__xludf.DUMMYFUNCTION("""COMPUTED_VALUE"""),"-") -> - | I23: =IFERROR(__xludf.DUMMYFUNCTION("""COMPUTED_VALUE"""),"-") -> - | J23: =IFERROR(__xludf.DUMMYFUNCTION("""COMPUTED_VALUE"""),"6,24") -> 6,24 | K23: =IFERROR(__xludf.DUMMYFUNCTION("""COMPUTED_VALUE"""),"5,87") -> 5,87 | L23: =IFERROR(__xludf.DUMMYFUNCTION("""COMPUTED_VALUE"""),"6,30") -> 6,30 | M23: =IFERROR(__xludf.DUMMYFUNCTION("""COMPUTED_VALUE"""),"5,87") -> 5,87 | N23: =IFERROR(__xludf.DUMMYFUNCTION("""COMPUTED_VALUE"""),87.573) -> 87.573
A24: =MID(C24, FIND("* ", C24) + 2, FIND(" *", C24, FIND("* ", C24) + 2) - FIND("* ", C24) - 2) -> ADGO | B24: =SUBSTITUTE(SUBSTITUTE(SUBSTITUTE(D24, ".", "\\"), ",", "."), "\\", ",") -> 15,950.00 | C24: =IFERROR(__xludf.DUMMYFUNCTION("""COMPUTED_VALUE"""),"* ADGO * Cedear Adecoagr...") -> * ADGO * Cedear Adecoagr... | D24: =IFERROR(__xludf.DUMMYFUNCTION("""COMPUTED_VALUE"""),"15.950,00") -> 15.950,00 | E24: =IFERROR(__xludf.DUMMYFUNCTION("""COMPUTED_VALUE"""),"3,57%") -> 3,57% | F24: =IFERROR(__xludf.DUMMYFUNCTION("""COMPUTED_VALUE"""),"-") -> - | G24: =IFERROR(__xludf.DUMMYFUNCTION("""COMPUTED_VALUE"""),"-") -> - | H24: =IFERROR(__xludf.DUMMYFUNCTION("""COMPUTED_VALUE"""),"-") -> - | I24: =IFERROR(__xludf.DUMMYFUNCTION("""COMPUTED_VALUE"""),"-") -> - | J24: =IFERROR(__xludf.DUMMYFUNCTION("""COMPUTED_VALUE"""),"15.510,00") -> 15.510,00 | K24: =IFERROR(__xludf.DUMMYFUNCTION("""COMPUTED_VALUE"""),"15.510,00") -> 15.510,00 | L24: =IFERROR(__xludf.DUMMYFUNCTION("""COMPUTED_VALUE"""),"16.040,00") -> 16.040,00 | M24: =IFERROR(__xludf.DUMMYFUNCTION("""COMPUTED_VALUE"""),"15.400,00") -> 15.400,00 | N24: =IFERROR(__xludf.DUMMYFUNCTION("""COMPUTED_VALUE"""),"487.223.290") -> 487.223.290
A25: =MID(C25, FIND("* ", C25) + 2, FIND(" *", C25, FIND("* ", C25) + 2) - FIND("* ", C25) - 2) -> ADI | B25: =SUBSTITUTE(SUBSTITUTE(SUBSTITUTE(D25, ".", "\\"), ",", "."), "\\", ",") -> 29,880.00 | C25: =IFERROR(__xludf.DUMMYFUNCTION("""COMPUTED_VALUE"""),"* ADI * Cedear Analog D...") -> * ADI * Cedear Analog D... | D25: =IFERROR(__xludf.DUMMYFUNCTION("""COMPUTED_VALUE"""),"29.880,00") -> 29.880,00 | E25: =IFERROR(__xludf.DUMMYFUNCTION("""COMPUTED_VALUE"""),"0,33%") -> 0,33% | F25: =IFERROR(__xludf.DUMMYFUNCTION("""COMPUTED_VALUE"""),"-") -> - | G25: =IFERROR(__xludf.DUMMYFUNCTION("""COMPUTED_VALUE"""),"-") -> - | H25: =IFERROR(__xludf.DUMMYFUNCTION("""COMPUTED_VALUE"""),"-") -> - | I25: =IFERROR(__xludf.DUMMYFUNCTION("""COMPUTED_VALUE"""),"-") -> - | J25: =IFERROR(__xludf.DUMMYFUNCTION("""COMPUTED_VALUE"""),"29.680,00") -> 29.680,00 | K25: =IFERROR(__xludf.DUMMYFUNCTION("""COMPUTED_VALUE"""),"29.600,00") -> 29.600,00 | L25: =IFERROR(__xludf.DUMMYFUNCTION("""COMPUTED_VALUE"""),"29.800,00") -> 29.800,00 | M25: =IFERROR(__xludf.DUMMYFUNCTION("""COMPUTED_VALUE"""),"29.880,00") -> 29.880,00 | N25: =IFERROR(__xludf.DUMMYFUNCTION("""COMPUTED_VALUE"""),"4.011.580") -> 4.011.580
A26: =MID(C26, FIND("* ", C26) + 2, FIND(" *", C26, FIND("* ", C26) + 2) - FIND("* ", C26) - 2) -> ADP | B26: =SUBSTITUTE(SUBSTITUTE(SUBSTITUTE(D26, ".", "\\"), ",", "."), "\\", ",") -> 51,225.00 | C26: =IFERROR(__xludf.DUMMYFUNCTION("""COMPUTED_VALUE"""),"* ADP * Cedear Automati...") -> * ADP * Cedear Automati... | D26: =IFERROR(__xludf.DUMMYFUNCTION("""COMPUTED_VALUE"""),"51.225,00") -> 51.225,00 | E26: =IFERROR(__xludf.DUMMYFUNCTION("""COMPUTED_VALUE"""),"2,32%") -> 2,32% | F26: =IFERROR(__xludf.DUMMYFUNCTION("""COMPUTED_VALUE"""),"-") -> - | G26: =IFERROR(__xludf.DUMMYFUNCTION("""COMPUTED_VALUE"""),"-") -> - | H26: =IFERROR(__xludf.DUMMYFUNCTION("""COMPUTED_VALUE"""),"-") -> - | I26: =IFERROR(__xludf.DUMMYFUNCTION("""COMPUTED_VALUE"""),"-") -> - | J26: =IFERROR(__xludf.DUMMYFUNCTION("""COMPUTED_VALUE"""),"50.375,00") -> 50.375,00 | K26: =IFERROR(__xludf.DUMMYFUNCTION("""COMPUTED_VALUE"""),"50.200,00") -> 50.200,00 | L26: =IFERROR(__xludf.DUMMYFUNCTION("""COMPUTED_VALUE"""),"51.150,00") -> 51.150,00 | M26: =IFERROR(__xludf.DUMMYFUNCTION("""COMPUTED_VALUE"""),"51.225,00") -> 51.225,00 | N26: =IFERROR(__xludf.DUMMYFUNCTION("""COMPUTED_VALUE"""),"33.635.050") -> 33.635.050
A27: =MID(C27, FIND("* ", C27) + 2, FIND(" *", C27, FIND("* ", C27) + 2) - FIND("* ", C27) - 2) -> ADS | B27: =SUBSTITUTE(SUBSTITUTE(SUBSTITUTE(D27, ".", "\\"), ",", "."), "\\", ",") -> 3,980.00 | C27: =IFERROR(__xludf.DUMMYFUNCTION("""COMPUTED_VALUE"""),"* ADS * Cedear Adidas Ag") -> * ADS * Cedear Adidas Ag | D27: =IFERROR(__xludf.DUMMYFUNCTION("""COMPUTED_VALUE"""),"3.980,00") -> 3.980,00 | E27: =IFERROR(__xludf.DUMMYFUNCTION("""COMPUTED_VALUE"""),0.0) -> 0 | F27: =IFERROR(__xludf.DUMMYFUNCTION("""COMPUTED_VALUE"""),"-") -> - | G27: =IFERROR(__xludf.DUMMYFUNCTION("""COMPUTED_VALUE"""),"-") -> - | H27: =IFERROR(__xludf.DUMMYFUNCTION("""COMPUTED_VALUE"""),"-") -> - | I27: =IFERROR(__xludf.DUMMYFUNCTION("""COMPUTED_VALUE"""),"-") -> - | J27: =IFERROR(__xludf.DUMMYFUNCTION("""COMPUTED_VALUE"""),"3.980,00") -> 3.980,00 | K27: =IFERROR(__xludf.DUMMYFUNCTION("""COMPUTED_VALUE"""),"3.980,00") -> 3.980,00 | L27: =IFERROR(__xludf.DUMMYFUNCTION("""COMPUTED_VALUE"""),"3.980,00") -> 3.980,00 | M27: =IFERROR(__xludf.DUMMYFUNCTION("""COMPUTED_VALUE"""),"3.980,00") -> 3.980,00 | N27: =IFERROR(__xludf.DUMMYFUNCTION("""COMPUTED_VALUE"""),0.0) -> 0
A28: =MID(C28, FIND("* ", C28) + 2, FIND(" *", C28, FIND("* ", C28) + 2) - FIND("* ", C28) - 2) -> AEG | B28: =SUBSTITUTE(SUBSTITUTE(SUBSTITUTE(D28, ".", "\\"), ",", "."), "\\", ",") -> 10,020.00 | C28: =IFERROR(__xludf.DUMMYFUNCTION("""COMPUTED_VALUE"""),"* AEG * Cedear Aegon N....") -> * AEG * Cedear Aegon N.... | D28: =IFERROR(__xludf.DUMMYFUNCTION("""COMPUTED_VALUE"""),"10.020,00") -> 10.020,00 | E28: =IFERROR(__xludf.DUMMYFUNCTION("""COMPUTED_VALUE"""),"-0,39%") -> -0,39% | F28: =IFERROR(__xludf.DUMMYFUNCTION("""COMPUTED_VALUE"""),"-") -> - | G28: =IFERROR(__xludf.DUMMYFUNCTION("""COMPUTED_VALUE"""),"-") -> - | H28: =IFERROR(__xludf.DUMMYFUNCTION("""COMPUTED_VALUE"""),"-") -> - | I28: =IFERROR(__xludf.DUMMYFUNCTION("""COMPUTED_VALUE"""),"-") -> - | J28: =IFERROR(__xludf.DUMMYFUNCTION("""COMPUTED_VALUE"""),"10.100,00") -> 10.100,00 | K28: =IFERROR(__xludf.DUMMYFUNCTION("""COMPUTED_VALUE"""),"9.970,00") -> 9.970,00 | L28: =IFERROR(__xludf.DUMMYFUNCTION("""COMPUTED_VALUE"""),"10.100,00") -> 10.100,00 | M28: =IFERROR(__xludf.DUMMYFUNCTION("""COMPUTED_VALUE"""),"10.020,00") -> 10.020,00 | N28: =IFERROR(__xludf.DUMMYFUNCTION("""COMPUTED_VALUE"""),"3.514.150") -> 3.514.150
A29: =MID(C29, FIND("* ", C29) + 2, FIND(" *", C29, FIND("* ", C29) + 2) - FIND("* ", C29) - 2) -> AEM | B29: =SUBSTITUTE(SUBSTITUTE(SUBSTITUTE(D29, ".", "\\"), ",", "."), "\\", ",") -> 50,850.00 | C29: =IFERROR(__xludf.DUMMYFUNCTION("""COMPUTED_VALUE"""),"* AEM * Cedear Agnico E...") -> * AEM * Cedear Agnico E... | D29: =IFERROR(__xludf.DUMMYFUNCTION("""COMPUTED_VALUE"""),"50.850,00") -> 50.850,00 | E29: =IFERROR(__xludf.DUMMYFUNCTION("""COMPUTED_VALUE"""),"-4,19%") -> -4,19% | F29: =IFERROR(__xludf.DUMMYFUNCTION("""COMPUTED_VALUE"""),"-") -> - | G29: =IFERROR(__xludf.DUMMYFUNCTION("""COMPUTED_VALUE"""),"-") -> - | H29: =IFERROR(__xludf.DUMMYFUNCTION("""COMPUTED_VALUE"""),"-") -> - | I29: =IFERROR(__xludf.DUMMYFUNCTION("""COMPUTED_VALUE"""),"-") -> - | J29: =IFERROR(__xludf.DUMMYFUNCTION("""COMPUTED_VALUE"""),"52.525,00") -> 52.525,00 | K29: =IFERROR(__xludf.DUMMYFUNCTION("""COMPUTED_VALUE"""),"50.600,00") -> 50.600,00 | L29: =IFERROR(__xludf.DUMMYFUNCTION("""COMPUTED_VALUE"""),"52.550,00") -> 52.550,00 | M29: =IFERROR(__xludf.DUMMYFUNCTION("""COMPUTED_VALUE"""),"50.850,00") -> 50.850,00 | N29: =IFERROR(__xludf.DUMMYFUNCTION("""COMPUTED_VALUE"""),"280.895.425") -> 280.895.425
A30: ARKK | B30: =SUBSTITUTE(SUBSTITUTE(SUBSTITUTE(D30, ".", "\\"), ",", "."), "\\", ",") -> 2,602.50 | C30: =IFERROR(__xludf.DUMMYFUNCTION("""COMPUTED_VALUE"""),"* AI * Cedear C3.Ai Inc") -> * AI * Cedear C3.Ai Inc | D30: =IFERROR(__xludf.DUMMYFUNCTION("""COMPUTED_VALUE"""),"2.602,50") -> 2.602,50 | E30: =IFERROR(__xludf.DUMMYFUNCTION("""COMPUTED_VALUE"""),"1,46%") -> 1,46% | F30: =IFERROR(__xludf.DUMMYFUNCTION("""COMPUTED_VALUE"""),"-") -> - | G30: =IFERROR(__xludf.DUMMYFUNCTION("""COMPUTED_VALUE"""),"-") -> - | H30: =IFERROR(__xludf.DUMMYFUNCTION("""COMPUTED_VALUE"""),"-") -> - | I30: =IFERROR(__xludf.DUMMYFUNCTION("""COMPUTED_VALUE"""),"-") -> - | J30: =IFERROR(__xludf.DUMMYFUNCTION("""COMPUTED_VALUE"""),"2.572,50") -> 2.572,50 | K30: =IFERROR(__xludf.DUMMYFUNCTION("""COMPUTED_VALUE"""),"2.530,00") -> 2.530,00 | L30: =IFERROR(__xludf.DUMMYFUNCTION("""COMPUTED_VALUE"""),"2.625,00") -> 2.625,00 | M30: =IFERROR(__xludf.DUMMYFUNCTION("""COMPUTED_VALUE"""),"2.602,50") -> 2.602,50 | N30: =IFERROR(__xludf.DUMMYFUNCTION("""COMPUTED_VALUE"""),"23.055.733") -> 23.055.733
A31: ARKKD | B31: =SUBSTITUTE(SUBSTITUTE(SUBSTITUTE(D31, ".", "\\"), ",", "."), "\\", ",") -> 22,510.00 | C31: =IFERROR(__xludf.DUMMYFUNCTION("""COMPUTED_VALUE"""),"* AIG * Cedear American...") -> * AIG * Cedear American... | D31: =IFERROR(__xludf.DUMMYFUNCTION("""COMPUTED_VALUE"""),"22.510,00") -> 22.510,00 | E31: =IFERROR(__xludf.DUMMYFUNCTION("""COMPUTED_VALUE"""),0.0) -> 0 | F31: =IFERROR(__xludf.DUMMYFUNCTION("""COMPUTED_VALUE"""),"-") -> - | G31: =IFERROR(__xludf.DUMMYFUNCTION("""COMPUTED_VALUE"""),"-") -> - | H31: =IFERROR(__xludf.DUMMYFUNCTION("""COMPUTED_VALUE"""),"-") -> - | I31: =IFERROR(__xludf.DUMMYFUNCTION("""COMPUTED_VALUE"""),"-") -> - | J31: =IFERROR(__xludf.DUMMYFUNCTION("""COMPUTED_VALUE"""),"22.500,00") -> 22.500,00 | K31: =IFERROR(__xludf.DUMMYFUNCTION("""COMPUTED_VALUE"""),"22.470,00") -> 22.470,00 | L31: =IFERROR(__xludf.DUMMYFUNCTION("""COMPUTED_VALUE"""),"22.560,00") -> 22.560,00 | M31: =IFERROR(__xludf.DUMMYFUNCTION("""COMPUTED_VALUE"""),"22.510,00") -> 22.510,00 | N31: =IFERROR(__xludf.DUMMYFUNCTION("""COMPUTED_VALUE"""),630.91) -> 630.91
A32: =MID(C32, FIND("* ", C32) + 2, FIND(" *", C32, FIND("* ", C32) + 2) - FIND("* ", C32) - 2) -> AKO.B | B32: =SUBSTITUTE(SUBSTITUTE(SUBSTITUTE(D32, ".", "\\"), ",", "."), "\\", ",") -> 38,000.00 | C32: =IFERROR(__xludf.DUMMYFUNCTION("""COMPUTED_VALUE"""),"* AKO.B * Cedear Embotell...") -> * AKO.B * Cedear Embotell... | D32: =IFERROR(__xludf.DUMMYFUNCTION("""COMPUTED_VALUE"""),"38.000,00") -> 38.000,00 | E32: =IFERROR(__xludf.DUMMYFUNCTION("""COMPUTED_VALUE"""),"1,06%") -> 1,06% | F32: =IFERROR(__xludf.DUMMYFUNCTION("""COMPUTED_VALUE"""),"-") -> - | G32: =IFERROR(__xludf.DUMMYFUNCTION("""COMPUTED_VALUE"""),"-") -> - | H32: =IFERROR(__xludf.DUMMYFUNCTION("""COMPUTED_VALUE"""),"-") -> - | I32: =IFERROR(__xludf.DUMMYFUNCTION("""COMPUTED_VALUE"""),"-") -> - | J32: =IFERROR(__xludf.DUMMYFUNCTION("""COMPUTED_VALUE"""),"37.600,00") -> 37.600,00 | K32: =IFERROR(__xludf.DUMMYFUNCTION("""COMPUTED_VALUE"""),"37.500,00") -> 37.500,00 | L32: =IFERROR(__xludf.DUMMYFUNCTION("""COMPUTED_VALUE"""),"37.600,00") -> 37.600,00 | M32: =IFERROR(__xludf.DUMMYFUNCTION("""COMPUTED_VALUE"""),"38.000,00") -> 38.000,00 | N32: =IFERROR(__xludf.DUMMYFUNCTION("""COMPUTED_VALUE"""),413.4) -> 413.4
A33: =MID(C33, FIND("* ", C33) + 2, FIND(" *", C33, FIND("* ", C33) + 2) - FIND("* ", C33) - 2) -> ALAB | B33: =SUBSTITUTE(SUBSTITUTE(SUBSTITUTE(D33, ".", "\\"), ",", "."), "\\", ",") -> 4,027.50 | C33: =IFERROR(__xludf.DUMMYFUNCTION("""COMPUTED_VALUE"""),"* ALAB * CEDEAR ASTERA L...") -> * ALAB * CEDEAR ASTERA L... | D33: =IFERROR(__xludf.DUMMYFUNCTION("""COMPUTED_VALUE"""),"4.027,50") -> 4.027,50 | E33: =IFERROR(__xludf.DUMMYFUNCTION("""COMPUTED_VALUE"""),"1,38%") -> 1,38% | F33: =IFERROR(__xludf.DUMMYFUNCTION("""COMPUTED_VALUE"""),"-") -> - | G33: =IFERROR(__xludf.DUMMYFUNCTION("""COMPUTED_VALUE"""),"-") -> - | H33: =IFERROR(__xludf.DUMMYFUNCTION("""COMPUTED_VALUE"""),"-") -> - | I33: =IFERROR(__xludf.DUMMYFUNCTION("""COMPUTED_VALUE"""),"-") -> - | J33: =IFERROR(__xludf.DUMMYFUNCTION("""COMPUTED_VALUE"""),"4.035,00") -> 4.035,00 | K33: =IFERROR(__xludf.DUMMYFUNCTION("""COMPUTED_VALUE"""),"3.900,00") -> 3.900,00 | L33: =IFERROR(__xludf.DUMMYFUNCTION("""COMPUTED_VALUE"""),"4.062,50") -> 4.062,50 | M33: =IFERROR(__xludf.DUMMYFUNCTION("""COMPUTED_VALUE"""),"3.972,50") -> 3.972,50 | N33: =IFERROR(__xludf.DUMMYFUNCTION("""COMPUTED_VALUE"""),"173.931.770") -> 173.931.770
A34: =MID(C34, FIND("* ", C34) + 2, FIND(" *", C34, FIND("* ", C34) + 2) - FIND("* ", C34) - 2) -> AMAT | B34: =SUBSTITUTE(SUBSTITUTE(SUBSTITUTE(D34, ".", "\\"), ",", "."), "\\", ",") -> 100,300.00 | C34: =IFERROR(__xludf.DUMMYFUNCTION("""COMPUTED_VALUE"""),"* AMAT * Cedear Applied ...") -> * AMAT * Cedear Applied ... | D34: =IFERROR(__xludf.DUMMYFUNCTION("""COMPUTED_VALUE"""),"100.300,00") -> 100.300,00 | E34: =IFERROR(__xludf.DUMMYFUNCTION("""COMPUTED_VALUE"""),"2,26%") -> 2,26% | F34: =IFERROR(__xludf.DUMMYFUNCTION("""COMPUTED_VALUE"""),"-") -> - | G34: =IFERROR(__xludf.DUMMYFUNCTION("""COMPUTED_VALUE"""),"-") -> - | H34: =IFERROR(__xludf.DUMMYFUNCTION("""COMPUTED_VALUE"""),"-") -> - | I34: =IFERROR(__xludf.DUMMYFUNCTION("""COMPUTED_VALUE"""),"-") -> - | J34: =IFERROR(__xludf.DUMMYFUNCTION("""COMPUTED_VALUE"""),"99.800,00") -> 99.800,00 | K34: =IFERROR(__xludf.DUMMYFUNCTION("""COMPUTED_VALUE"""),"99.725,00") -> 99.725,00 | L34: =IFERROR(__xludf.DUMMYFUNCTION("""COMPUTED_VALUE"""),"101.675,00") -> 101.675,00 | M34: =IFERROR(__xludf.DUMMYFUNCTION("""COMPUTED_VALUE"""),"100.300,00") -> 100.300,00 | N34: =IFERROR(__xludf.DUMMYFUNCTION("""COMPUTED_VALUE"""),"189.126.375") -> 189.126.375
A35: =MID(C35, FIND("* ", C35) + 2, FIND(" *", C35, FIND("* ", C35) + 2) - FIND("* ", C35) - 2) -> AMD | B35: =SUBSTITUTE(SUBSTITUTE(SUBSTITUTE(D35, ".", "\\"), ",", "."), "\\", ",") -> 28,360.00 | C35: =IFERROR(__xludf.DUMMYFUNCTION("""COMPUTED_VALUE"""),"* AMD * Cedear Advanced...") -> * AMD * Cedear Advanced... | D35: =IFERROR(__xludf.DUMMYFUNCTION("""COMPUTED_VALUE"""),"28.360,00") -> 28.360,00 | E35: =IFERROR(__xludf.DUMMYFUNCTION("""COMPUTED_VALUE"""),"-1,52%") -> -1,52% | F35: =IFERROR(__xludf.DUMMYFUNCTION("""COMPUTED_VALUE"""),"-") -> - | G35: =IFERROR(__xludf.DUMMYFUNCTION("""COMPUTED_VALUE"""),"-") -> - | H35: =IFERROR(__xludf.DUMMYFUNCTION("""COMPUTED_VALUE"""),"-") -> - | I35: =IFERROR(__xludf.DUMMYFUNCTION("""COMPUTED_VALUE"""),"-") -> - | J35: =IFERROR(__xludf.DUMMYFUNCTION("""COMPUTED_VALUE"""),"29.000,00") -> 29.000,00 | K35: =IFERROR(__xludf.DUMMYFUNCTION("""COMPUTED_VALUE"""),"28.200,00") -> 28.200,00 | L35: =IFERROR(__xludf.DUMMYFUNCTION("""COMPUTED_VALUE"""),"29.080,00") -> 29.080,00 | M35: =IFERROR(__xludf.DUMMYFUNCTION("""COMPUTED_VALUE"""),"28.800,00") -> 28.800,00 | N35: =IFERROR(__xludf.DUMMYFUNCTION("""COMPUTED_VALUE"""),"817.821.200") -> 817.821.200
A36: =MID(C36, FIND("* ", C36) + 2, FIND(" *", C36, FIND("* ", C36) + 2) - FIND("* ", C36) - 2) -> AMDD | B36: =SUBSTITUTE(SUBSTITUTE(SUBSTITUTE(D36, ".", "\\"), ",", "."), "\\", ",") -> 19.97 | C36: =IFERROR(__xludf.DUMMYFUNCTION("""COMPUTED_VALUE"""),"* AMDD * Cedear Advanced...") -> * AMDD * Cedear Advanced... | D36: =IFERROR(__xludf.DUMMYFUNCTION("""COMPUTED_VALUE"""),"19,97") -> 19,97 | E36: =IFERROR(__xludf.DUMMYFUNCTION("""COMPUTED_VALUE"""),"-2,29%") -> -2,29% | F36: =IFERROR(__xludf.DUMMYFUNCTION("""COMPUTED_VALUE"""),"-") -> - | G36: =IFERROR(__xludf.DUMMYFUNCTION("""COMPUTED_VALUE"""),"-") -> - | H36: =IFERROR(__xludf.DUMMYFUNCTION("""COMPUTED_VALUE"""),"-") -> - | I36: =IFERROR(__xludf.DUMMYFUNCTION("""COMPUTED_VALUE"""),"-") -> - | J36: =IFERROR(__xludf.DUMMYFUNCTION("""COMPUTED_VALUE"""),"20,36") -> 20,36 | K36: =IFERROR(__xludf.DUMMYFUNCTION("""COMPUTED_VALUE"""),"19,86") -> 19,86 | L36: =IFERROR(__xludf.DUMMYFUNCTION("""COMPUTED_VALUE"""),"20,55") -> 20,55 | M36: =IFERROR(__xludf.DUMMYFUNCTION("""COMPUTED_VALUE"""),"19,97") -> 19,97 | N36: =IFERROR(__xludf.DUMMYFUNCTION("""COMPUTED_VALUE"""),58.605) -> 58.605
A37: =MID(C37, FIND("* ", C37) + 2, FIND(" *", C37, FIND("* ", C37) + 2) - FIND("* ", C37) - 2) -> AMGN | B37: =SUBSTITUTE(SUBSTITUTE(SUBSTITUTE(D37, ".", "\\"), ",", "."), "\\", ",") -> 17,990.00 | C37: =IFERROR(__xludf.DUMMYFUNCTION("""COMPUTED_VALUE"""),"* AMGN * Cedear Amgen Inc.") -> * AMGN * Cedear Amgen Inc. | D37: =IFERROR(__xludf.DUMMYFUNCTION("""COMPUTED_VALUE"""),"17.990,00") -> 17.990,00 | E37: =IFERROR(__xludf.DUMMYFUNCTION("""COMPUTED_VALUE"""),"0,72%") -> 0,72% | F37: =IFERROR(__xludf.DUMMYFUNCTION("""COMPUTED_VALUE"""),"-") -> - | G37: =IFERROR(__xludf.DUMMYFUNCTION("""COMPUTED_VALUE"""),"-") -> - | H37: =IFERROR(__xludf.DUMMYFUNCTION("""COMPUTED_VALUE"""),"-") -> - | I37: =IFERROR(__xludf.DUMMYFUNCTION("""COMPUTED_VALUE"""),"-") -> - | J37: =IFERROR(__xludf.DUMMYFUNCTION("""COMPUTED_VALUE"""),"18.060,00") -> 18.060,00 | K37: =IFERROR(__xludf.DUMMYFUNCTION("""COMPUTED_VALUE"""),"17.810,00") -> 17.810,00 | L37: =IFERROR(__xludf.DUMMYFUNCTION("""COMPUTED_VALUE"""),"18.060,00") -> 18.060,00 | M37: =IFERROR(__xludf.DUMMYFUNCTION("""COMPUTED_VALUE"""),"17.990,00") -> 17.990,00 | N37: =IFERROR(__xludf.DUMMYFUNCTION("""COMPUTED_VALUE"""),"8.304.700") -> 8.304.700
A38: =MID(C38, FIND("* ", C38) + 2, FIND(" *", C38, FIND("* ", C38) + 2) - FIND("* ", C38) - 2) -> AMX | B38: =SUBSTITUTE(SUBSTITUTE(SUBSTITUTE(D38, ".", "\\"), ",", "."), "\\", ",") -> 33,680.00 | C38: =IFERROR(__xludf.DUMMYFUNCTION("""COMPUTED_VALUE"""),"* AMX * Cedear America ...") -> * AMX * Cedear America ... | D38: =IFERROR(__xludf.DUMMYFUNCTION("""COMPUTED_VALUE"""),"33.680,00") -> 33.680,00 | E38: =IFERROR(__xludf.DUMMYFUNCTION("""COMPUTED_VALUE"""),"0,53%") -> 0,53% | F38: =IFERROR(__xludf.DUMMYFUNCTION("""COMPUTED_VALUE"""),"-") -> - | G38: =IFERROR(__xludf.DUMMYFUNCTION("""COMPUTED_VALUE"""),"-") -> - | H38: =IFERROR(__xludf.DUMMYFUNCTION("""COMPUTED_VALUE"""),"-") -> - | I38: =IFERROR(__xludf.DUMMYFUNCTION("""COMPUTED_VALUE"""),"-") -> - | J38: =IFERROR(__xludf.DUMMYFUNCTION("""COMPUTED_VALUE"""),"33.500,00") -> 33.500,00 | K38: =IFERROR(__xludf.DUMMYFUNCTION("""COMPUTED_VALUE"""),"0,00") -> 0,00 | L38: =IFERROR(__xludf.DUMMYFUNCTION("""COMPUTED_VALUE"""),"0,00") -> 0,00 | M38: =IFERROR(__xludf.DUMMYFUNCTION("""COMPUTED_VALUE"""),"33.680,00") -> 33.680,00 | N38: =IFERROR(__xludf.DUMMYFUNCTION("""COMPUTED_VALUE"""),0.0) -> 0
A39: =MID(C39, FIND("* ", C39) + 2, FIND(" *", C39, FIND("* ", C39) + 2) - FIND("* ", C39) - 2) -> AMXD | B39: =SUBSTITUTE(SUBSTITUTE(SUBSTITUTE(D39, ".", "\\"), ",", "."), "\\", ",") -> 25.55 | C39: =IFERROR(__xludf.DUMMYFUNCTION("""COMPUTED_VALUE"""),"* AMXD * Cedear America ...") -> * AMXD * Cedear America ... | D39: =IFERROR(__xludf.DUMMYFUNCTION("""COMPUTED_VALUE"""),"25,55") -> 25,55 | E39: =IFERROR(__xludf.DUMMYFUNCTION("""COMPUTED_VALUE"""),0.0) -> 0 | F39: =IFERROR(__xludf.DUMMYFUNCTION("""COMPUTED_VALUE"""),"-") -> - | G39: =IFERROR(__xludf.DUMMYFUNCTION("""COMPUTED_VALUE"""),"-") -> - | H39: =IFERROR(__xludf.DUMMYFUNCTION("""COMPUTED_VALUE"""),"-") -> - | I39: =IFERROR(__xludf.DUMMYFUNCTION("""COMPUTED_VALUE"""),"-") -> - | J39: =IFERROR(__xludf.DUMMYFUNCTION("""COMPUTED_VALUE"""),"23,61") -> 23,61 | K39: =IFERROR(__xludf.DUMMYFUNCTION("""COMPUTED_VALUE"""),"23,61") -> 23,61 | L39: =IFERROR(__xludf.DUMMYFUNCTION("""COMPUTED_VALUE"""),"25,35") -> 25,35 | M39: =IFERROR(__xludf.DUMMYFUNCTION("""COMPUTED_VALUE"""),"25,55") -> 25,55 | N39: =IFERROR(__xludf.DUMMYFUNCTION("""COMPUTED_VALUE"""),0.0) -> 0
A40: =MID(C40, FIND("* ", C40) + 2, FIND(" *", C40, FIND("* ", C40) + 2) - FIND("* ", C40) - 2) -> AMZN | B40: =SUBSTITUTE(SUBSTITUTE(SUBSTITUTE(D40, ".", "\\"), ",", "."), "\\", ",") -> 2,126.00 | C40: =IFERROR(__xludf.DUMMYFUNCTION("""COMPUTED_VALUE"""),"* AMZN * Cedear Amazon.C...") -> * AMZN * Cedear Amazon.C... | D40: =IFERROR(__xludf.DUMMYFUNCTION("""COMPUTED_VALUE"""),"2.126,00") -> 2.126,00 | E40: =IFERROR(__xludf.DUMMYFUNCTION("""COMPUTED_VALUE"""),"0,23%") -> 0,23% | F40: =IFERROR(__xludf.DUMMYFUNCTION("""COMPUTED_VALUE"""),"-") -> - | G40: =IFERROR(__xludf.DUMMYFUNCTION("""COMPUTED_VALUE"""),"-") -> - | H40: =IFERROR(__xludf.DUMMYFUNCTION("""COMPUTED_VALUE"""),"-") -> - | I40: =IFERROR(__xludf.DUMMYFUNCTION("""COMPUTED_VALUE"""),"-") -> - | J40: =IFERROR(__xludf.DUMMYFUNCTION("""COMPUTED_VALUE"""),"2.120,00") -> 2.120,00 | K40: =IFERROR(__xludf.DUMMYFUNCTION("""COMPUTED_VALUE"""),"2.093,00") -> 2.093,00 | L40: =IFERROR(__xludf.DUMMYFUNCTION("""COMPUTED_VALUE"""),"2.131,00") -> 2.131,00 | M40: =IFERROR(__xludf.DUMMYFUNCTION("""COMPUTED_VALUE"""),"2.121,00") -> 2.121,00 | N40: =IFERROR(__xludf.DUMMYFUNCTION("""COMPUTED_VALUE"""),"1.264.497.260") -> 1.264.497.260
A41: =MID(C41, FIND("* ", C41) + 2, FIND(" *", C41, FIND("* ", C41) + 2) - FIND("* ", C41) - 2) -> AMZNC | B41: =SUBSTITUTE(SUBSTITUTE(SUBSTITUTE(D41, ".", "\\"), ",", "."), "\\", ",") -> 1.45 | C41: =IFERROR(__xludf.DUMMYFUNCTION("""COMPUTED_VALUE"""),"* AMZNC * Cedear Amazon.C...") -> * AMZNC * Cedear Amazon.C... | D41: =IFERROR(__xludf.DUMMYFUNCTION("""COMPUTED_VALUE"""),"1,45") -> 1,45 | E41: =IFERROR(__xludf.DUMMYFUNCTION("""COMPUTED_VALUE"""),"-1,02%") -> -1,02% | F41: =IFERROR(__xludf.DUMMYFUNCTION("""COMPUTED_VALUE"""),"-") -> - | G41: =IFERROR(__xludf.DUMMYFUNCTION("""COMPUTED_VALUE"""),"-") -> - | H41: =IFERROR(__xludf.DUMMYFUNCTION("""COMPUTED_VALUE"""),"-") -> - | I41: =IFERROR(__xludf.DUMMYFUNCTION("""COMPUTED_VALUE"""),"-") -> - | J41: =IFERROR(__xludf.DUMMYFUNCTION("""COMPUTED_VALUE"""),"1,45") -> 1,45 | K41: =IFERROR(__xludf.DUMMYFUNCTION("""COMPUTED_VALUE"""),"1,44") -> 1,44 | L41: =IFERROR(__xludf.DUMMYFUNCTION("""COMPUTED_VALUE"""),"1,47") -> 1,47 | M41: =IFERROR(__xludf.DUMMYFUNCTION("""COMPUTED_VALUE"""),"1,45") -> 1,45 | N41: =IFERROR(__xludf.DUMMYFUNCTION("""COMPUTED_VALUE"""),6.055) -> 6.055
A42: =MID(C42, FIND("* ", C42) + 2, FIND(" *", C42, FIND("* ", C42) + 2) - FIND("* ", C42) - 2) -> AMZND | B42: =SUBSTITUTE(SUBSTITUTE(SUBSTITUTE(D42, ".", "\\"), ",", "."), "\\", ",") -> 1.50 | C42: =IFERROR(__xludf.DUMMYFUNCTION("""COMPUTED_VALUE"""),"* AMZND * Cedear Amazon.C...") -> * AMZND * Cedear Amazon.C... | D42: =IFERROR(__xludf.DUMMYFUNCTION("""COMPUTED_VALUE"""),"1,50") -> 1,50 | E42: =IFERROR(__xludf.DUMMYFUNCTION("""COMPUTED_VALUE"""),"-1,64%") -> -1,64% | F42: =IFERROR(__xludf.DUMMYFUNCTION("""COMPUTED_VALUE"""),"-") -> - | G42: =IFERROR(__xludf.DUMMYFUNCTION("""COMPUTED_VALUE"""),"-") -> - | H42: =IFERROR(__xludf.DUMMYFUNCTION("""COMPUTED_VALUE"""),"-") -> - | I42: =IFERROR(__xludf.DUMMYFUNCTION("""COMPUTED_VALUE"""),"-") -> - | J42: =IFERROR(__xludf.DUMMYFUNCTION("""COMPUTED_VALUE"""),"1,50") -> 1,50 | K42: =IFERROR(__xludf.DUMMYFUNCTION("""COMPUTED_VALUE"""),"1,48") -> 1,48 | L42: =IFERROR(__xludf.DUMMYFUNCTION("""COMPUTED_VALUE"""),"1,51") -> 1,51 | M42: =IFERROR(__xludf.DUMMYFUNCTION("""COMPUTED_VALUE"""),"1,50") -> 1,50 | N42: =IFERROR(__xludf.DUMMYFUNCTION("""COMPUTED_VALUE"""),96.893) -> 96.893
A43: =MID(C43, FIND("* ", C43) + 2, FIND(" *", C43, FIND("* ", C43) + 2) - FIND("* ", C43) - 2) -> ANF | B43: =SUBSTITUTE(SUBSTITUTE(SUBSTITUTE(D43, ".", "\\"), ",", "."), "\\", ",") -> 119,925.00 | C43: =IFERROR(__xludf.DUMMYFUNCTION("""COMPUTED_VALUE"""),"* ANF * Cedear Abercrom...") -> * ANF * Cedear Abercrom... | D43: =IFERROR(__xludf.DUMMYFUNCTION("""COMPUTED_VALUE"""),"119.925,00") -> 119.925,00 | E43: =IFERROR(__xludf.DUMMYFUNCTION("""COMPUTED_VALUE"""),"-2,20%") -> -2,20% | F43: =IFERROR(__xludf.DUMMYFUNCTION("""COMPUTED_VALUE"""),"-") -> - | G43: =IFERROR(__xludf.DUMMYFUNCTION("""COMPUTED_VALUE"""),"-") -> - | H43: =IFERROR(__xludf.DUMMYFUNCTION("""COMPUTED_VALUE"""),"-") -> - | I43: =IFERROR(__xludf.DUMMYFUNCTION("""COMPUTED_VALUE"""),"-") -> - | J43: =IFERROR(__xludf.DUMMYFUNCTION("""COMPUTED_VALUE"""),"122.500,00") -> 122.500,00 | K43: =IFERROR(__xludf.DUMMYFUNCTION("""COMPUTED_VALUE"""),"119.550,00") -> 119.550,00 | L43: =IFERROR(__xludf.DUMMYFUNCTION("""COMPUTED_VALUE"""),"122.500,00") -> 122.500,00 | M43: =IFERROR(__xludf.DUMMYFUNCTION("""COMPUTED_VALUE"""),"119.925,00") -> 119.925,00 | N43: =IFERROR(__xludf.DUMMYFUNCTION("""COMPUTED_VALUE"""),"573.818.100") -> 573.818.100
A44: =MID(C44, FIND("* ", C44) + 2, FIND(" *", C44, FIND("* ", C44) + 2) - FIND("* ", C44) - 2) -> ANFD | B44: =SUBSTITUTE(SUBSTITUTE(SUBSTITUTE(D44, ".", "\\"), ",", "."), "\\", ",") -> 91.50 | C44: =IFERROR(__xludf.DUMMYFUNCTION("""COMPUTED_VALUE"""),"* ANFD * Cedear Abercrom...") -> * ANFD * Cedear Abercrom... | D44: =IFERROR(__xludf.DUMMYFUNCTION("""COMPUTED_VALUE"""),"91,50") -> 91,50 | E44: =IFERROR(__xludf.DUMMYFUNCTION("""COMPUTED_VALUE"""),0.0) -> 0 | F44: =IFERROR(__xludf.DUMMYFUNCTION("""COMPUTED_VALUE"""),"-") -> - | G44: =IFERROR(__xludf.DUMMYFUNCTION("""COMPUTED_VALUE"""),"-") -> - | H44: =IFERROR(__xludf.DUMMYFUNCTION("""COMPUTED_VALUE"""),"-") -> - | I44: =IFERROR(__xludf.DUMMYFUNCTION("""COMPUTED_VALUE"""),"-") -> - | J44: =IFERROR(__xludf.DUMMYFUNCTION("""COMPUTED_VALUE"""),"92,50") -> 92,50 | K44: =IFERROR(__xludf.DUMMYFUNCTION("""COMPUTED_VALUE"""),"90,70") -> 90,70 | L44: =IFERROR(__xludf.DUMMYFUNCTION("""COMPUTED_VALUE"""),"92,50") -> 92,50 | M44: =IFERROR(__xludf.DUMMYFUNCTION("""COMPUTED_VALUE"""),"91,50") -> 91,50 | N44: =IFERROR(__xludf.DUMMYFUNCTION("""COMPUTED_VALUE"""),0.0) -> 0
A45: =MID(C45, FIND("* ", C45) + 2, FIND(" *", C45, FIND("* ", C45) + 2) - FIND("* ", C45) - 2) -> ARCO | B45: =SUBSTITUTE(SUBSTITUTE(SUBSTITUTE(D45, ".", "\\"), ",", "."), "\\", ",") -> 22,560.00 | C45: =IFERROR(__xludf.DUMMYFUNCTION("""COMPUTED_VALUE"""),"* ARCO * Cedear Arcos Do...") -> * ARCO * Cedear Arcos Do... | D45: =IFERROR(__xludf.DUMMYFUNCTION("""COMPUTED_VALUE"""),"22.560,00") -> 22.560,00 | E45: =IFERROR(__xludf.DUMMYFUNCTION("""COMPUTED_VALUE"""),"-0,35%") -> -0,35% | F45: =IFERROR(__xludf.DUMMYFUNCTION("""COMPUTED_VALUE"""),"-") -> - | G45: =IFERROR(__xludf.DUMMYFUNCTION("""COMPUTED_VALUE"""),"-") -> - | H45: =IFERROR(__xludf.DUMMYFUNCTION("""COMPUTED_VALUE"""),"-") -> - | I45: =IFERROR(__xludf.DUMMYFUNCTION("""COMPUTED_VALUE"""),"-") -> - | J45: =IFERROR(__xludf.DUMMYFUNCTION("""COMPUTED_VALUE"""),"22.720,00") -> 22.720,00 | K45: =IFERROR(__xludf.DUMMYFUNCTION("""COMPUTED_VALUE"""),"22.530,00") -> 22.530,00 | L45: =IFERROR(__xludf.DUMMYFUNCTION("""COMPUTED_VALUE"""),"22.940,00") -> 22.940,00 | M45: =IFERROR(__xludf.DUMMYFUNCTION("""COMPUTED_VALUE"""),"22.560,00") -> 22.560,00 | N45: =IFERROR(__xludf.DUMMYFUNCTION("""COMPUTED_VALUE"""),"19.350.750") -> 19.350.750
A46: =MID(C46, FIND("* ", C46) + 2, FIND(" *", C46, FIND("* ", C46) + 2) - FIND("* ", C46) - 2) -> #VALUE! | B46: =SUBSTITUTE(SUBSTITUTE(SUBSTITUTE(D46, ".", "\\"), ",", "."), "\\", ",") -> 10,290.00 | C46: =IFERROR(__xludf.DUMMYFUNCTION("""COMPUTED_VALUE"""),"* ARKK ETF* Cedear Ark Inno...") -> * ARKK ETF* Cedear Ark Inno... | D46: =IFERROR(__xludf.DUMMYFUNCTION("""COMPUTED_VALUE"""),"10.290,00") -> 10.290,00 | E46: =IFERROR(__xludf.DUMMYFUNCTION("""COMPUTED_VALUE"""),"0,09%") -> 0,09% | F46: =IFERROR(__xludf.DUMMYFUNCTION("""COMPUTED_VALUE"""),"-") -> - | G46: =IFERROR(__xludf.DUMMYFUNCTION("""COMPUTED_VALUE"""),"-") -> - | H46: =IFERROR(__xludf.DUMMYFUNCTION("""COMPUTED_VALUE"""),"-") -> - | I46: =IFERROR(__xludf.DUMMYFUNCTION("""COMPUTED_VALUE"""),"-") -> - | J46: =IFERROR(__xludf.DUMMYFUNCTION("""COMPUTED_VALUE"""),"10.430,00") -> 10.430,00 | K46: =IFERROR(__xludf.DUMMYFUNCTION("""COMPUTED_VALUE"""),"10.210,00") -> 10.210,00 | L46: =IFERROR(__xludf.DUMMYFUNCTION("""COMPUTED_VALUE"""),"10.490,00") -> 10.490,00 | M46: =IFERROR(__xludf.DUMMYFUNCTION("""COMPUTED_VALUE"""),"10.290,00") -> 10.290,00 | N46: =IFERROR(__xludf.DUMMYFUNCTION("""COMPUTED_VALUE"""),"55.747.110") -> 55.747.110
A47: =MID(C47, FIND("* ", C47) + 2, FIND(" *", C47, FIND("* ", C47) + 2) - FIND("* ", C47) - 2) -> #VALUE! | B47: =SUBSTITUTE(SUBSTITUTE(SUBSTITUTE(D47, ".", "\\"), ",", "."), "\\", ",") -> 7.34 | C47: =IFERROR(__xludf.DUMMYFUNCTION("""COMPUTED_VALUE"""),"* ARKKC ETF* Cedear Ark Inno...") -> * ARKKC ETF* Cedear Ark Inno... | D47: =IFERROR(__xludf.DUMMYFUNCTION("""COMPUTED_VALUE"""),"7,34") -> 7,34 | E47: =IFERROR(__xludf.DUMMYFUNCTION("""COMPUTED_VALUE"""),0.0) -> 0 | F47: =IFERROR(__xludf.DUMMYFUNCTION("""COMPUTED_VALUE"""),"-") -> - | G47: =IFERROR(__xludf.DUMMYFUNCTION("""COMPUTED_VALUE"""),"-") -> - | H47: =IFERROR(__xludf.DUMMYFUNCTION("""COMPUTED_VALUE"""),"-") -> - | I47: =IFERROR(__xludf.DUMMYFUNCTION("""COMPUTED_VALUE"""),"-") -> - | J47: =IFERROR(__xludf.DUMMYFUNCTION("""COMPUTED_VALUE"""),"7,27") -> 7,27 | K47: =IFERROR(__xludf.DUMMYFUNCTION("""COMPUTED_VALUE"""),"0,00") -> 0,00 | L47: =IFERROR(__xludf.DUMMYFUNCTION("""COMPUTED_VALUE"""),"0,00") -> 0,00 | M47: =IFERROR(__xludf.DUMMYFUNCTION("""COMPUTED_VALUE"""),"7,34") -> 7,34 | N47: =IFERROR(__xludf.DUMMYFUNCTION("""COMPUTED_VALUE"""),0.0) -> 0
A48: =MID(C48, FIND("* ", C48) + 2, FIND(" *", C48, FIND("* ", C48) + 2) - FIND("* ", C48) - 2) -> #VALUE! | B48: =SUBSTITUTE(SUBSTITUTE(SUBSTITUTE(D48, ".", "\\"), ",", "."), "\\", ",") -> 7.36 | C48: =IFERROR(__xludf.DUMMYFUNCTION("""COMPUTED_VALUE"""),"* ARKKD ETF* Cedear Ark Inno...") -> * ARKKD ETF* Cedear Ark Inno... | D48: =IFERROR(__xludf.DUMMYFUNCTION("""COMPUTED_VALUE"""),"7,36") -> 7,36 | E48: =IFERROR(__xludf.DUMMYFUNCTION("""COMPUTED_VALUE"""),"0,68%") -> 0,68% | F48: =IFERROR(__xludf.DUMMYFUNCTION("""COMPUTED_VALUE"""),"-") -> - | G48: =IFERROR(__xludf.DUMMYFUNCTION("""COMPUTED_VALUE"""),"-") -> - | H48: =IFERROR(__xludf.DUMMYFUNCTION("""COMPUTED_VALUE"""),"-") -> - | I48: =IFERROR(__xludf.DUMMYFUNCTION("""COMPUTED_VALUE"""),"-") -> - | J48: =IFERROR(__xludf.DUMMYFUNCTION("""COMPUTED_VALUE"""),"7,27") -> 7,27 | K48: =IFERROR(__xludf.DUMMYFUNCTION("""COMPUTED_VALUE"""),"7,27") -> 7,27 | L48: =IFERROR(__xludf.DUMMYFUNCTION("""COMPUTED_VALUE"""),"7,54") -> 7,54 | M48: =IFERROR(__xludf.DUMMYFUNCTION("""COMPUTED_VALUE"""),"7,36") -> 7,36 | N48: =IFERROR(__xludf.DUMMYFUNCTION("""COMPUTED_VALUE"""),2.507) -> 2.507
A49: =MID(C49, FIND("* ", C49) + 2, FIND(" *", C49, FIND("* ", C49) + 2) - FIND("* ", C49) - 2) -> ARM | B49: =SUBSTITUTE(SUBSTITUTE(SUBSTITUTE(D49, ".", "\\"), ",", "."), "\\", ",") -> 6,250.00 | C49: =IFERROR(__xludf.DUMMYFUNCTION("""COMPUTED_VALUE"""),"* ARM * Cedear Arm Hold...") -> * ARM * Cedear Arm Hold... | D49: =IFERROR(__xludf.DUMMYFUNCTION("""COMPUTED_VALUE"""),"6.250,00") -> 6.250,00 | E49: =IFERROR(__xludf.DUMMYFUNCTION("""COMPUTED_VALUE"""),"0,72%") -> 0,72% | F49: =IFERROR(__xludf.DUMMYFUNCTION("""COMPUTED_VALUE"""),"-") -> - | G49: =IFERROR(__xludf.DUMMYFUNCTION("""COMPUTED_VALUE"""),"-") -> - | H49: =IFERROR(__xludf.DUMMYFUNCTION("""COMPUTED_VALUE"""),"-") -> - | I49: =IFERROR(__xludf.DUMMYFUNCTION("""COMPUTED_VALUE"""),"-") -> - | J49: =IFERROR(__xludf.DUMMYFUNCTION("""COMPUTED_VALUE"""),"6.235,00") -> 6.235,00 | K49: =IFERROR(__xludf.DUMMYFUNCTION("""COMPUTED_VALUE"""),"6.100,00") -> 6.100,00 | L49: =IFERROR(__xludf.DUMMYFUNCTION("""COMPUTED_VALUE"""),"6.345,00") -> 6.345,00 | M49: =IFERROR(__xludf.DUMMYFUNCTION("""COMPUTED_VALUE"""),"6.250,00") -> 6.250,00 | N49: =IFERROR(__xludf.DUMMYFUNCTION("""COMPUTED_VALUE"""),"77.268.175") -> 77.268.175
A50: =MID(C50, FIND("* ", C50) + 2, FIND(" *", C50, FIND("* ", C50) + 2) - FIND("* ", C50) - 2) -> ASML | B50: =SUBSTITUTE(SUBSTITUTE(SUBSTITUTE(D50, ".", "\\"), ",", "."), "\\", ",") -> 13,580.00 | C50: =IFERROR(__xludf.DUMMYFUNCTION("""COMPUTED_VALUE"""),"* ASML * Cedear Asml Hol...") -> * ASML * Cedear Asml Hol... | D50: =IFERROR(__xludf.DUMMYFUNCTION("""COMPUTED_VALUE"""),"13.580,00") -> 13.580,00 | E50: =IFERROR(__xludf.DUMMYFUNCTION("""COMPUTED_VALUE"""),"0,66%") -> 0,66% | F50: =IFERROR(__xludf.DUMMYFUNCTION("""COMPUTED_VALUE"""),"-") -> - | G50: =IFERROR(__xludf.DUMMYFUNCTION("""COMPUTED_VALUE"""),"-") -> - | H50: =IFERROR(__xludf.DUMMYFUNCTION("""COMPUTED_VALUE"""),"-") -> - | I50: =IFERROR(__xludf.DUMMYFUNCTION("""COMPUTED_VALUE"""),"-") -> - | J50: =IFERROR(__xludf.DUMMYFUNCTION("""COMPUTED_VALUE"""),"14.000,00") -> 14.000,00 | K50: =IFERROR(__xludf.DUMMYFUNCTION("""COMPUTED_VALUE"""),"13.430,00") -> 13.430,00 | L50: =IFERROR(__xludf.DUMMYFUNCTION("""COMPUTED_VALUE"""),"14.000,00") -> 14.000,00 | M50: =IFERROR(__xludf.DUMMYFUNCTION("""COMPUTED_VALUE"""),"13.580,00") -> 13.580,00 | N50: =IFERROR(__xludf.DUMMYFUNCTION("""COMPUTED_VALUE"""),"232.733.050") -> 232.733.050
A51: =MID(C51, FIND("* ", C51) + 2, FIND(" *", C51, FIND("* ", C51) + 2) - FIND("* ", C51) - 2) -> ASR | B51: =SUBSTITUTE(SUBSTITUTE(SUBSTITUTE(D51, ".", "\\"), ",", "."), "\\", ",") -> 23,470.00 | C51: =IFERROR(__xludf.DUMMYFUNCTION("""COMPUTED_VALUE"""),"* ASR * Cedear Grupo Ae...") -> * ASR * Cedear Grupo Ae... | D51: =IFERROR(__xludf.DUMMYFUNCTION("""COMPUTED_VALUE"""),"23.470,00") -> 23.470,00 | E51: =IFERROR(__xludf.DUMMYFUNCTION("""COMPUTED_VALUE"""),"0,12%") -> 0,12% | F51: =IFERROR(__xludf.DUMMYFUNCTION("""COMPUTED_VALUE"""),"-") -> - | G51: =IFERROR(__xludf.DUMMYFUNCTION("""COMPUTED_VALUE"""),"-") -> - | H51: =IFERROR(__xludf.DUMMYFUNCTION("""COMPUTED_VALUE"""),"-") -> - | I51: =IFERROR(__xludf.DUMMYFUNCTION("""COMPUTED_VALUE"""),"-") -> - | J51: =IFERROR(__xludf.DUMMYFUNCTION("""COMPUTED_VALUE"""),"23.510,00") -> 23.510,00 | K51: =IFERROR(__xludf.DUMMYFUNCTION("""COMPUTED_VALUE"""),"23.200,00") -> 23.200,00 | L51: =IFERROR(__xludf.DUMMYFUNCTION("""COMPUTED_VALUE"""),"23.510,00") -> 23.510,00 | M51: =IFERROR(__xludf.DUMMYFUNCTION("""COMPUTED_VALUE"""),"23.470,00") -> 23.470,00 | N51: =IFERROR(__xludf.DUMMYFUNCTION("""COMPUTED_VALUE"""),"563.551.780") -> 563.551.780
A52: =MID(C52, FIND("* ", C52) + 2, FIND(" *", C52, FIND("* ", C52) + 2) - FIND("* ", C52) - 2) -> ASTS | B52: =SUBSTITUTE(SUBSTITUTE(SUBSTITUTE(D52, ".", "\\"), ",", "."), "\\", ",") -> 8,460.00 | C52: =IFERROR(__xludf.DUMMYFUNCTION("""COMPUTED_VALUE"""),"* ASTS * CEDEAR AST SPAC...") -> * ASTS * CEDEAR AST SPAC... | D52: =IFERROR(__xludf.DUMMYFUNCTION("""COMPUTED_VALUE"""),"8.460,00") -> 8.460,00 | E52: =IFERROR(__xludf.DUMMYFUNCTION("""COMPUTED_VALUE"""),"-0,05%") -> -0,05% | F52: =IFERROR(__xludf.DUMMYFUNCTION("""COMPUTED_VALUE"""),"-") -> - | G52: =IFERROR(__xludf.DUMMYFUNCTION("""COMPUTED_VALUE"""),"-") -> - | H52: =IFERROR(__xludf.DUMMYFUNCTION("""COMPUTED_VALUE"""),"-") -> - | I52: =IFERROR(__xludf.DUMMYFUNCTION("""COMPUTED_VALUE"""),"-") -> - | J52: =IFERROR(__xludf.DUMMYFUNCTION("""COMPUTED_VALUE"""),"8.860,00") -> 8.860,00 | K52: =IFERROR(__xludf.DUMMYFUNCTION("""COMPUTED_VALUE"""),"8.350,00") -> 8.350,00 | L52: =IFERROR(__xludf.DUMMYFUNCTION("""COMPUTED_VALUE"""),"8.935,00") -> 8.935,00 | M52: =IFERROR(__xludf.DUMMYFUNCTION("""COMPUTED_VALUE"""),"8.465,00") -> 8.465,00 | N52: =IFERROR(__xludf.DUMMYFUNCTION("""COMPUTED_VALUE"""),"377.965.925") -> 377.965.925
A53: =MID(C53, FIND("* ", C53) + 2, FIND(" *", C53, FIND("* ", C53) + 2) - FIND("* ", C53) - 2) -> AVGO | B53: =SUBSTITUTE(SUBSTITUTE(SUBSTITUTE(D53, ".", "\\"), ",", "."), "\\", ",") -> 12,170.00 | C53: =IFERROR(__xludf.DUMMYFUNCTION("""COMPUTED_VALUE"""),"* AVGO * Cedear Broadcom...") -> * AVGO * Cedear Broadcom... | D53: =IFERROR(__xludf.DUMMYFUNCTION("""COMPUTED_VALUE"""),"12.170,00") -> 12.170,00 | E53: =IFERROR(__xludf.DUMMYFUNCTION("""COMPUTED_VALUE"""),"-3,02%") -> -3,02% | F53: =IFERROR(__xludf.DUMMYFUNCTION("""COMPUTED_VALUE"""),"-") -> - | G53: =IFERROR(__xludf.DUMMYFUNCTION("""COMPUTED_VALUE"""),"-") -> - | H53: =IFERROR(__xludf.DUMMYFUNCTION("""COMPUTED_VALUE"""),"-") -> - | I53: =IFERROR(__xludf.DUMMYFUNCTION("""COMPUTED_VALUE"""),"-") -> - | J53: =IFERROR(__xludf.DUMMYFUNCTION("""COMPUTED_VALUE"""),"12.540,00") -> 12.540,00 | K53: =IFERROR(__xludf.DUMMYFUNCTION("""COMPUTED_VALUE"""),"12.080,00") -> 12.080,00 | L53: =IFERROR(__xludf.DUMMYFUNCTION("""COMPUTED_VALUE"""),"12.610,00") -> 12.610,00 | M53: =IFERROR(__xludf.DUMMYFUNCTION("""COMPUTED_VALUE"""),"12.170,00") -> 12.170,00 | N53: =IFERROR(__xludf.DUMMYFUNCTION("""COMPUTED_VALUE"""),"454.520.150") -> 454.520.150
A54: =MID(C54, FIND("* ", C54) + 2, FIND(" *", C54, FIND("* ", C54) + 2) - FIND("* ", C54) - 2) -> AVGOC | B54: =SUBSTITUTE(SUBSTITUTE(SUBSTITUTE(D54, ".", "\\"), ",", "."), "\\", ",") -> 8.47 | C54: =IFERROR(__xludf.DUMMYFUNCTION("""COMPUTED_VALUE"""),"* AVGOC * Cedear Broadcom...") -> * AVGOC * Cedear Broadcom... | D54: =IFERROR(__xludf.DUMMYFUNCTION("""COMPUTED_VALUE"""),"8,47") -> 8,47 | E54: =IFERROR(__xludf.DUMMYFUNCTION("""COMPUTED_VALUE"""),"-3,53%") -> -3,53% | F54: =IFERROR(__xludf.DUMMYFUNCTION("""COMPUTED_VALUE"""),"-") -> - | G54: =IFERROR(__xludf.DUMMYFUNCTION("""COMPUTED_VALUE"""),"-") -> - | H54: =IFERROR(__xludf.DUMMYFUNCTION("""COMPUTED_VALUE"""),"-") -> - | I54: =IFERROR(__xludf.DUMMYFUNCTION("""COMPUTED_VALUE"""),"-") -> - | J54: =IFERROR(__xludf.DUMMYFUNCTION("""COMPUTED_VALUE"""),"8,72") -> 8,72 | K54: =IFERROR(__xludf.DUMMYFUNCTION("""COMPUTED_VALUE"""),"8,33") -> 8,33 | L54: =IFERROR(__xludf.DUMMYFUNCTION("""COMPUTED_VALUE"""),"8,72") -> 8,72 | M54: =IFERROR(__xludf.DUMMYFUNCTION("""COMPUTED_VALUE"""),"8,47") -> 8,47 | N54: =IFERROR(__xludf.DUMMYFUNCTION("""COMPUTED_VALUE"""),427.0) -> 427
A55: =MID(C55, FIND("* ", C55) + 2, FIND(" *", C55, FIND("* ", C55) + 2) - FIND("* ", C55) - 2) -> AVGOD | B55: =SUBSTITUTE(SUBSTITUTE(SUBSTITUTE(D55, ".", "\\"), ",", "."), "\\", ",") -> 8.55 | C55: =IFERROR(__xludf.DUMMYFUNCTION("""COMPUTED_VALUE"""),"* AVGOD * Cedear Broadcom...") -> * AVGOD * Cedear Broadcom... | D55: =IFERROR(__xludf.DUMMYFUNCTION("""COMPUTED_VALUE"""),"8,55") -> 8,55 | E55: =IFERROR(__xludf.DUMMYFUNCTION("""COMPUTED_VALUE"""),"-3,82%") -> -3,82% | F55: =IFERROR(__xludf.DUMMYFUNCTION("""COMPUTED_VALUE"""),"-") -> - | G55: =IFERROR(__xludf.DUMMYFUNCTION("""COMPUTED_VALUE"""),"-") -> - | H55: =IFERROR(__xludf.DUMMYFUNCTION("""COMPUTED_VALUE"""),"-") -> - | I55: =IFERROR(__xludf.DUMMYFUNCTION("""COMPUTED_VALUE"""),"-") -> - | J55: =IFERROR(__xludf.DUMMYFUNCTION("""COMPUTED_VALUE"""),"8,90") -> 8,90 | K55: =IFERROR(__xludf.DUMMYFUNCTION("""COMPUTED_VALUE"""),"8,52") -> 8,52 | L55: =IFERROR(__xludf.DUMMYFUNCTION("""COMPUTED_VALUE"""),"9,09") -> 9,09 | M55: =IFERROR(__xludf.DUMMYFUNCTION("""COMPUTED_VALUE"""),"8,55") -> 8,55 | N55: =IFERROR(__xludf.DUMMYFUNCTION("""COMPUTED_VALUE"""),34.351) -> 34.351
A56: =MID(C56, FIND("* ", C56) + 2, FIND(" *", C56, FIND("* ", C56) + 2) - FIND("* ", C56) - 2) -> AVY | B56: =SUBSTITUTE(SUBSTITUTE(SUBSTITUTE(D56, ".", "\\"), ",", "."), "\\", ",") -> 13,980.00 | C56: =IFERROR(__xludf.DUMMYFUNCTION("""COMPUTED_VALUE"""),"* AVY * Cedear Avery De...") -> * AVY * Cedear Avery De... | D56: =IFERROR(__xludf.DUMMYFUNCTION("""COMPUTED_VALUE"""),"13.980,00") -> 13.980,00 | E56: =IFERROR(__xludf.DUMMYFUNCTION("""COMPUTED_VALUE"""),"0,86%") -> 0,86% | F56: =IFERROR(__xludf.DUMMYFUNCTION("""COMPUTED_VALUE"""),"-") -> - | G56: =IFERROR(__xludf.DUMMYFUNCTION("""COMPUTED_VALUE"""),"-") -> - | H56: =IFERROR(__xludf.DUMMYFUNCTION("""COMPUTED_VALUE"""),"-") -> - | I56: =IFERROR(__xludf.DUMMYFUNCTION("""COMPUTED_VALUE"""),"-") -> - | J56: =IFERROR(__xludf.DUMMYFUNCTION("""COMPUTED_VALUE"""),"13.870,00") -> 13.870,00 | K56: =IFERROR(__xludf.DUMMYFUNCTION("""COMPUTED_VALUE"""),"13.870,00") -> 13.870,00 | L56: =IFERROR(__xludf.DUMMYFUNCTION("""COMPUTED_VALUE"""),"13.930,00") -> 13.930,00 | M56: =IFERROR(__xludf.DUMMYFUNCTION("""COMPUTED_VALUE"""),"13.980,00") -> 13.980,00 | N56: =IFERROR(__xludf.DUMMYFUNCTION("""COMPUTED_VALUE"""),403.81) -> 403.81
A57: =MID(C57, FIND("* ", C57) + 2, FIND(" *", C57, FIND("* ", C57) + 2) - FIND("* ", C57) - 2) -> AXIA | B57: =SUBSTITUTE(SUBSTITUTE(SUBSTITUTE(D57, ".", "\\"), ",", "."), "\\", ",") -> 64,550.00 | C57: =IFERROR(__xludf.DUMMYFUNCTION("""COMPUTED_VALUE"""),"* AXIA * Cedear Axia Ene...") -> * AXIA * Cedear Axia Ene... | D57: =IFERROR(__xludf.DUMMYFUNCTION("""COMPUTED_VALUE"""),"64.550,00") -> 64.550,00 | E57: =IFERROR(__xludf.DUMMYFUNCTION("""COMPUTED_VALUE"""),"-0,53%") -> -0,53% | F57: =IFERROR(__xludf.DUMMYFUNCTION("""COMPUTED_VALUE"""),"-") -> - | G57: =IFERROR(__xludf.DUMMYFUNCTION("""COMPUTED_VALUE"""),"-") -> - | H57: =IFERROR(__xludf.DUMMYFUNCTION("""COMPUTED_VALUE"""),"-") -> - | I57: =IFERROR(__xludf.DUMMYFUNCTION("""COMPUTED_VALUE"""),"-") -> - | J57: =IFERROR(__xludf.DUMMYFUNCTION("""COMPUTED_VALUE"""),"66.650,00") -> 66.650,00 | K57: =IFERROR(__xludf.DUMMYFUNCTION("""COMPUTED_VALUE"""),"64.000,00") -> 64.000,00 | L57: =IFERROR(__xludf.DUMMYFUNCTION("""COMPUTED_VALUE"""),"66.650,00") -> 66.650,00 | M57: =IFERROR(__xludf.DUMMYFUNCTION("""COMPUTED_VALUE"""),"64.550,00") -> 64.550,00 | N57: =IFERROR(__xludf.DUMMYFUNCTION("""COMPUTED_VALUE"""),"19.285.075") -> 19.285.075
A58: =MID(C58, FIND("* ", C58) + 2, FIND(" *", C58, FIND("* ", C58) + 2) - FIND("* ", C58) - 2) -> AXP | B58: =SUBSTITUTE(SUBSTITUTE(SUBSTITUTE(D58, ".", "\\"), ",", "."), "\\", ",") -> 29,360.00 | C58: =IFERROR(__xludf.DUMMYFUNCTION("""COMPUTED_VALUE"""),"* AXP * Cedear American...") -> * AXP * Cedear American... | D58: =IFERROR(__xludf.DUMMYFUNCTION("""COMPUTED_VALUE"""),"29.360,00") -> 29.360,00 | E58: =IFERROR(__xludf.DUMMYFUNCTION("""COMPUTED_VALUE"""),"0,06%") -> 0,06% | F58: =IFERROR(__xludf.DUMMYFUNCTION("""COMPUTED_VALUE"""),"-") -> - | G58: =IFERROR(__xludf.DUMMYFUNCTION("""COMPUTED_VALUE"""),"-") -> - | H58: =IFERROR(__xludf.DUMMYFUNCTION("""COMPUTED_VALUE"""),"-") -> - | I58: =IFERROR(__xludf.DUMMYFUNCTION("""COMPUTED_VALUE"""),"-") -> - | J58: =IFERROR(__xludf.DUMMYFUNCTION("""COMPUTED_VALUE"""),"29.420,00") -> 29.420,00 | K58: =IFERROR(__xludf.DUMMYFUNCTION("""COMPUTED_VALUE"""),"29.220,00") -> 29.220,00 | L58: =IFERROR(__xludf.DUMMYFUNCTION("""COMPUTED_VALUE"""),"29.620,00") -> 29.620,00 | M58: =IFERROR(__xludf.DUMMYFUNCTION("""COMPUTED_VALUE"""),"29.360,00") -> 29.360,00 | N58: =IFERROR(__xludf.DUMMYFUNCTION("""COMPUTED_VALUE"""),"75.128.900") -> 75.128.900
A59: =MID(C59, FIND("* ", C59) + 2, FIND(" *", C59, FIND("* ", C59) + 2) - FIND("* ", C59) - 2) -> AXPD | B59: =SUBSTITUTE(SUBSTITUTE(SUBSTITUTE(D59, ".", "\\"), ",", "."), "\\", ",") -> 21.00 | C59: =IFERROR(__xludf.DUMMYFUNCTION("""COMPUTED_VALUE"""),"* AXPD * Cedear American...") -> * AXPD * Cedear American... | D59: =IFERROR(__xludf.DUMMYFUNCTION("""COMPUTED_VALUE"""),"21,00") -> 21,00 | E59: =IFERROR(__xludf.DUMMYFUNCTION("""COMPUTED_VALUE"""),"0,86%") -> 0,86% | F59: =IFERROR(__xludf.DUMMYFUNCTION("""COMPUTED_VALUE"""),"-") -> - | G59: =IFERROR(__xludf.DUMMYFUNCTION("""COMPUTED_VALUE"""),"-") -> - | H59: =IFERROR(__xludf.DUMMYFUNCTION("""COMPUTED_VALUE"""),"-") -> - | I59: =IFERROR(__xludf.DUMMYFUNCTION("""COMPUTED_VALUE"""),"-") -> - | J59: =IFERROR(__xludf.DUMMYFUNCTION("""COMPUTED_VALUE"""),"21,22") -> 21,22 | K59: =IFERROR(__xludf.DUMMYFUNCTION("""COMPUTED_VALUE"""),"20,82") -> 20,82 | L59: =IFERROR(__xludf.DUMMYFUNCTION("""COMPUTED_VALUE"""),"21,46") -> 21,46 | M59: =IFERROR(__xludf.DUMMYFUNCTION("""COMPUTED_VALUE"""),"21,00") -> 21,00 | N59: =IFERROR(__xludf.DUMMYFUNCTION("""COMPUTED_VALUE"""),3.551) -> 3.551
A60: =MID(C60, FIND("* ", C60) + 2, FIND(" *", C60, FIND("* ", C60) + 2) - FIND("* ", C60) - 2) -> AZN | B60: =SUBSTITUTE(SUBSTITUTE(SUBSTITUTE(D60, ".", "\\"), ",", "."), "\\", ",") -> 70,025.00 | C60: =IFERROR(__xludf.DUMMYFUNCTION("""COMPUTED_VALUE"""),"* AZN * Cedear Astrazen...") -> * AZN * Cedear Astrazen... | D60: =IFERROR(__xludf.DUMMYFUNCTION("""COMPUTED_VALUE"""),"70.025,00") -> 70.025,00 | E60: =IFERROR(__xludf.DUMMYFUNCTION("""COMPUTED_VALUE"""),"0,35%") -> 0,35% | F60: =IFERROR(__xludf.DUMMYFUNCTION("""COMPUTED_VALUE"""),"-") -> - | G60: =IFERROR(__xludf.DUMMYFUNCTION("""COMPUTED_VALUE"""),"-") -> - | H60: =IFERROR(__xludf.DUMMYFUNCTION("""COMPUTED_VALUE"""),"-") -> - | I60: =IFERROR(__xludf.DUMMYFUNCTION("""COMPUTED_VALUE"""),"-") -> - | J60: =IFERROR(__xludf.DUMMYFUNCTION("""COMPUTED_VALUE"""),"70.200,00") -> 70.200,00 | K60: =IFERROR(__xludf.DUMMYFUNCTION("""COMPUTED_VALUE"""),"69.050,00") -> 69.050,00 | L60: =IFERROR(__xludf.DUMMYFUNCTION("""COMPUTED_VALUE"""),"70.200,00") -> 70.200,00 | M60: =IFERROR(__xludf.DUMMYFUNCTION("""COMPUTED_VALUE"""),"69.775,00") -> 69.775,00 | N60: =IFERROR(__xludf.DUMMYFUNCTION("""COMPUTED_VALUE"""),"14.343.125") -> 14.343.125
A61: =MID(C61, FIND("* ", C61) + 2, FIND(" *", C61, FIND("* ", C61) + 2) - FIND("* ", C61) - 2) -> AZND | B61: =SUBSTITUTE(SUBSTITUTE(SUBSTITUTE(D61, ".", "\\"), ",", "."), "\\", ",") -> 49.70 | C61: =IFERROR(__xludf.DUMMYFUNCTION("""COMPUTED_VALUE"""),"* AZND * Cedear Aztrazen...") -> * AZND * Cedear Aztrazen... | D61: =IFERROR(__xludf.DUMMYFUNCTION("""COMPUTED_VALUE"""),"49,70") -> 49,70 | E61: =IFERROR(__xludf.DUMMYFUNCTION("""COMPUTED_VALUE"""),"-5,15%") -> -5,15% | F61: =IFERROR(__xludf.DUMMYFUNCTION("""COMPUTED_VALUE"""),"-") -> - | G61: =IFERROR(__xludf.DUMMYFUNCTION("""COMPUTED_VALUE"""),"-") -> - | H61: =IFERROR(__xludf.DUMMYFUNCTION("""COMPUTED_VALUE"""),"-") -> - | I61: =IFERROR(__xludf.DUMMYFUNCTION("""COMPUTED_VALUE"""),"-") -> - | J61: =IFERROR(__xludf.DUMMYFUNCTION("""COMPUTED_VALUE"""),"52,40") -> 52,40 | K61: =IFERROR(__xludf.DUMMYFUNCTION("""COMPUTED_VALUE"""),"0,00") -> 0,00 | L61: =IFERROR(__xludf.DUMMYFUNCTION("""COMPUTED_VALUE"""),"0,00") -> 0,00 | M61: =IFERROR(__xludf.DUMMYFUNCTION("""COMPUTED_VALUE"""),"49,70") -> 49,70 | N61: =IFERROR(__xludf.DUMMYFUNCTION("""COMPUTED_VALUE"""),0.0) -> 0
A62: =MID(C62, FIND("* ", C62) + 2, FIND(" *", C62, FIND("* ", C62) + 2) - FIND("* ", C62) - 2) -> B | B62: =SUBSTITUTE(SUBSTITUTE(SUBSTITUTE(D62, ".", "\\"), ",", "."), "\\", ",") -> 31,080.00 | C62: =IFERROR(__xludf.DUMMYFUNCTION("""COMPUTED_VALUE"""),"* B * Cedear Barrick ...") -> * B * Cedear Barrick ... | D62: =IFERROR(__xludf.DUMMYFUNCTION("""COMPUTED_VALUE"""),"31.080,00") -> 31.080,00 | E62: =IFERROR(__xludf.DUMMYFUNCTION("""COMPUTED_VALUE"""),"-4,19%") -> -4,19% | F62: =IFERROR(__xludf.DUMMYFUNCTION("""COMPUTED_VALUE"""),"-") -> - | G62: =IFERROR(__xludf.DUMMYFUNCTION("""COMPUTED_VALUE"""),"-") -> - | H62: =IFERROR(__xludf.DUMMYFUNCTION("""COMPUTED_VALUE"""),"-") -> - | I62: =IFERROR(__xludf.DUMMYFUNCTION("""COMPUTED_VALUE"""),"-") -> - | J62: =IFERROR(__xludf.DUMMYFUNCTION("""COMPUTED_VALUE"""),"32.300,00") -> 32.300,00 | K62: =IFERROR(__xludf.DUMMYFUNCTION("""COMPUTED_VALUE"""),"30.880,00") -> 30.880,00 | L62: =IFERROR(__xludf.DUMMYFUNCTION("""COMPUTED_VALUE"""),"32.420,00") -> 32.420,00 | M62: =IFERROR(__xludf.DUMMYFUNCTION("""COMPUTED_VALUE"""),"31.080,00") -> 31.080,00 | N62: =IFERROR(__xludf.DUMMYFUNCTION("""COMPUTED_VALUE"""),"862.086.320") -> 862.086.320
A63: =MID(C63, FIND("* ", C63) + 2, FIND(" *", C63, FIND("* ", C63) + 2) - FIND("* ", C63) - 2) -> B.C | B63: =SUBSTITUTE(SUBSTITUTE(SUBSTITUTE(D63, ".", "\\"), ",", "."), "\\", ",") -> 21.29 | C63: =IFERROR(__xludf.DUMMYFUNCTION("""COMPUTED_VALUE"""),"* B.C * Cedear Barrick ...") -> * B.C * Cedear Barrick ... | D63: =IFERROR(__xludf.DUMMYFUNCTION("""COMPUTED_VALUE"""),"21,29") -> 21,29 | E63: =IFERROR(__xludf.DUMMYFUNCTION("""COMPUTED_VALUE"""),"-4,57%") -> -4,57% | F63: =IFERROR(__xludf.DUMMYFUNCTION("""COMPUTED_VALUE"""),"-") -> - | G63: =IFERROR(__xludf.DUMMYFUNCTION("""COMPUTED_VALUE"""),"-") -> - | H63: =IFERROR(__xludf.DUMMYFUNCTION("""COMPUTED_VALUE"""),"-") -> - | I63: =IFERROR(__xludf.DUMMYFUNCTION("""COMPUTED_VALUE"""),"-") -> - | J63: =IFERROR(__xludf.DUMMYFUNCTION("""COMPUTED_VALUE"""),"21,29") -> 21,29 | K63: =IFERROR(__xludf.DUMMYFUNCTION("""COMPUTED_VALUE"""),"21,29") -> 21,29 | L63: =IFERROR(__xludf.DUMMYFUNCTION("""COMPUTED_VALUE"""),"21,29") -> 21,29 | M63: =IFERROR(__xludf.DUMMYFUNCTION("""COMPUTED_VALUE"""),"21,29") -> 21,29 | N63: =IFERROR(__xludf.DUMMYFUNCTION("""COMPUTED_VALUE"""),511.0) -> 511
A64: =MID(C64, FIND("* ", C64) + 2, FIND(" *", C64, FIND("* ", C64) + 2) - FIND("* ", C64) - 2) -> B.D | B64: =SUBSTITUTE(SUBSTITUTE(SUBSTITUTE(D64, ".", "\\"), ",", "."), "\\", ",") -> 21.72 | C64: =IFERROR(__xludf.DUMMYFUNCTION("""COMPUTED_VALUE"""),"* B.D * Cedear Barrick ...") -> * B.D * Cedear Barrick ... | D64: =IFERROR(__xludf.DUMMYFUNCTION("""COMPUTED_VALUE"""),"21,72") -> 21,72 | E64: =IFERROR(__xludf.DUMMYFUNCTION("""COMPUTED_VALUE"""),"-5,15%") -> -5,15% | F64: =IFERROR(__xludf.DUMMYFUNCTION("""COMPUTED_VALUE"""),"-") -> - | G64: =IFERROR(__xludf.DUMMYFUNCTION("""COMPUTED_VALUE"""),"-") -> - | H64: =IFERROR(__xludf.DUMMYFUNCTION("""COMPUTED_VALUE"""),"-") -> - | I64: =IFERROR(__xludf.DUMMYFUNCTION("""COMPUTED_VALUE"""),"-") -> - | J64: =IFERROR(__xludf.DUMMYFUNCTION("""COMPUTED_VALUE"""),"23,49") -> 23,49 | K64: =IFERROR(__xludf.DUMMYFUNCTION("""COMPUTED_VALUE"""),"21,74") -> 21,74 | L64: =IFERROR(__xludf.DUMMYFUNCTION("""COMPUTED_VALUE"""),"23,49") -> 23,49 | M64: =IFERROR(__xludf.DUMMYFUNCTION("""COMPUTED_VALUE"""),"21,72") -> 21,72 | N64: =IFERROR(__xludf.DUMMYFUNCTION("""COMPUTED_VALUE"""),48.371) -> 48.371
A65: =MID(C65, FIND("* ", C65) + 2, FIND(" *", C65, FIND("* ", C65) + 2) - FIND("* ", C65) - 2) -> BA | B65: =SUBSTITUTE(SUBSTITUTE(SUBSTITUTE(D65, ".", "\\"), ",", "."), "\\", ",") -> 12,830.00 | C65: =IFERROR(__xludf.DUMMYFUNCTION("""COMPUTED_VALUE"""),"* BA * Cedear The Boei...") -> * BA * Cedear The Boei... | D65: =IFERROR(__xludf.DUMMYFUNCTION("""COMPUTED_VALUE"""),"12.830,00") -> 12.830,00 | E65: =IFERROR(__xludf.DUMMYFUNCTION("""COMPUTED_VALUE"""),"3,05%") -> 3,05% | F65: =IFERROR(__xludf.DUMMYFUNCTION("""COMPUTED_VALUE"""),"-") -> - | G65: =IFERROR(__xludf.DUMMYFUNCTION("""COMPUTED_VALUE"""),"-") -> - | H65: =IFERROR(__xludf.DUMMYFUNCTION("""COMPUTED_VALUE"""),"-") -> - | I65: =IFERROR(__xludf.DUMMYFUNCTION("""COMPUTED_VALUE"""),"-") -> - | J65: =IFERROR(__xludf.DUMMYFUNCTION("""COMPUTED_VALUE"""),"12.490,00") -> 12.490,00 | K65: =IFERROR(__xludf.DUMMYFUNCTION("""COMPUTED_VALUE"""),"12.490,00") -> 12.490,00 | L65: =IFERROR(__xludf.DUMMYFUNCTION("""COMPUTED_VALUE"""),"12.880,00") -> 12.880,00 | M65: =IFERROR(__xludf.DUMMYFUNCTION("""COMPUTED_VALUE"""),"12.830,00") -> 12.830,00 | N65: =IFERROR(__xludf.DUMMYFUNCTION("""COMPUTED_VALUE"""),"174.268.230") -> 174.268.230
A66: =MID(C66, FIND("* ", C66) + 2, FIND(" *", C66, FIND("* ", C66) + 2) - FIND("* ", C66) - 2) -> BA.C | B66: =SUBSTITUTE(SUBSTITUTE(SUBSTITUTE(D66, ".", "\\"), ",", "."), "\\", ",") -> 17,190.00 | C66: =IFERROR(__xludf.DUMMYFUNCTION("""COMPUTED_VALUE"""),"* BA.C * Cedear Bank Of ...") -> * BA.C * Cedear Bank Of ... | D66: =IFERROR(__xludf.DUMMYFUNCTION("""COMPUTED_VALUE"""),"17.190,00") -> 17.190,00 | E66: =IFERROR(__xludf.DUMMYFUNCTION("""COMPUTED_VALUE"""),"0,46%") -> 0,46% | F66: =IFERROR(__xludf.DUMMYFUNCTION("""COMPUTED_VALUE"""),"-") -> - | G66: =IFERROR(__xludf.DUMMYFUNCTION("""COMPUTED_VALUE"""),"-") -> - | H66: =IFERROR(__xludf.DUMMYFUNCTION("""COMPUTED_VALUE"""),"-") -> - | I66: =IFERROR(__xludf.DUMMYFUNCTION("""COMPUTED_VALUE"""),"-") -> - | J66: =IFERROR(__xludf.DUMMYFUNCTION("""COMPUTED_VALUE"""),"17.280,00") -> 17.280,00 | K66: =IFERROR(__xludf.DUMMYFUNCTION("""COMPUTED_VALUE"""),"17.140,00") -> 17.140,00 | L66: =IFERROR(__xludf.DUMMYFUNCTION("""COMPUTED_VALUE"""),"17.380,00") -> 17.380,00 | M66: =IFERROR(__xludf.DUMMYFUNCTION("""COMPUTED_VALUE"""),"17.110,00") -> 17.110,00 | N66: =IFERROR(__xludf.DUMMYFUNCTION("""COMPUTED_VALUE"""),"84.645.430") -> 84.645.430
A67: =MID(C67, FIND("* ", C67) + 2, FIND(" *", C67, FIND("* ", C67) + 2) - FIND("* ", C67) - 2) -> BA.CD | B67: =SUBSTITUTE(SUBSTITUTE(SUBSTITUTE(D67, ".", "\\"), ",", "."), "\\", ",") -> 12.15 | C67: =IFERROR(__xludf.DUMMYFUNCTION("""COMPUTED_VALUE"""),"* BA.CD * Cedear Bank Of ...") -> * BA.CD * Cedear Bank Of ... | D67: =IFERROR(__xludf.DUMMYFUNCTION("""COMPUTED_VALUE"""),"12,15") -> 12,15 | E67: =IFERROR(__xludf.DUMMYFUNCTION("""COMPUTED_VALUE"""),"0,57%") -> 0,57% | F67: =IFERROR(__xludf.DUMMYFUNCTION("""COMPUTED_VALUE"""),"-") -> - | G67: =IFERROR(__xludf.DUMMYFUNCTION("""COMPUTED_VALUE"""),"-") -> - | H67: =IFERROR(__xludf.DUMMYFUNCTION("""COMPUTED_VALUE"""),"-") -> - | I67: =IFERROR(__xludf.DUMMYFUNCTION("""COMPUTED_VALUE"""),"-") -> - | J67: =IFERROR(__xludf.DUMMYFUNCTION("""COMPUTED_VALUE"""),"12,27") -> 12,27 | K67: =IFERROR(__xludf.DUMMYFUNCTION("""COMPUTED_VALUE"""),"12,13") -> 12,13 | L67: =IFERROR(__xludf.DUMMYFUNCTION("""COMPUTED_VALUE"""),"12,32") -> 12,32 | M67: =IFERROR(__xludf.DUMMYFUNCTION("""COMPUTED_VALUE"""),"12,15") -> 12,15 | N67: =IFERROR(__xludf.DUMMYFUNCTION("""COMPUTED_VALUE"""),5.576) -> 5.576
A68: =MID(C68, FIND("* ", C68) + 2, FIND(" *", C68, FIND("* ", C68) + 2) - FIND("* ", C68) - 2) -> BABA | B68: =SUBSTITUTE(SUBSTITUTE(SUBSTITUTE(D68, ".", "\\"), ",", "."), "\\", ",") -> 22,070.00 | C68: =IFERROR(__xludf.DUMMYFUNCTION("""COMPUTED_VALUE"""),"* BABA * Cedear Alibaba ...") -> * BABA * Cedear Alibaba ... | D68: =IFERROR(__xludf.DUMMYFUNCTION("""COMPUTED_VALUE"""),"22.070,00") -> 22.070,00 | E68: =IFERROR(__xludf.DUMMYFUNCTION("""COMPUTED_VALUE"""),"1,70%") -> 1,70% | F68: =IFERROR(__xludf.DUMMYFUNCTION("""COMPUTED_VALUE"""),"-") -> - | G68: =IFERROR(__xludf.DUMMYFUNCTION("""COMPUTED_VALUE"""),"-") -> - | H68: =IFERROR(__xludf.DUMMYFUNCTION("""COMPUTED_VALUE"""),"-") -> - | I68: =IFERROR(__xludf.DUMMYFUNCTION("""COMPUTED_VALUE"""),"-") -> - | J68: =IFERROR(__xludf.DUMMYFUNCTION("""COMPUTED_VALUE"""),"21.850,00") -> 21.850,00 | K68: =IFERROR(__xludf.DUMMYFUNCTION("""COMPUTED_VALUE"""),"21.810,00") -> 21.810,00 | L68: =IFERROR(__xludf.DUMMYFUNCTION("""COMPUTED_VALUE"""),"22.190,00") -> 22.190,00 | M68: =IFERROR(__xludf.DUMMYFUNCTION("""COMPUTED_VALUE"""),"22.070,00") -> 22.070,00 | N68: =IFERROR(__xludf.DUMMYFUNCTION("""COMPUTED_VALUE"""),"338.932.100") -> 338.932.100
A69: =MID(C69, FIND("* ", C69) + 2, FIND(" *", C69, FIND("* ", C69) + 2) - FIND("* ", C69) - 2) -> BABAC | B69: =SUBSTITUTE(SUBSTITUTE(SUBSTITUTE(D69, ".", "\\"), ",", "."), "\\", ",") -> 15.11 | C69: =IFERROR(__xludf.DUMMYFUNCTION("""COMPUTED_VALUE"""),"* BABAC * Cedear Alibaba ...") -> * BABAC * Cedear Alibaba ... | D69: =IFERROR(__xludf.DUMMYFUNCTION("""COMPUTED_VALUE"""),"15,11") -> 15,11 | E69: =IFERROR(__xludf.DUMMYFUNCTION("""COMPUTED_VALUE"""),0.0) -> 0 | F69: =IFERROR(__xludf.DUMMYFUNCTION("""COMPUTED_VALUE"""),"-") -> - | G69: =IFERROR(__xludf.DUMMYFUNCTION("""COMPUTED_VALUE"""),"-") -> - | H69: =IFERROR(__xludf.DUMMYFUNCTION("""COMPUTED_VALUE"""),"-") -> - | I69: =IFERROR(__xludf.DUMMYFUNCTION("""COMPUTED_VALUE"""),"-") -> - | J69: =IFERROR(__xludf.DUMMYFUNCTION("""COMPUTED_VALUE"""),"15,35") -> 15,35 | K69: =IFERROR(__xludf.DUMMYFUNCTION("""COMPUTED_VALUE"""),"15,29") -> 15,29 | L69: =IFERROR(__xludf.DUMMYFUNCTION("""COMPUTED_VALUE"""),"15,35") -> 15,35 | M69: =IFERROR(__xludf.DUMMYFUNCTION("""COMPUTED_VALUE"""),"15,11") -> 15,11 | N69: =IFERROR(__xludf.DUMMYFUNCTION("""COMPUTED_VALUE"""),0.0) -> 0
A70: =MID(C70, FIND("* ", C70) + 2, FIND(" *", C70, FIND("* ", C70) + 2) - FIND("* ", C70) - 2) -> BABAD | B70: =SUBSTITUTE(SUBSTITUTE(SUBSTITUTE(D70, ".", "\\"), ",", "."), "\\", ",") -> 15.49 | C70: =IFERROR(__xludf.DUMMYFUNCTION("""COMPUTED_VALUE"""),"* BABAD * Cedear Alibaba ...") -> * BABAD * Cedear Alibaba ... | D70: =IFERROR(__xludf.DUMMYFUNCTION("""COMPUTED_VALUE"""),"15,49") -> 15,49 | E70: =IFERROR(__xludf.DUMMYFUNCTION("""COMPUTED_VALUE"""),"0,12%") -> 0,12% | F70: =IFERROR(__xludf.DUMMYFUNCTION("""COMPUTED_VALUE"""),"-") -> - | G70: =IFERROR(__xludf.DUMMYFUNCTION("""COMPUTED_VALUE"""),"-") -> - | H70: =IFERROR(__xludf.DUMMYFUNCTION("""COMPUTED_VALUE"""),"-") -> - | I70: =IFERROR(__xludf.DUMMYFUNCTION("""COMPUTED_VALUE"""),"-") -> - | J70: =IFERROR(__xludf.DUMMYFUNCTION("""COMPUTED_VALUE"""),"15,78") -> 15,78 | K70: =IFERROR(__xludf.DUMMYFUNCTION("""COMPUTED_VALUE"""),"15,47") -> 15,47 | L70: =IFERROR(__xludf.DUMMYFUNCTION("""COMPUTED_VALUE"""),"15,78") -> 15,78 | M70: =IFERROR(__xludf.DUMMYFUNCTION("""COMPUTED_VALUE"""),"15,47") -> 15,47 | N70: =IFERROR(__xludf.DUMMYFUNCTION("""COMPUTED_VALUE"""),16.387) -> 16.387
A71: =MID(C71, FIND("* ", C71) + 2, FIND(" *", C71, FIND("* ", C71) + 2) - FIND("* ", C71) - 2) -> BAD | B71: =SUBSTITUTE(SUBSTITUTE(SUBSTITUTE(D71, ".", "\\"), ",", "."), "\\", ",") -> 9.03 | C71: =IFERROR(__xludf.DUMMYFUNCTION("""COMPUTED_VALUE"""),"* BAD * Cedear The Boei...") -> * BAD * Cedear The Boei... | D71: =IFERROR(__xludf.DUMMYFUNCTION("""COMPUTED_VALUE"""),"9,03") -> 9,03 | E71: =IFERROR(__xludf.DUMMYFUNCTION("""COMPUTED_VALUE"""),"2,14%") -> 2,14% | F71: =IFERROR(__xludf.DUMMYFUNCTION("""COMPUTED_VALUE"""),"-") -> - | G71: =IFERROR(__xludf.DUMMYFUNCTION("""COMPUTED_VALUE"""),"-") -> - | H71: =IFERROR(__xludf.DUMMYFUNCTION("""COMPUTED_VALUE"""),"-") -> - | I71: =IFERROR(__xludf.DUMMYFUNCTION("""COMPUTED_VALUE"""),"-") -> - | J71: =IFERROR(__xludf.DUMMYFUNCTION("""COMPUTED_VALUE"""),"8,91") -> 8,91 | K71: =IFERROR(__xludf.DUMMYFUNCTION("""COMPUTED_VALUE"""),"8,86") -> 8,86 | L71: =IFERROR(__xludf.DUMMYFUNCTION("""COMPUTED_VALUE"""),"9,07") -> 9,07 | M71: =IFERROR(__xludf.DUMMYFUNCTION("""COMPUTED_VALUE"""),"9,03") -> 9,03 | N71: =IFERROR(__xludf.DUMMYFUNCTION("""COMPUTED_VALUE"""),3.588) -> 3.588
A72: =MID(C72, FIND("* ", C72) + 2, FIND(" *", C72, FIND("* ", C72) + 2) - FIND("* ", C72) - 2) -> BAK | B72: =SUBSTITUTE(SUBSTITUTE(SUBSTITUTE(D72, ".", "\\"), ",", "."), "\\", ",") -> 3,165.00 | C72: =IFERROR(__xludf.DUMMYFUNCTION("""COMPUTED_VALUE"""),"* BAK * Cedear Braskem Sa") -> * BAK * Cedear Braskem Sa | D72: =IFERROR(__xludf.DUMMYFUNCTION("""COMPUTED_VALUE"""),"3.165,00") -> 3.165,00 | E72: =IFERROR(__xludf.DUMMYFUNCTION("""COMPUTED_VALUE"""),"-7,52%") -> -7,52% | F72: =IFERROR(__xludf.DUMMYFUNCTION("""COMPUTED_VALUE"""),"-") -> - | G72: =IFERROR(__xludf.DUMMYFUNCTION("""COMPUTED_VALUE"""),"-") -> - | H72: =IFERROR(__xludf.DUMMYFUNCTION("""COMPUTED_VALUE"""),"-") -> - | I72: =IFERROR(__xludf.DUMMYFUNCTION("""COMPUTED_VALUE"""),"-") -> - | J72: =IFERROR(__xludf.DUMMYFUNCTION("""COMPUTED_VALUE"""),"3.397,50") -> 3.397,50 | K72: =IFERROR(__xludf.DUMMYFUNCTION("""COMPUTED_VALUE"""),"3.165,00") -> 3.165,00 | L72: =IFERROR(__xludf.DUMMYFUNCTION("""COMPUTED_VALUE"""),"3.437,50") -> 3.437,50 | M72: =IFERROR(__xludf.DUMMYFUNCTION("""COMPUTED_VALUE"""),"3.165,00") -> 3.165,00 | N72: =IFERROR(__xludf.DUMMYFUNCTION("""COMPUTED_VALUE"""),"69.405.878") -> 69.405.878
A73: =MID(C73, FIND("* ", C73) + 2, FIND(" *", C73, FIND("* ", C73) + 2) - FIND("* ", C73) - 2) -> BB | B73: =SUBSTITUTE(SUBSTITUTE(SUBSTITUTE(D73, ".", "\\"), ",", "."), "\\", ",") -> 1,613.00 | C73: =IFERROR(__xludf.DUMMYFUNCTION("""COMPUTED_VALUE"""),"* BB * Cedear Blackberry") -> * BB * Cedear Blackberry | D73: =IFERROR(__xludf.DUMMYFUNCTION("""COMPUTED_VALUE"""),"1.613,00") -> 1.613,00 | E73: =IFERROR(__xludf.DUMMYFUNCTION("""COMPUTED_VALUE"""),"-2,59%") -> -2,59% | F73: =IFERROR(__xludf.DUMMYFUNCTION("""COMPUTED_VALUE"""),"-") -> - | G73: =IFERROR(__xludf.DUMMYFUNCTION("""COMPUTED_VALUE"""),"-") -> - | H73: =IFERROR(__xludf.DUMMYFUNCTION("""COMPUTED_VALUE"""),"-") -> - | I73: =IFERROR(__xludf.DUMMYFUNCTION("""COMPUTED_VALUE"""),"-") -> - | J73: =IFERROR(__xludf.DUMMYFUNCTION("""COMPUTED_VALUE"""),"1.650,00") -> 1.650,00 | K73: =IFERROR(__xludf.DUMMYFUNCTION("""COMPUTED_VALUE"""),"1.598,00") -> 1.598,00 | L73: =IFERROR(__xludf.DUMMYFUNCTION("""COMPUTED_VALUE"""),"1.675,00") -> 1.675,00 | M73: =IFERROR(__xludf.DUMMYFUNCTION("""COMPUTED_VALUE"""),"1.613,00") -> 1.613,00 | N73: =IFERROR(__xludf.DUMMYFUNCTION("""COMPUTED_VALUE"""),"24.227.023") -> 24.227.023
A74: =MID(C74, FIND("* ", C74) + 2, FIND(" *", C74, FIND("* ", C74) + 2) - FIND("* ", C74) - 2) -> BBAS3 | B74: =SUBSTITUTE(SUBSTITUTE(SUBSTITUTE(D74, ".", "\\"), ",", "."), "\\", ",") -> 3,307.50 | C74: =IFERROR(__xludf.DUMMYFUNCTION("""COMPUTED_VALUE"""),"* BBAS3 * Cedear Banco Do...") -> * BBAS3 * Cedear Banco Do... | D74: =IFERROR(__xludf.DUMMYFUNCTION("""COMPUTED_VALUE"""),"3.307,50") -> 3.307,50 | E74: =IFERROR(__xludf.DUMMYFUNCTION("""COMPUTED_VALUE"""),"-2,50%") -> -2,50% | F74: =IFERROR(__xludf.DUMMYFUNCTION("""COMPUTED_VALUE"""),"-") -> - | G74: =IFERROR(__xludf.DUMMYFUNCTION("""COMPUTED_VALUE"""),"-") -> - | H74: =IFERROR(__xludf.DUMMYFUNCTION("""COMPUTED_VALUE"""),"-") -> - | I74: =IFERROR(__xludf.DUMMYFUNCTION("""COMPUTED_VALUE"""),"-") -> - | J74: =IFERROR(__xludf.DUMMYFUNCTION("""COMPUTED_VALUE"""),"3.372,50") -> 3.372,50 | K74: =IFERROR(__xludf.DUMMYFUNCTION("""COMPUTED_VALUE"""),"3.237,50") -> 3.237,50 | L74: =IFERROR(__xludf.DUMMYFUNCTION("""COMPUTED_VALUE"""),"3.445,00") -> 3.445,00 | M74: =IFERROR(__xludf.DUMMYFUNCTION("""COMPUTED_VALUE"""),"3.307,50") -> 3.307,50 | N74: =IFERROR(__xludf.DUMMYFUNCTION("""COMPUTED_VALUE"""),"97.949.438") -> 97.949.438
A75: =MID(C75, FIND("* ", C75) + 2, FIND(" *", C75, FIND("* ", C75) + 2) - FIND("* ", C75) - 2) -> BBD | B75: =SUBSTITUTE(SUBSTITUTE(SUBSTITUTE(D75, ".", "\\"), ",", "."), "\\", ",") -> 5,200.00 | C75: =IFERROR(__xludf.DUMMYFUNCTION("""COMPUTED_VALUE"""),"* BBD * Cedear Banco Br...") -> * BBD * Cedear Banco Br... | D75: =IFERROR(__xludf.DUMMYFUNCTION("""COMPUTED_VALUE"""),"5.200,00") -> 5.200,00 | E75: =IFERROR(__xludf.DUMMYFUNCTION("""COMPUTED_VALUE"""),"-1,70%") -> -1,70% | F75: =IFERROR(__xludf.DUMMYFUNCTION("""COMPUTED_VALUE"""),"-") -> - | G75: =IFERROR(__xludf.DUMMYFUNCTION("""COMPUTED_VALUE"""),"-") -> - | H75: =IFERROR(__xludf.DUMMYFUNCTION("""COMPUTED_VALUE"""),"-") -> - | I75: =IFERROR(__xludf.DUMMYFUNCTION("""COMPUTED_VALUE"""),"-") -> - | J75: =IFERROR(__xludf.DUMMYFUNCTION("""COMPUTED_VALUE"""),"5.360,00") -> 5.360,00 | K75: =IFERROR(__xludf.DUMMYFUNCTION("""COMPUTED_VALUE"""),"5.145,00") -> 5.145,00 | L75: =IFERROR(__xludf.DUMMYFUNCTION("""COMPUTED_VALUE"""),"5.390,00") -> 5.390,00 | M75: =IFERROR(__xludf.DUMMYFUNCTION("""COMPUTED_VALUE"""),"5.200,00") -> 5.200,00 | N75: =IFERROR(__xludf.DUMMYFUNCTION("""COMPUTED_VALUE"""),"610.894.905") -> 610.894.905
A76: =MID(C76, FIND("* ", C76) + 2, FIND(" *", C76, FIND("* ", C76) + 2) - FIND("* ", C76) - 2) -> BBDC | B76: =SUBSTITUTE(SUBSTITUTE(SUBSTITUTE(D76, ".", "\\"), ",", "."), "\\", ",") -> 3.61 | C76: =IFERROR(__xludf.DUMMYFUNCTION("""COMPUTED_VALUE"""),"* BBDC * Cedear Banco Br...") -> * BBDC * Cedear Banco Br... | D76: =IFERROR(__xludf.DUMMYFUNCTION("""COMPUTED_VALUE"""),"3,61") -> 3,61 | E76: =IFERROR(__xludf.DUMMYFUNCTION("""COMPUTED_VALUE"""),"-13,56%") -> -13,56% | F76: =IFERROR(__xludf.DUMMYFUNCTION("""COMPUTED_VALUE"""),"-") -> - | G76: =IFERROR(__xludf.DUMMYFUNCTION("""COMPUTED_VALUE"""),"-") -> - | H76: =IFERROR(__xludf.DUMMYFUNCTION("""COMPUTED_VALUE"""),"-") -> - | I76: =IFERROR(__xludf.DUMMYFUNCTION("""COMPUTED_VALUE"""),"-") -> - | J76: =IFERROR(__xludf.DUMMYFUNCTION("""COMPUTED_VALUE"""),"3,64") -> 3,64 | K76: =IFERROR(__xludf.DUMMYFUNCTION("""COMPUTED_VALUE"""),"3,64") -> 3,64 | L76: =IFERROR(__xludf.DUMMYFUNCTION("""COMPUTED_VALUE"""),"3,64") -> 3,64 | M76: =IFERROR(__xludf.DUMMYFUNCTION("""COMPUTED_VALUE"""),"3,61") -> 3,61 | N76: =IFERROR(__xludf.DUMMYFUNCTION("""COMPUTED_VALUE"""),7.0) -> 7
A77: =MID(C77, FIND("* ", C77) + 2, FIND(" *", C77, FIND("* ", C77) + 2) - FIND("* ", C77) - 2) -> BBDD | B77: =SUBSTITUTE(SUBSTITUTE(SUBSTITUTE(D77, ".", "\\"), ",", "."), "\\", ",") -> 3.65 | C77: =IFERROR(__xludf.DUMMYFUNCTION("""COMPUTED_VALUE"""),"* BBDD * Cedear Banco Br...") -> * BBDD * Cedear Banco Br... | D77: =IFERROR(__xludf.DUMMYFUNCTION("""COMPUTED_VALUE"""),"3,65") -> 3,65 | E77: =IFERROR(__xludf.DUMMYFUNCTION("""COMPUTED_VALUE"""),"-3,31%") -> -3,31% | F77: =IFERROR(__xludf.DUMMYFUNCTION("""COMPUTED_VALUE"""),"-") -> - | G77: =IFERROR(__xludf.DUMMYFUNCTION("""COMPUTED_VALUE"""),"-") -> - | H77: =IFERROR(__xludf.DUMMYFUNCTION("""COMPUTED_VALUE"""),"-") -> - | I77: =IFERROR(__xludf.DUMMYFUNCTION("""COMPUTED_VALUE"""),"-") -> - | J77: =IFERROR(__xludf.DUMMYFUNCTION("""COMPUTED_VALUE"""),"3,73") -> 3,73 | K77: =IFERROR(__xludf.DUMMYFUNCTION("""COMPUTED_VALUE"""),"3,50") -> 3,50 | L77: =IFERROR(__xludf.DUMMYFUNCTION("""COMPUTED_VALUE"""),"3,81") -> 3,81 | M77: =IFERROR(__xludf.DUMMYFUNCTION("""COMPUTED_VALUE"""),"3,65") -> 3,65 | N77: =IFERROR(__xludf.DUMMYFUNCTION("""COMPUTED_VALUE"""),218.147) -> 218.147
A78: =MID(C78, FIND("* ", C78) + 2, FIND(" *", C78, FIND("* ", C78) + 2) - FIND("* ", C78) - 2) -> BBV | B78: =SUBSTITUTE(SUBSTITUTE(SUBSTITUTE(D78, ".", "\\"), ",", "."), "\\", ",") -> 29,900.00 | C78: =IFERROR(__xludf.DUMMYFUNCTION("""COMPUTED_VALUE"""),"* BBV * Cedear Banco Bi...") -> * BBV * Cedear Banco Bi... | D78: =IFERROR(__xludf.DUMMYFUNCTION("""COMPUTED_VALUE"""),"29.900,00") -> 29.900,00 | E78: =IFERROR(__xludf.DUMMYFUNCTION("""COMPUTED_VALUE"""),"-1,45%") -> -1,45% | F78: =IFERROR(__xludf.DUMMYFUNCTION("""COMPUTED_VALUE"""),"-") -> - | G78: =IFERROR(__xludf.DUMMYFUNCTION("""COMPUTED_VALUE"""),"-") -> - | H78: =IFERROR(__xludf.DUMMYFUNCTION("""COMPUTED_VALUE"""),"-") -> - | I78: =IFERROR(__xludf.DUMMYFUNCTION("""COMPUTED_VALUE"""),"-") -> - | J78: =IFERROR(__xludf.DUMMYFUNCTION("""COMPUTED_VALUE"""),"30.280,00") -> 30.280,00 | K78: =IFERROR(__xludf.DUMMYFUNCTION("""COMPUTED_VALUE"""),"29.880,00") -> 29.880,00 | L78: =IFERROR(__xludf.DUMMYFUNCTION("""COMPUTED_VALUE"""),"30.380,00") -> 30.380,00 | M78: =IFERROR(__xludf.DUMMYFUNCTION("""COMPUTED_VALUE"""),"29.900,00") -> 29.900,00 | N78: =IFERROR(__xludf.DUMMYFUNCTION("""COMPUTED_VALUE"""),"6.134.280") -> 6.134.280
A79: =MID(C79, FIND("* ", C79) + 2, FIND(" *", C79, FIND("* ", C79) + 2) - FIND("* ", C79) - 2) -> BCS | B79: =SUBSTITUTE(SUBSTITUTE(SUBSTITUTE(D79, ".", "\\"), ",", "."), "\\", ",") -> 30,080.00 | C79: =IFERROR(__xludf.DUMMYFUNCTION("""COMPUTED_VALUE"""),"* BCS * Cedear Barclays...") -> * BCS * Cedear Barclays... | D79: =IFERROR(__xludf.DUMMYFUNCTION("""COMPUTED_VALUE"""),"30.080,00") -> 30.080,00 | E79: =IFERROR(__xludf.DUMMYFUNCTION("""COMPUTED_VALUE"""),"-1,31%") -> -1,31% | F79: =IFERROR(__xludf.DUMMYFUNCTION("""COMPUTED_VALUE"""),"-") -> - | G79: =IFERROR(__xludf.DUMMYFUNCTION("""COMPUTED_VALUE"""),"-") -> - | H79: =IFERROR(__xludf.DUMMYFUNCTION("""COMPUTED_VALUE"""),"-") -> - | I79: =IFERROR(__xludf.DUMMYFUNCTION("""COMPUTED_VALUE"""),"-") -> - | J79: =IFERROR(__xludf.DUMMYFUNCTION("""COMPUTED_VALUE"""),"30.400,00") -> 30.400,00 | K79: =IFERROR(__xludf.DUMMYFUNCTION("""COMPUTED_VALUE"""),"30.000,00") -> 30.000,00 | L79: =IFERROR(__xludf.DUMMYFUNCTION("""COMPUTED_VALUE"""),"30.400,00") -> 30.400,00 | M79: =IFERROR(__xludf.DUMMYFUNCTION("""COMPUTED_VALUE"""),"30.080,00") -> 30.080,00 | N79: =IFERROR(__xludf.DUMMYFUNCTION("""COMPUTED_VALUE"""),"1.203.320") -> 1.203.320
A80: =MID(C80, FIND("* ", C80) + 2, FIND(" *", C80, FIND("* ", C80) + 2) - FIND("* ", C80) - 2) -> BHP | B80: =SUBSTITUTE(SUBSTITUTE(SUBSTITUTE(D80, ".", "\\"), ",", "."), "\\", ",") -> 50,600.00 | C80: =IFERROR(__xludf.DUMMYFUNCTION("""COMPUTED_VALUE"""),"* BHP * Cedear Bhp Bill...") -> * BHP * Cedear Bhp Bill... | D80: =IFERROR(__xludf.DUMMYFUNCTION("""COMPUTED_VALUE"""),"50.600,00") -> 50.600,00 | E80: =IFERROR(__xludf.DUMMYFUNCTION("""COMPUTED_VALUE"""),"-2,41%") -> -2,41% | F80: =IFERROR(__xludf.DUMMYFUNCTION("""COMPUTED_VALUE"""),"-") -> - | G80: =IFERROR(__xludf.DUMMYFUNCTION("""COMPUTED_VALUE"""),"-") -> - | H80: =IFERROR(__xludf.DUMMYFUNCTION("""COMPUTED_VALUE"""),"-") -> - | I80: =IFERROR(__xludf.DUMMYFUNCTION("""COMPUTED_VALUE"""),"-") -> - | J80: =IFERROR(__xludf.DUMMYFUNCTION("""COMPUTED_VALUE"""),"51.075,00") -> 51.075,00 | K80: =IFERROR(__xludf.DUMMYFUNCTION("""COMPUTED_VALUE"""),"50.200,00") -> 50.200,00 | L80: =IFERROR(__xludf.DUMMYFUNCTION("""COMPUTED_VALUE"""),"51.250,00") -> 51.250,00 | M80: =IFERROR(__xludf.DUMMYFUNCTION("""COMPUTED_VALUE"""),"50.600,00") -> 50.600,00 | N80: =IFERROR(__xludf.DUMMYFUNCTION("""COMPUTED_VALUE"""),"37.388.675") -> 37.388.675
A81: =MID(C81, FIND("* ", C81) + 2, FIND(" *", C81, FIND("* ", C81) + 2) - FIND("* ", C81) - 2) -> BIDU | B81: =SUBSTITUTE(SUBSTITUTE(SUBSTITUTE(D81, ".", "\\"), ",", "."), "\\", ",") -> 16,640.00 | C81: =IFERROR(__xludf.DUMMYFUNCTION("""COMPUTED_VALUE"""),"* BIDU * Cedear Baidu, Inc.") -> * BIDU * Cedear Baidu, Inc. | D81: =IFERROR(__xludf.DUMMYFUNCTION("""COMPUTED_VALUE"""),"16.640,00") -> 16.640,00 | E81: =IFERROR(__xludf.DUMMYFUNCTION("""COMPUTED_VALUE"""),"1,96%") -> 1,96% | F81: =IFERROR(__xludf.DUMMYFUNCTION("""COMPUTED_VALUE"""),"-") -> - | G81: =IFERROR(__xludf.DUMMYFUNCTION("""COMPUTED_VALUE"""),"-") -> - | H81: =IFERROR(__xludf.DUMMYFUNCTION("""COMPUTED_VALUE"""),"-") -> - | I81: =IFERROR(__xludf.DUMMYFUNCTION("""COMPUTED_VALUE"""),"-") -> - | J81: =IFERROR(__xludf.DUMMYFUNCTION("""COMPUTED_VALUE"""),"16.780,00") -> 16.780,00 | K81: =IFERROR(__xludf.DUMMYFUNCTION("""COMPUTED_VALUE"""),"16.480,00") -> 16.480,00 | L81: =IFERROR(__xludf.DUMMYFUNCTION("""COMPUTED_VALUE"""),"16.920,00") -> 16.920,00 | M81: =IFERROR(__xludf.DUMMYFUNCTION("""COMPUTED_VALUE"""),"16.640,00") -> 16.640,00 | N81: =IFERROR(__xludf.DUMMYFUNCTION("""COMPUTED_VALUE"""),"223.269.350") -> 223.269.350
A82: =MID(C82, FIND("* ", C82) + 2, FIND(" *", C82, FIND("* ", C82) + 2) - FIND("* ", C82) - 2) -> BIDUD | B82: =SUBSTITUTE(SUBSTITUTE(SUBSTITUTE(D82, ".", "\\"), ",", "."), "\\", ",") -> 11.64 | C82: =IFERROR(__xludf.DUMMYFUNCTION("""COMPUTED_VALUE"""),"* BIDUD * Cedear Baidu, Inc.") -> * BIDUD * Cedear Baidu, Inc. | D82: =IFERROR(__xludf.DUMMYFUNCTION("""COMPUTED_VALUE"""),"11,64") -> 11,64 | E82: =IFERROR(__xludf.DUMMYFUNCTION("""COMPUTED_VALUE"""),"1,65%") -> 1,65% | F82: =IFERROR(__xludf.DUMMYFUNCTION("""COMPUTED_VALUE"""),"-") -> - | G82: =IFERROR(__xludf.DUMMYFUNCTION("""COMPUTED_VALUE"""),"-") -> - | H82: =IFERROR(__xludf.DUMMYFUNCTION("""COMPUTED_VALUE"""),"-") -> - | I82: =IFERROR(__xludf.DUMMYFUNCTION("""COMPUTED_VALUE"""),"-") -> - | J82: =IFERROR(__xludf.DUMMYFUNCTION("""COMPUTED_VALUE"""),"11,85") -> 11,85 | K82: =IFERROR(__xludf.DUMMYFUNCTION("""COMPUTED_VALUE"""),"11,70") -> 11,70 | L82: =IFERROR(__xludf.DUMMYFUNCTION("""COMPUTED_VALUE"""),"11,92") -> 11,92 | M82: =IFERROR(__xludf.DUMMYFUNCTION("""COMPUTED_VALUE"""),"11,64") -> 11,64 | N82: =IFERROR(__xludf.DUMMYFUNCTION("""COMPUTED_VALUE"""),412.0) -> 412
A83: =MID(C83, FIND("* ", C83) + 2, FIND(" *", C83, FIND("* ", C83) + 2) - FIND("* ", C83) - 2) -> BIIB | B83: =SUBSTITUTE(SUBSTITUTE(SUBSTITUTE(D83, ".", "\\"), ",", "."), "\\", ",") -> 20,570.00 | C83: =IFERROR(__xludf.DUMMYFUNCTION("""COMPUTED_VALUE"""),"* BIIB * Cedear Biogen Inc.") -> * BIIB * Cedear Biogen Inc. | D83: =IFERROR(__xludf.DUMMYFUNCTION("""COMPUTED_VALUE"""),"20.570,00") -> 20.570,00 | E83: =IFERROR(__xludf.DUMMYFUNCTION("""COMPUTED_VALUE"""),"-0,57%") -> -0,57% | F83: =IFERROR(__xludf.DUMMYFUNCTION("""COMPUTED_VALUE"""),"-") -> - | G83: =IFERROR(__xludf.DUMMYFUNCTION("""COMPUTED_VALUE"""),"-") -> - | H83: =IFERROR(__xludf.DUMMYFUNCTION("""COMPUTED_VALUE"""),"-") -> - | I83: =IFERROR(__xludf.DUMMYFUNCTION("""COMPUTED_VALUE"""),"-") -> - | J83: =IFERROR(__xludf.DUMMYFUNCTION("""COMPUTED_VALUE"""),"20.650,00") -> 20.650,00 | K83: =IFERROR(__xludf.DUMMYFUNCTION("""COMPUTED_VALUE"""),"20.520,00") -> 20.520,00 | L83: =IFERROR(__xludf.DUMMYFUNCTION("""COMPUTED_VALUE"""),"20.910,00") -> 20.910,00 | M83: =IFERROR(__xludf.DUMMYFUNCTION("""COMPUTED_VALUE"""),"20.570,00") -> 20.570,00 | N83: =IFERROR(__xludf.DUMMYFUNCTION("""COMPUTED_VALUE"""),"22.429.390") -> 22.429.390
A84: =MID(C84, FIND("* ", C84) + 2, FIND(" *", C84, FIND("* ", C84) + 2) - FIND("* ", C84) - 2) -> BIOX | B84: =SUBSTITUTE(SUBSTITUTE(SUBSTITUTE(D84, ".", "\\"), ",", "."), "\\", ",") -> 793.50 | C84: =IFERROR(__xludf.DUMMYFUNCTION("""COMPUTED_VALUE"""),"* BIOX * Cedear Bioceres...") -> * BIOX * Cedear Bioceres... | D84: =IFERROR(__xludf.DUMMYFUNCTION("""COMPUTED_VALUE"""),"793,50") -> 793,50 | E84: =IFERROR(__xludf.DUMMYFUNCTION("""COMPUTED_VALUE"""),"-9,21%") -> -9,21% | F84: =IFERROR(__xludf.DUMMYFUNCTION("""COMPUTED_VALUE"""),"-") -> - | G84: =IFERROR(__xludf.DUMMYFUNCTION("""COMPUTED_VALUE"""),"-") -> - | H84: =IFERROR(__xludf.DUMMYFUNCTION("""COMPUTED_VALUE"""),"-") -> - | I84: =IFERROR(__xludf.DUMMYFUNCTION("""COMPUTED_VALUE"""),"-") -> - | J84: =IFERROR(__xludf.DUMMYFUNCTION("""COMPUTED_VALUE"""),"869,50") -> 869,50 | K84: =IFERROR(__xludf.DUMMYFUNCTION("""COMPUTED_VALUE"""),"766,00") -> 766,00 | L84: =IFERROR(__xludf.DUMMYFUNCTION("""COMPUTED_VALUE"""),"869,50") -> 869,50 | M84: =IFERROR(__xludf.DUMMYFUNCTION("""COMPUTED_VALUE"""),"793,50") -> 793,50 | N84: =IFERROR(__xludf.DUMMYFUNCTION("""COMPUTED_VALUE"""),"345.992.191") -> 345.992.191
A85: =MID(C85, FIND("* ", C85) + 2, FIND(" *", C85, FIND("* ", C85) + 2) - FIND("* ", C85) - 2) -> BIOXC | B85: =SUBSTITUTE(SUBSTITUTE(SUBSTITUTE(D85, ".", "\\"), ",", "."), "\\", ",") -> 0.52 | C85: =IFERROR(__xludf.DUMMYFUNCTION("""COMPUTED_VALUE"""),"* BIOXC * Cedear Bioceres...") -> * BIOXC * Cedear Bioceres... | D85: =IFERROR(__xludf.DUMMYFUNCTION("""COMPUTED_VALUE"""),"0,52") -> 0,52 | E85: =IFERROR(__xludf.DUMMYFUNCTION("""COMPUTED_VALUE"""),0.0) -> 0 | F85: =IFERROR(__xludf.DUMMYFUNCTION("""COMPUTED_VALUE"""),"-") -> - | G85: =IFERROR(__xludf.DUMMYFUNCTION("""COMPUTED_VALUE"""),"-") -> - | H85: =IFERROR(__xludf.DUMMYFUNCTION("""COMPUTED_VALUE"""),"-") -> - | I85: =IFERROR(__xludf.DUMMYFUNCTION("""COMPUTED_VALUE"""),"-") -> - | J85: =IFERROR(__xludf.DUMMYFUNCTION("""COMPUTED_VALUE"""),"0,54") -> 0,54 | K85: =IFERROR(__xludf.DUMMYFUNCTION("""COMPUTED_VALUE"""),"0,54") -> 0,54 | L85: =IFERROR(__xludf.DUMMYFUNCTION("""COMPUTED_VALUE"""),"0,54") -> 0,54 | M85: =IFERROR(__xludf.DUMMYFUNCTION("""COMPUTED_VALUE"""),"0,52") -> 0,52 | N85: =IFERROR(__xludf.DUMMYFUNCTION("""COMPUTED_VALUE"""),0.0) -> 0
A86: =MID(C86, FIND("* ", C86) + 2, FIND(" *", C86, FIND("* ", C86) + 2) - FIND("* ", C86) - 2) -> BIOXD | B86: =SUBSTITUTE(SUBSTITUTE(SUBSTITUTE(D86, ".", "\\"), ",", "."), "\\", ",") -> 0.54 | C86: =IFERROR(__xludf.DUMMYFUNCTION("""COMPUTED_VALUE"""),"* BIOXD * Cedear Bioceres...") -> * BIOXD * Cedear Bioceres... | D86: =IFERROR(__xludf.DUMMYFUNCTION("""COMPUTED_VALUE"""),"0,54") -> 0,54 | E86: =IFERROR(__xludf.DUMMYFUNCTION("""COMPUTED_VALUE"""),"-13,16%") -> -13,16% | F86: =IFERROR(__xludf.DUMMYFUNCTION("""COMPUTED_VALUE"""),"-") -> - | G86: =IFERROR(__xludf.DUMMYFUNCTION("""COMPUTED_VALUE"""),"-") -> - | H86: =IFERROR(__xludf.DUMMYFUNCTION("""COMPUTED_VALUE"""),"-") -> - | I86: =IFERROR(__xludf.DUMMYFUNCTION("""COMPUTED_VALUE"""),"-") -> - | J86: =IFERROR(__xludf.DUMMYFUNCTION("""COMPUTED_VALUE"""),"0,63") -> 0,63 | K86: =IFERROR(__xludf.DUMMYFUNCTION("""COMPUTED_VALUE"""),"0,54") -> 0,54 | L86: =IFERROR(__xludf.DUMMYFUNCTION("""COMPUTED_VALUE"""),"0,64") -> 0,64 | M86: =IFERROR(__xludf.DUMMYFUNCTION("""COMPUTED_VALUE"""),"0,54") -> 0,54 | N86: =IFERROR(__xludf.DUMMYFUNCTION("""COMPUTED_VALUE"""),3.891) -> 3.891
A87: =MID(C87, FIND("* ", C87) + 2, FIND(" *", C87, FIND("* ", C87) + 2) - FIND("* ", C87) - 2) -> BITF | B87: =SUBSTITUTE(SUBSTITUTE(SUBSTITUTE(D87, ".", "\\"), ",", "."), "\\", ",") -> 16,370.00 | C87: =IFERROR(__xludf.DUMMYFUNCTION("""COMPUTED_VALUE"""),"* BITF * Cedear Bitfarms...") -> * BITF * Cedear Bitfarms... | D87: =IFERROR(__xludf.DUMMYFUNCTION("""COMPUTED_VALUE"""),"16.370,00") -> 16.370,00 | E87: =IFERROR(__xludf.DUMMYFUNCTION("""COMPUTED_VALUE"""),"1,86%") -> 1,86% | F87: =IFERROR(__xludf.DUMMYFUNCTION("""COMPUTED_VALUE"""),"-") -> - | G87: =IFERROR(__xludf.DUMMYFUNCTION("""COMPUTED_VALUE"""),"-") -> - | H87: =IFERROR(__xludf.DUMMYFUNCTION("""COMPUTED_VALUE"""),"-") -> - | I87: =IFERROR(__xludf.DUMMYFUNCTION("""COMPUTED_VALUE"""),"-") -> - | J87: =IFERROR(__xludf.DUMMYFUNCTION("""COMPUTED_VALUE"""),"16.890,00") -> 16.890,00 | K87: =IFERROR(__xludf.DUMMYFUNCTION("""COMPUTED_VALUE"""),"15.980,00") -> 15.980,00 | L87: =IFERROR(__xludf.DUMMYFUNCTION("""COMPUTED_VALUE"""),"17.070,00") -> 17.070,00 | M87: =IFERROR(__xludf.DUMMYFUNCTION("""COMPUTED_VALUE"""),"16.070,00") -> 16.070,00 | N87: =IFERROR(__xludf.DUMMYFUNCTION("""COMPUTED_VALUE"""),"308.895.640") -> 308.895.640
A88: =MID(C88, FIND("* ", C88) + 2, FIND(" *", C88, FIND("* ", C88) + 2) - FIND("* ", C88) - 2) -> BITFC | B88: =SUBSTITUTE(SUBSTITUTE(SUBSTITUTE(D88, ".", "\\"), ",", "."), "\\", ",") -> 11.12 | C88: =IFERROR(__xludf.DUMMYFUNCTION("""COMPUTED_VALUE"""),"* BITFC * Cedear Bitfarms...") -> * BITFC * Cedear Bitfarms... | D88: =IFERROR(__xludf.DUMMYFUNCTION("""COMPUTED_VALUE"""),"11,12") -> 11,12 | E88: =IFERROR(__xludf.DUMMYFUNCTION("""COMPUTED_VALUE"""),0.0) -> 0 | F88: =IFERROR(__xludf.DUMMYFUNCTION("""COMPUTED_VALUE"""),"-") -> - | G88: =IFERROR(__xludf.DUMMYFUNCTION("""COMPUTED_VALUE"""),"-") -> - | H88: =IFERROR(__xludf.DUMMYFUNCTION("""COMPUTED_VALUE"""),"-") -> - | I88: =IFERROR(__xludf.DUMMYFUNCTION("""COMPUTED_VALUE"""),"-") -> - | J88: =IFERROR(__xludf.DUMMYFUNCTION("""COMPUTED_VALUE"""),"11,55") -> 11,55 | K88: =IFERROR(__xludf.DUMMYFUNCTION("""COMPUTED_VALUE"""),"11,02") -> 11,02 | L88: =IFERROR(__xludf.DUMMYFUNCTION("""COMPUTED_VALUE"""),"11,55") -> 11,55 | M88: =IFERROR(__xludf.DUMMYFUNCTION("""COMPUTED_VALUE"""),"11,12") -> 11,12 | N88: =IFERROR(__xludf.DUMMYFUNCTION("""COMPUTED_VALUE"""),0.0) -> 0
A89: =MID(C89, FIND("* ", C89) + 2, FIND(" *", C89, FIND("* ", C89) + 2) - FIND("* ", C89) - 2) -> BITFD | B89: =SUBSTITUTE(SUBSTITUTE(SUBSTITUTE(D89, ".", "\\"), ",", "."), "\\", ",") -> 11.42 | C89: =IFERROR(__xludf.DUMMYFUNCTION("""COMPUTED_VALUE"""),"* BITFD * Cedear Bitfarms...") -> * BITFD * Cedear Bitfarms... | D89: =IFERROR(__xludf.DUMMYFUNCTION("""COMPUTED_VALUE"""),"11,42") -> 11,42 | E89: =IFERROR(__xludf.DUMMYFUNCTION("""COMPUTED_VALUE"""),"-0,69%") -> -0,69% | F89: =IFERROR(__xludf.DUMMYFUNCTION("""COMPUTED_VALUE"""),"-") -> - | G89: =IFERROR(__xludf.DUMMYFUNCTION("""COMPUTED_VALUE"""),"-") -> - | H89: =IFERROR(__xludf.DUMMYFUNCTION("""COMPUTED_VALUE"""),"-") -> - | I89: =IFERROR(__xludf.DUMMYFUNCTION("""COMPUTED_VALUE"""),"-") -> - | J89: =IFERROR(__xludf.DUMMYFUNCTION("""COMPUTED_VALUE"""),"12,10") -> 12,10 | K89: =IFERROR(__xludf.DUMMYFUNCTION("""COMPUTED_VALUE"""),"11,40") -> 11,40 | L89: =IFERROR(__xludf.DUMMYFUNCTION("""COMPUTED_VALUE"""),"12,10") -> 12,10 | M89: =IFERROR(__xludf.DUMMYFUNCTION("""COMPUTED_VALUE"""),"11,42") -> 11,42 | N89: =IFERROR(__xludf.DUMMYFUNCTION("""COMPUTED_VALUE"""),8.486) -> 8.486
A90: =MID(C90, FIND("* ", C90) + 2, FIND(" *", C90, FIND("* ", C90) + 2) - FIND("* ", C90) - 2) -> BK | B90: =SUBSTITUTE(SUBSTITUTE(SUBSTITUTE(D90, ".", "\\"), ",", "."), "\\", ",") -> 85,250.00 | C90: =IFERROR(__xludf.DUMMYFUNCTION("""COMPUTED_VALUE"""),"* BK * Cedear The Bank...") -> * BK * Cedear The Bank... | D90: =IFERROR(__xludf.DUMMYFUNCTION("""COMPUTED_VALUE"""),"85.250,00") -> 85.250,00 | E90: =IFERROR(__xludf.DUMMYFUNCTION("""COMPUTED_VALUE"""),"-0,05%") -> -0,05% | F90: =IFERROR(__xludf.DUMMYFUNCTION("""COMPUTED_VALUE"""),"-") -> - | G90: =IFERROR(__xludf.DUMMYFUNCTION("""COMPUTED_VALUE"""),"-") -> - | H90: =IFERROR(__xludf.DUMMYFUNCTION("""COMPUTED_VALUE"""),"-") -> - | I90: =IFERROR(__xludf.DUMMYFUNCTION("""COMPUTED_VALUE"""),"-") -> - | J90: =IFERROR(__xludf.DUMMYFUNCTION("""COMPUTED_VALUE"""),"85.150,00") -> 85.150,00 | K90: =IFERROR(__xludf.DUMMYFUNCTION("""COMPUTED_VALUE"""),"84.950,00") -> 84.950,00 | L90: =IFERROR(__xludf.DUMMYFUNCTION("""COMPUTED_VALUE"""),"85.150,00") -> 85.150,00 | M90: =IFERROR(__xludf.DUMMYFUNCTION("""COMPUTED_VALUE"""),"85.250,00") -> 85.250,00 | N90: =IFERROR(__xludf.DUMMYFUNCTION("""COMPUTED_VALUE"""),340.2) -> 340.2
A91: =MID(C91, FIND("* ", C91) + 2, FIND(" *", C91, FIND("* ", C91) + 2) - FIND("* ", C91) - 2) -> BKNG | B91: =SUBSTITUTE(SUBSTITUTE(SUBSTITUTE(D91, ".", "\\"), ",", "."), "\\", ",") -> 8,930.00 | C91: =IFERROR(__xludf.DUMMYFUNCTION("""COMPUTED_VALUE"""),"* BKNG * Cedear Booking ...") -> * BKNG * Cedear Booking ... | D91: =IFERROR(__xludf.DUMMYFUNCTION("""COMPUTED_VALUE"""),"8.930,00") -> 8.930,00 | E91: =IFERROR(__xludf.DUMMYFUNCTION("""COMPUTED_VALUE"""),0.0) -> 0 | F91: =IFERROR(__xludf.DUMMYFUNCTION("""COMPUTED_VALUE"""),"-") -> - | G91: =IFERROR(__xludf.DUMMYFUNCTION("""COMPUTED_VALUE"""),"-") -> - | H91: =IFERROR(__xludf.DUMMYFUNCTION("""COMPUTED_VALUE"""),"-") -> - | I91: =IFERROR(__xludf.DUMMYFUNCTION("""COMPUTED_VALUE"""),"-") -> - | J91: =IFERROR(__xludf.DUMMYFUNCTION("""COMPUTED_VALUE"""),"9.015,00") -> 9.015,00 | K91: =IFERROR(__xludf.DUMMYFUNCTION("""COMPUTED_VALUE"""),"8.800,00") -> 8.800,00 | L91: =IFERROR(__xludf.DUMMYFUNCTION("""COMPUTED_VALUE"""),"9.050,00") -> 9.050,00 | M91: =IFERROR(__xludf.DUMMYFUNCTION("""COMPUTED_VALUE"""),"8.930,00") -> 8.930,00 | N91: =IFERROR(__xludf.DUMMYFUNCTION("""COMPUTED_VALUE"""),"3.406.865") -> 3.406.865
A92: =MID(C92, FIND("* ", C92) + 2, FIND(" *", C92, FIND("* ", C92) + 2) - FIND("* ", C92) - 2) -> BKNGD | B92: =SUBSTITUTE(SUBSTITUTE(SUBSTITUTE(D92, ".", "\\"), ",", "."), "\\", ",") -> 6.22 | C92: =IFERROR(__xludf.DUMMYFUNCTION("""COMPUTED_VALUE"""),"* BKNGD * Cedear Booking ...") -> * BKNGD * Cedear Booking ... | D92: =IFERROR(__xludf.DUMMYFUNCTION("""COMPUTED_VALUE"""),"6,22") -> 6,22 | E92: =IFERROR(__xludf.DUMMYFUNCTION("""COMPUTED_VALUE"""),"0,32%") -> 0,32% | F92: =IFERROR(__xludf.DUMMYFUNCTION("""COMPUTED_VALUE"""),"-") -> - | G92: =IFERROR(__xludf.DUMMYFUNCTION("""COMPUTED_VALUE"""),"-") -> - | H92: =IFERROR(__xludf.DUMMYFUNCTION("""COMPUTED_VALUE"""),"-") -> - | I92: =IFERROR(__xludf.DUMMYFUNCTION("""COMPUTED_VALUE"""),"-") -> - | J92: =IFERROR(__xludf.DUMMYFUNCTION("""COMPUTED_VALUE"""),"6,28") -> 6,28 | K92: =IFERROR(__xludf.DUMMYFUNCTION("""COMPUTED_VALUE"""),"6,28") -> 6,28 | L92: =IFERROR(__xludf.DUMMYFUNCTION("""COMPUTED_VALUE"""),"6,28") -> 6,28 | M92: =IFERROR(__xludf.DUMMYFUNCTION("""COMPUTED_VALUE"""),"6,22") -> 6,22 | N92: =IFERROR(__xludf.DUMMYFUNCTION("""COMPUTED_VALUE"""),678.0) -> 678
A93: DIA | B93: =SUBSTITUTE(SUBSTITUTE(SUBSTITUTE(D93, ".", "\\"), ",", "."), "\\", ",") -> 11,270.00 | C93: =IFERROR(__xludf.DUMMYFUNCTION("""COMPUTED_VALUE"""),"* BKR * Cedear Baker Hu...") -> * BKR * Cedear Baker Hu... | D93: =IFERROR(__xludf.DUMMYFUNCTION("""COMPUTED_VALUE"""),"11.270,00") -> 11.270,00 | E93: =IFERROR(__xludf.DUMMYFUNCTION("""COMPUTED_VALUE"""),"-4,49%") -> -4,49% | F93: =IFERROR(__xludf.DUMMYFUNCTION("""COMPUTED_VALUE"""),"-") -> - | G93: =IFERROR(__xludf.DUMMYFUNCTION("""COMPUTED_VALUE"""),"-") -> - | H93: =IFERROR(__xludf.DUMMYFUNCTION("""COMPUTED_VALUE"""),"-") -> - | I93: =IFERROR(__xludf.DUMMYFUNCTION("""COMPUTED_VALUE"""),"-") -> - | J93: =IFERROR(__xludf.DUMMYFUNCTION("""COMPUTED_VALUE"""),"11.800,00") -> 11.800,00 | K93: =IFERROR(__xludf.DUMMYFUNCTION("""COMPUTED_VALUE"""),"11.250,00") -> 11.250,00 | L93: =IFERROR(__xludf.DUMMYFUNCTION("""COMPUTED_VALUE"""),"11.800,00") -> 11.800,00 | M93: =IFERROR(__xludf.DUMMYFUNCTION("""COMPUTED_VALUE"""),"11.270,00") -> 11.270,00 | N93: =IFERROR(__xludf.DUMMYFUNCTION("""COMPUTED_VALUE"""),93.32) -> 93.32
A94: DIAD | B94: =SUBSTITUTE(SUBSTITUTE(SUBSTITUTE(D94, ".", "\\"), ",", "."), "\\", ",") -> 28,960.00 | C94: =IFERROR(__xludf.DUMMYFUNCTION("""COMPUTED_VALUE"""),"* BMY * Cedear Bristol-...") -> * BMY * Cedear Bristol-... | D94: =IFERROR(__xludf.DUMMYFUNCTION("""COMPUTED_VALUE"""),"28.960,00") -> 28.960,00 | E94: =IFERROR(__xludf.DUMMYFUNCTION("""COMPUTED_VALUE"""),"0,41%") -> 0,41% | F94: =IFERROR(__xludf.DUMMYFUNCTION("""COMPUTED_VALUE"""),"-") -> - | G94: =IFERROR(__xludf.DUMMYFUNCTION("""COMPUTED_VALUE"""),"-") -> - | H94: =IFERROR(__xludf.DUMMYFUNCTION("""COMPUTED_VALUE"""),"-") -> - | I94: =IFERROR(__xludf.DUMMYFUNCTION("""COMPUTED_VALUE"""),"-") -> - | J94: =IFERROR(__xludf.DUMMYFUNCTION("""COMPUTED_VALUE"""),"28.700,00") -> 28.700,00 | K94: =IFERROR(__xludf.DUMMYFUNCTION("""COMPUTED_VALUE"""),"28.500,00") -> 28.500,00 | L94: =IFERROR(__xludf.DUMMYFUNCTION("""COMPUTED_VALUE"""),"28.960,00") -> 28.960,00 | M94: =IFERROR(__xludf.DUMMYFUNCTION("""COMPUTED_VALUE"""),"28.960,00") -> 28.960,00 | N94: =IFERROR(__xludf.DUMMYFUNCTION("""COMPUTED_VALUE"""),"16.113.920") -> 16.113.920
A95: =MID(C95, FIND("* ", C95) + 2, FIND(" *", C95, FIND("* ", C95) + 2) - FIND("* ", C95) - 2) -> BMYD | B95: =SUBSTITUTE(SUBSTITUTE(SUBSTITUTE(D95, ".", "\\"), ",", "."), "\\", ",") -> 20.47 | C95: =IFERROR(__xludf.DUMMYFUNCTION("""COMPUTED_VALUE"""),"* BMYD * Cedear Bristol ...") -> * BMYD * Cedear Bristol ... | D95: =IFERROR(__xludf.DUMMYFUNCTION("""COMPUTED_VALUE"""),"20,47") -> 20,47 | E95: =IFERROR(__xludf.DUMMYFUNCTION("""COMPUTED_VALUE"""),0.0) -> 0 | F95: =IFERROR(__xludf.DUMMYFUNCTION("""COMPUTED_VALUE"""),"-") -> - | G95: =IFERROR(__xludf.DUMMYFUNCTION("""COMPUTED_VALUE"""),"-") -> - | H95: =IFERROR(__xludf.DUMMYFUNCTION("""COMPUTED_VALUE"""),"-") -> - | I95: =IFERROR(__xludf.DUMMYFUNCTION("""COMPUTED_VALUE"""),"-") -> - | J95: =IFERROR(__xludf.DUMMYFUNCTION("""COMPUTED_VALUE"""),"20,47") -> 20,47 | K95: =IFERROR(__xludf.DUMMYFUNCTION("""COMPUTED_VALUE"""),"0,00") -> 0,00 | L95: =IFERROR(__xludf.DUMMYFUNCTION("""COMPUTED_VALUE"""),"0,00") -> 0,00 | M95: =IFERROR(__xludf.DUMMYFUNCTION("""COMPUTED_VALUE"""),"20,47") -> 20,47 | N95: =IFERROR(__xludf.DUMMYFUNCTION("""COMPUTED_VALUE"""),0.0) -> 0
A96: =MID(C96, FIND("* ", C96) + 2, FIND(" *", C96, FIND("* ", C96) + 2) - FIND("* ", C96) - 2) -> BNG | B96: =SUBSTITUTE(SUBSTITUTE(SUBSTITUTE(D96, ".", "\\"), ",", "."), "\\", ",") -> 36,780.00 | C96: =IFERROR(__xludf.DUMMYFUNCTION("""COMPUTED_VALUE"""),"* BNG * Cedear Bunge Li...") -> * BNG * Cedear Bunge Li... | D96: =IFERROR(__xludf.DUMMYFUNCTION("""COMPUTED_VALUE"""),"36.780,00") -> 36.780,00 | E96: =IFERROR(__xludf.DUMMYFUNCTION("""COMPUTED_VALUE"""),"0,43%") -> 0,43% | F96: =IFERROR(__xludf.DUMMYFUNCTION("""COMPUTED_VALUE"""),"-") -> - | G96: =IFERROR(__xludf.DUMMYFUNCTION("""COMPUTED_VALUE"""),"-") -> - | H96: =IFERROR(__xludf.DUMMYFUNCTION("""COMPUTED_VALUE"""),"-") -> - | I96: =IFERROR(__xludf.DUMMYFUNCTION("""COMPUTED_VALUE"""),"-") -> - | J96: =IFERROR(__xludf.DUMMYFUNCTION("""COMPUTED_VALUE"""),"36.860,00") -> 36.860,00 | K96: =IFERROR(__xludf.DUMMYFUNCTION("""COMPUTED_VALUE"""),"36.420,00") -> 36.420,00 | L96: =IFERROR(__xludf.DUMMYFUNCTION("""COMPUTED_VALUE"""),"37.100,00") -> 37.100,00 | M96: =IFERROR(__xludf.DUMMYFUNCTION("""COMPUTED_VALUE"""),"36.780,00") -> 36.780,00 | N96: =IFERROR(__xludf.DUMMYFUNCTION("""COMPUTED_VALUE"""),"40.549.040") -> 40.549.040
A97: =MID(C97, FIND("* ", C97) + 2, FIND(" *", C97, FIND("* ", C97) + 2) - FIND("* ", C97) - 2) -> BP | B97: =SUBSTITUTE(SUBSTITUTE(SUBSTITUTE(D97, ".", "\\"), ",", "."), "\\", ",") -> 12,500.00 | C97: =IFERROR(__xludf.DUMMYFUNCTION("""COMPUTED_VALUE"""),"* BP * Cedear Bp P.L.C.") -> * BP * Cedear Bp P.L.C. | D97: =IFERROR(__xludf.DUMMYFUNCTION("""COMPUTED_VALUE"""),"12.500,00") -> 12.500,00 | E97: =IFERROR(__xludf.DUMMYFUNCTION("""COMPUTED_VALUE"""),"1,95%") -> 1,95% | F97: =IFERROR(__xludf.DUMMYFUNCTION("""COMPUTED_VALUE"""),"-") -> - | G97: =IFERROR(__xludf.DUMMYFUNCTION("""COMPUTED_VALUE"""),"-") -> - | H97: =IFERROR(__xludf.DUMMYFUNCTION("""COMPUTED_VALUE"""),"-") -> - | I97: =IFERROR(__xludf.DUMMYFUNCTION("""COMPUTED_VALUE"""),"-") -> - | J97: =IFERROR(__xludf.DUMMYFUNCTION("""COMPUTED_VALUE"""),"12.320,00") -> 12.320,00 | K97: =IFERROR(__xludf.DUMMYFUNCTION("""COMPUTED_VALUE"""),"12.280,00") -> 12.280,00 | L97: =IFERROR(__xludf.DUMMYFUNCTION("""COMPUTED_VALUE"""),"12.580,00") -> 12.580,00 | M97: =IFERROR(__xludf.DUMMYFUNCTION("""COMPUTED_VALUE"""),"12.500,00") -> 12.500,00 | N97: =IFERROR(__xludf.DUMMYFUNCTION("""COMPUTED_VALUE"""),"21.037.860") -> 21.037.860
A98: =MID(C98, FIND("* ", C98) + 2, FIND(" *", C98, FIND("* ", C98) + 2) - FIND("* ", C98) - 2) -> BPD | B98: =SUBSTITUTE(SUBSTITUTE(SUBSTITUTE(D98, ".", "\\"), ",", "."), "\\", ",") -> 8.80 | C98: =IFERROR(__xludf.DUMMYFUNCTION("""COMPUTED_VALUE"""),"* BPD * Cedear Bp P.L.C.") -> * BPD * Cedear Bp P.L.C. | D98: =IFERROR(__xludf.DUMMYFUNCTION("""COMPUTED_VALUE"""),"8,80") -> 8,80 | E98: =IFERROR(__xludf.DUMMYFUNCTION("""COMPUTED_VALUE"""),"1,14%") -> 1,14% | F98: =IFERROR(__xludf.DUMMYFUNCTION("""COMPUTED_VALUE"""),"-") -> - | G98: =IFERROR(__xludf.DUMMYFUNCTION("""COMPUTED_VALUE"""),"-") -> - | H98: =IFERROR(__xludf.DUMMYFUNCTION("""COMPUTED_VALUE"""),"-") -> - | I98: =IFERROR(__xludf.DUMMYFUNCTION("""COMPUTED_VALUE"""),"-") -> - | J98: =IFERROR(__xludf.DUMMYFUNCTION("""COMPUTED_VALUE"""),"8,36") -> 8,36 | K98: =IFERROR(__xludf.DUMMYFUNCTION("""COMPUTED_VALUE"""),"8,36") -> 8,36 | L98: =IFERROR(__xludf.DUMMYFUNCTION("""COMPUTED_VALUE"""),"8,80") -> 8,80 | M98: =IFERROR(__xludf.DUMMYFUNCTION("""COMPUTED_VALUE"""),"8,70") -> 8,70 | N98: =IFERROR(__xludf.DUMMYFUNCTION("""COMPUTED_VALUE"""),5.832) -> 5.832
A99: =MID(C99, FIND("* ", C99) + 2, FIND(" *", C99, FIND("* ", C99) + 2) - FIND("* ", C99) - 2) -> BRKB | B99: =SUBSTITUTE(SUBSTITUTE(SUBSTITUTE(D99, ".", "\\"), ",", "."), "\\", ",") -> 32,800.00 | C99: =IFERROR(__xludf.DUMMYFUNCTION("""COMPUTED_VALUE"""),"* BRKB * Cedear Berkshir...") -> * BRKB * Cedear Berkshir... | D99: =IFERROR(__xludf.DUMMYFUNCTION("""COMPUTED_VALUE"""),"32.800,00") -> 32.800,00 | E99: =IFERROR(__xludf.DUMMYFUNCTION("""COMPUTED_VALUE"""),"0,79%") -> 0,79% | F99: =IFERROR(__xludf.DUMMYFUNCTION("""COMPUTED_VALUE"""),"-") -> - | G99: =IFERROR(__xludf.DUMMYFUNCTION("""COMPUTED_VALUE"""),"-") -> - | H99: =IFERROR(__xludf.DUMMYFUNCTION("""COMPUTED_VALUE"""),"-") -> - | I99: =IFERROR(__xludf.DUMMYFUNCTION("""COMPUTED_VALUE"""),"-") -> - | J99: =IFERROR(__xludf.DUMMYFUNCTION("""COMPUTED_VALUE"""),"32.680,00") -> 32.680,00 | K99: =IFERROR(__xludf.DUMMYFUNCTION("""COMPUTED_VALUE"""),"32.360,00") -> 32.360,00 | L99: =IFERROR(__xludf.DUMMYFUNCTION("""COMPUTED_VALUE"""),"32.880,00") -> 32.880,00 | M99: =IFERROR(__xludf.DUMMYFUNCTION("""COMPUTED_VALUE"""),"32.800,00") -> 32.800,00 | N99: =IFERROR(__xludf.DUMMYFUNCTION("""COMPUTED_VALUE"""),"1.115.756.020") -> 1.115.756.020
A100: =MID(C100, FIND("* ", C100) + 2, FIND(" *", C100, FIND("* ", C100) + 2) - FIND("* ", C100) - 2) -> BRKBC | B100: =SUBSTITUTE(SUBSTITUTE(SUBSTITUTE(D100, ".", "\\"), ",", "."), "\\", ",") -> 22.34 | C100: =IFERROR(__xludf.DUMMYFUNCTION("""COMPUTED_VALUE"""),"* BRKBC * Cedear Berkshir...") -> * BRKBC * Cedear Berkshir... | D100: =IFERROR(__xludf.DUMMYFUNCTION("""COMPUTED_VALUE"""),"22,34") -> 22,34 | E100: =IFERROR(__xludf.DUMMYFUNCTION("""COMPUTED_VALUE"""),"-0,44%") -> -0,44% | F100: =IFERROR(__xludf.DUMMYFUNCTION("""COMPUTED_VALUE"""),"-") -> - | G100: =IFERROR(__xludf.DUMMYFUNCTION("""COMPUTED_VALUE"""),"-") -> - | H100: =IFERROR(__xludf.DUMMYFUNCTION("""COMPUTED_VALUE"""),"-") -> - | I100: =IFERROR(__xludf.DUMMYFUNCTION("""COMPUTED_VALUE"""),"-") -> - | J100: =IFERROR(__xludf.DUMMYFUNCTION("""COMPUTED_VALUE"""),"22,45") -> 22,45 | K100: =IFERROR(__xludf.DUMMYFUNCTION("""COMPUTED_VALUE"""),"22,30") -> 22,30 | L100: =IFERROR(__xludf.DUMMYFUNCTION("""COMPUTED_VALUE"""),"22,45") -> 22,45 | M100: =IFERROR(__xludf.DUMMYFUNCTION("""COMPUTED_VALUE"""),"22,34") -> 22,34 | N100: =IFERROR(__xludf.DUMMYFUNCTION("""COMPUTED_VALUE"""),492.0) -> 492
...
